Workbook
Name DateDeath: 'Loyd List 1-190 - Edit'!$C$1:$O$184
Name Generation: 'Loyd List 1-190 - Edit'!$A$1:$B$184
Name Loydname: 'Loyd List 1-190 - Edit'!$C$1:$Q$184
Name namewithfather: 'Loyd List 1-190 - Edit'!$P$1:$R$184

Sheet Data check lookup table
A1: Loyd # | F1: Contacting responsibility | H1: From meeting Domininc, Jeremy & Rick
A2: 1 | B2: =COUNTIF('Loyd List 1-190 - Edit'!$R$3:$R$184,'Data check lookup table'!A2) -> 7 | D2: =COUNTIF(B2:B173,">0") -> 1 | G2: Loyd ## | H2: Name | I2: Father's Loyd # | J2: Father's Name | K2: GParent # | L2: GParent Name | M2: 2000 Address | N2: Age - Current | O2: Number of Kids in 2000 | P2: Establishing Contact | Q2: Landline | R2: Mobile | S2: Email | T2: Postal Address in 2021 | U2: Comments
A3: =#REF!+1 -> #REF! | B3: =COUNTIF('Loyd List 1-190 - Edit'!$R$3:$R$184,'Data check lookup table'!A3) -> 0 | G3: 109 | H3: =VLOOKUP(G3,namewithfather,2,FALSE) -> Margaret (109): 1932– | I3: =VLOOKUP(G3,namewithfather,3,FALSE) -> 80 | J3: =VLOOKUP(I3,namewithfather,2,FALSE) -> Eric (80): 1894–1963 | K3: =VLOOKUP(I3,namewithfather,3,FALSE) -> 29 | L3: =VLOOKUP(K3,namewithfather,2,FALSE) -> Arthur (29): 1845–1930 | M3: =VLOOKUP(G3,'Loyd List 1-190 - Edit'!$P$3:$AN$184,25,FALSE) -> 1 | N3: =VLOOKUP(G3,'Loyd List 1-190 - Edit'!$P$3:$AGI$184,26,FALSE) -> 90 | O3: =VLOOKUP(G3,'Loyd List 1-190 - Edit'!$P$3:$AM$184,22,FALSE) -> 3 | P3: Jeremy | S3: mantlehill@aol.com | V3: mantlehill@aol.com
A4: =A3+1 -> #REF! | B4: =COUNTIF('Loyd List 1-190 - Edit'!$R$3:$R$184,'Data check lookup table'!A4) -> 0 | G4: 110 | H4: =VLOOKUP(G4,namewithfather,2,FALSE) -> Jean (110): 1933– | I4: =VLOOKUP(G4,namewithfather,3,FALSE) -> 80 | J4: =VLOOKUP(I4,namewithfather,2,FALSE) -> Eric (80): 1894–1963 | K4: =VLOOKUP(I4,namewithfather,3,FALSE) -> 29 | L4: =VLOOKUP(K4,namewithfather,2,FALSE) -> Arthur (29): 1845–1930 | M4: =VLOOKUP(G4,'Loyd List 1-190 - Edit'!$P$3:$AN$184,25,FALSE) -> 1 | N4: =VLOOKUP(G4,'Loyd List 1-190 - Edit'!$P$3:$AGI$184,26,FALSE) -> 88 | O4: =VLOOKUP(G4,'Loyd List 1-190 - Edit'!$P$3:$AM$184,22,FALSE) -> 8 | P4: Jeremy | S4: mantlehill@aol.com | V4: mantlehill@aol.com
A5: =A4+1 -> #REF! | B5: =COUNTIF('Loyd List 1-190 - Edit'!$R$3:$R$184,'Data check lookup table'!A5) -> 0 | G5: 114 | H5: =VLOOKUP(G5,namewithfather,2,FALSE) -> Michael (114): 1938– | I5: =VLOOKUP(G5,namewithfather,3,FALSE) -> 80 | J5: =VLOOKUP(I5,namewithfather,2,FALSE) -> Eric (80): 1894–1963 | K5: =VLOOKUP(I5,namewithfather,3,FALSE) -> 29 | L5: =VLOOKUP(K5,namewithfather,2,FALSE) -> Arthur (29): 1845–1930 | M5: =VLOOKUP(G5,'Loyd List 1-190 - Edit'!$P$3:$AN$184,25,FALSE) -> 1 | N5: =VLOOKUP(G5,'Loyd List 1-190 - Edit'!$P$3:$AGI$184,26,FALSE) -> 83 | O5: =VLOOKUP(G5,'Loyd List 1-190 - Edit'!$P$3:$AM$184,22,FALSE) -> 8 | P5: Jeremy | S5: loydthreepwood@gmail.com | V5: loydthreepwood@gmail.com
A6: =A5+1 -> #REF! | B6: =COUNTIF('Loyd List 1-190 - Edit'!$R$3:$R$184,'Data check lookup table'!A6) -> 0 | G6: 119 | H6: =VLOOKUP(G6,namewithfather,2,FALSE) -> Peter (119): 1942– | I6: =VLOOKUP(G6,namewithfather,3,FALSE) -> 80 | J6: =VLOOKUP(I6,namewithfather,2,FALSE) -> Eric (80): 1894–1963 | K6: =VLOOKUP(I6,namewithfather,3,FALSE) -> 29 | L6: =VLOOKUP(K6,namewithfather,2,FALSE) -> Arthur (29): 1845–1930 | M6: =VLOOKUP(G6,'Loyd List 1-190 - Edit'!$P$3:$AN$184,25,FALSE) -> 1 | N6: =VLOOKUP(G6,'Loyd List 1-190 - Edit'!$P$3:$AGI$184,26,FALSE) -> 79 | O6: =VLOOKUP(G6,'Loyd List 1-190 - Edit'!$P$3:$AM$184,22,FALSE) -> 9 | P6: Jeremy | S6: mantlehill@aol.com | V6: mantlehill@aol.com
A7: =A6+1 -> #REF! | B7: =COUNTIF('Loyd List 1-190 - Edit'!$R$3:$R$184,'Data check lookup table'!A7) -> 0 | G7: 102 | H7: =VLOOKUP(G7,namewithfather,2,FALSE) -> Zelda (102): 1923–2014 | I7: =VLOOKUP(G7,namewithfather,3,FALSE) -> 62 | J7: =VLOOKUP(I7,namewithfather,2,FALSE) -> Bobby (62): 1887–1977 | K7: =VLOOKUP(I7,namewithfather,3,FALSE) -> 30 | L7: =VLOOKUP(K7,namewithfather,2,FALSE) -> Archie (30): 1847–1922 | M7: =VLOOKUP(G7,'Loyd List 1-190 - Edit'!$P$3:$AN$184,25,FALSE) -> 30 | N7: =VLOOKUP(G7,'Loyd List 1-190 - Edit'!$P$3:$AGI$184,26,FALSE) -> 90 | O7: =VLOOKUP(G7,'Loyd List 1-190 - Edit'!$P$3:$AM$184,22,FALSE) -> 5 | P7: Jeremy | S7: tessdunlop@gmail.com; celinadunlop@btinternet.com
A8: =A7+1 -> #REF! | B8: =COUNTIF('Loyd List 1-190 - Edit'!$R$3:$R$184,'Data check lookup table'!A8) -> 0 | G8: 98 | H8: =VLOOKUP(G8,namewithfather,2,FALSE) -> Peter (98): 1922–2022 | I8: =VLOOKUP(G8,namewithfather,3,FALSE) -> 77 | J8: =VLOOKUP(I8,namewithfather,2,FALSE) -> Wilfrid (77): 1893–1971 | K8: =VLOOKUP(I8,namewithfather,3,FALSE) -> 30 | L8: =VLOOKUP(K8,namewithfather,2,FALSE) -> Archie (30): 1847–1922 | M8: =VLOOKUP(G8,'Loyd List 1-190 - Edit'!$P$3:$AN$184,25,FALSE) -> 13 | N8: =VLOOKUP(G8,'Loyd List 1-190 - Edit'!$P$3:$AGI$184,26,FALSE) -> 99 | O8: =VLOOKUP(G8,'Loyd List 1-190 - Edit'!$P$3:$AM$184,22,FALSE) -> 8 | P8: Jeremy | S8: rosemaryloyd@gmail.com | V8: rosemaryloyd@gmail.com
A9: =A8+1 -> #REF! | B9: =COUNTIF('Loyd List 1-190 - Edit'!$R$3:$R$184,'Data check lookup table'!A9) -> 0 | G9: 106 | H9: =VLOOKUP(G9,namewithfather,2,FALSE) -> Denise (106): 1928– | I9: =VLOOKUP(G9,namewithfather,3,FALSE) -> 77 | J9: =VLOOKUP(I9,namewithfather,2,FALSE) -> Wilfrid (77): 1893–1971 | K9: =VLOOKUP(I9,namewithfather,3,FALSE) -> 30 | L9: =VLOOKUP(K9,namewithfather,2,FALSE) -> Archie (30): 1847–1922 | M9: =VLOOKUP(G9,'Loyd List 1-190 - Edit'!$P$3:$AN$184,25,FALSE) -> 1 | N9: =VLOOKUP(G9,'Loyd List 1-190 - Edit'!$P$3:$AGI$184,26,FALSE) -> 93 | O9: =VLOOKUP(G9,'Loyd List 1-190 - Edit'!$P$3:$AM$184,22,FALSE) -> 11 | P9: Jeremy | S9: rosemaryloyd@gmail.com | V9: rosemaryloyd@gmail.com
A10: =#REF!+1 -> #REF! | B10: =COUNTIF('Loyd List 1-190 - Edit'!$R$3:$R$184,'Data check lookup table'!A10) -> 0 | G10: 116 | H10: =VLOOKUP(G10,namewithfather,2,FALSE) -> Peggy (116): 1939– | I10: =VLOOKUP(G10,namewithfather,3,FALSE) -> 55 | J10: =VLOOKUP(I10,namewithfather,2,FALSE) -> Dick (55): 1882–1950 | K10: =VLOOKUP(I10,namewithfather,3,FALSE) -> 35 | L10: =VLOOKUP(K10,namewithfather,2,FALSE) -> Lewis (35): 1852–1908 | M10: =VLOOKUP(G10,'Loyd List 1-190 - Edit'!$P$3:$AN$184,25,FALSE) -> 1 | N10: =VLOOKUP(G10,'Loyd List 1-190 - Edit'!$P$3:$AGI$184,26,FALSE) -> 82 | O10: =VLOOKUP(G10,'Loyd List 1-190 - Edit'!$P$3:$AM$184,22,FALSE) -> 11 | P10: Jeremy | S10: patrickloyd@cwgsy.net | V10: patrickloyd@cwgsy.net
A11: =A10+1 -> #REF! | B11: =COUNTIF('Loyd List 1-190 - Edit'!$R$3:$R$184,'Data check lookup table'!A11) -> 0 | G11: 117 | H11: =VLOOKUP(G11,namewithfather,2,FALSE) -> Patrick (117): 1942– | I11: =VLOOKUP(G11,namewithfather,3,FALSE) -> 55 | J11: =VLOOKUP(I11,namewithfather,2,FALSE) -> Dick (55): 1882–1950 | K11: =VLOOKUP(I11,namewithfather,3,FALSE) -> 35 | L11: =VLOOKUP(K11,namewithfather,2,FALSE) -> Lewis (35): 1852–1908 | M11: =VLOOKUP(G11,'Loyd List 1-190 - Edit'!$P$3:$AN$184,25,FALSE) -> 1 | N11: =VLOOKUP(G11,'Loyd List 1-190 - Edit'!$P$3:$AGI$184,26,FALSE) -> 80 | O11: =VLOOKUP(G11,'Loyd List 1-190 - Edit'!$P$3:$AM$184,22,FALSE) -> 3 | P11: Jeremy | S11: patrickloyd@cwgsy.net | V11: patrickloyd@cwgsy.net
A12: =A11+1 -> #REF! | B12: =COUNTIF('Loyd List 1-190 - Edit'!$R$3:$R$184,'Data check lookup table'!A12) -> 0 | G12: 97 | H12: =VLOOKUP(G12,namewithfather,2,FALSE) -> Audrey (97): 1922–2005 | I12: =VLOOKUP(G12,namewithfather,3,FALSE) -> 53 | J12: =VLOOKUP(I12,namewithfather,2,FALSE) -> Edward (53): 1881–1962 | K12: =VLOOKUP(I12,namewithfather,3,FALSE) -> 41 | L12: =VLOOKUP(K12,namewithfather,2,FALSE) -> Frederic (41): 1856–1936 | M12: =VLOOKUP(G12,'Loyd List 1-190 - Edit'!$P$3:$AN$184,25,FALSE) -> 4 | N12: =VLOOKUP(G12,'Loyd List 1-190 - Edit'!$P$3:$AGI$184,26,FALSE) -> 83 | O12: =VLOOKUP(G12,'Loyd List 1-190 - Edit'!$P$3:$AM$184,22,FALSE) -> 4 | P12: Rick | S12: Deceased
A13: =#REF!+1 -> #REF! | B13: =COUNTIF('Loyd List 1-190 - Edit'!$R$3:$R$184,'Data check lookup table'!A13) -> 0 | G13: 127 | H13: =VLOOKUP(G13,namewithfather,2,FALSE) -> Vivian (127): 1951– | I13: =VLOOKUP(G13,namewithfather,3,FALSE) -> 78 | J13: =VLOOKUP(I13,namewithfather,2,FALSE) -> Vivian (78): 1894–1972 | K13: =VLOOKUP(I13,namewithfather,3,FALSE) -> 46 | L13: =VLOOKUP(K13,namewithfather,2,FALSE) -> William (46): 1863–1923 | M13: =VLOOKUP(G13,'Loyd List 1-190 - Edit'!$P$3:$AN$184,25,FALSE) -> 1 | N13: =VLOOKUP(G13,'Loyd List 1-190 - Edit'!$P$3:$AGI$184,26,FALSE) -> 70 | O13: =VLOOKUP(G13,'Loyd List 1-190 - Edit'!$P$3:$AM$184,22,FALSE) -> 11 | P13: Dominic | S13: victoryyardiow@gmail.com | V13: victoryyardiow@gmail.com
A14: =A13+1 -> #REF! | B14: =COUNTIF('Loyd List 1-190 - Edit'!$R$3:$R$184,'Data check lookup table'!A14) -> 0 | G14: 140 | H14: =VLOOKUP(G14,namewithfather,2,FALSE) -> Ginie (140): 1961– | I14: =VLOOKUP(G14,namewithfather,3,FALSE) -> 78 | J14: =VLOOKUP(I14,namewithfather,2,FALSE) -> Vivian (78): 1894–1972 | K14: =VLOOKUP(I14,namewithfather,3,FALSE) -> 46 | L14: =VLOOKUP(K14,namewithfather,2,FALSE) -> William (46): 1863–1923 | M14: =VLOOKUP(G14,'Loyd List 1-190 - Edit'!$P$3:$AN$184,25,FALSE) -> 1 | N14: =VLOOKUP(G14,'Loyd List 1-190 - Edit'!$P$3:$AGI$184,26,FALSE) -> 60 | O14: =VLOOKUP(G14,'Loyd List 1-190 - Edit'!$P$3:$AM$184,22,FALSE) -> 8 | P14: Dominic | S14: cherrytreefarms@gmail.com | V14: cherrytreefarms@gmail.com
A15: =A14+1 -> #REF! | B15: =COUNTIF('Loyd List 1-190 - Edit'!$R$3:$R$184,'Data check lookup table'!A15) -> 0 | G15: 123 | H15: =VLOOKUP(G15,namewithfather,2,FALSE) -> Janet (123): 1949– | I15: =VLOOKUP(G15,namewithfather,3,FALSE) -> 89 | J15: =VLOOKUP(I15,namewithfather,2,FALSE) -> Sir Francis/Frank (89): 1916–2006 | K15: =VLOOKUP(I15,namewithfather,3,FALSE) -> 54 | L15: =VLOOKUP(K15,namewithfather,2,FALSE) -> Alfred (54): 1882–1919 | M15: =VLOOKUP(G15,'Loyd List 1-190 - Edit'!$P$3:$AN$184,25,FALSE) -> 1 | N15: =VLOOKUP(G15,'Loyd List 1-190 - Edit'!$P$3:$AGI$184,26,FALSE) -> 73 | O15: =VLOOKUP(G15,'Loyd List 1-190 - Edit'!$P$3:$AM$184,22,FALSE) -> 5 | P15: Dominic | S15: janetbosman@icloud.com | V15: janetbosman@icloud.com
A16: =A15+1 -> #REF! | B16: =COUNTIF('Loyd List 1-190 - Edit'!$R$3:$R$184,'Data check lookup table'!A16) -> 0 | G16: 129 | H16: =VLOOKUP(G16,namewithfather,2,FALSE) -> Diana (129): 1952– | I16: =VLOOKUP(G16,namewithfather,3,FALSE) -> 89 | J16: =VLOOKUP(I16,namewithfather,2,FALSE) -> Sir Francis/Frank (89): 1916–2006 | K16: =VLOOKUP(I16,namewithfather,3,FALSE) -> 54 | L16: =VLOOKUP(K16,namewithfather,2,FALSE) -> Alfred (54): 1882–1919 | M16: =VLOOKUP(G16,'Loyd List 1-190 - Edit'!$P$3:$AN$184,25,FALSE) -> 1 | N16: =VLOOKUP(G16,'Loyd List 1-190 - Edit'!$P$3:$AGI$184,26,FALSE) -> 70 | O16: =VLOOKUP(G16,'Loyd List 1-190 - Edit'!$P$3:$AM$184,22,FALSE) -> 5 | P16: Dominic | S16: dmsako@shaw.ca | V16: dmsako@shaw.ca
A17: =A16+1 -> #REF! | B17: =COUNTIF('Loyd List 1-190 - Edit'!$R$3:$R$184,'Data check lookup table'!A17) -> 0 | G17: 147 | H17: =VLOOKUP(G17,namewithfather,2,FALSE) -> Susannah (147): 1965– | I17: =VLOOKUP(G17,namewithfather,3,FALSE) -> 117 | J17: =VLOOKUP(I17,namewithfather,2,FALSE) -> Patrick (117): 1942– | K17: =VLOOKUP(I17,namewithfather,3,FALSE) -> 55 | L17: =VLOOKUP(K17,namewithfather,2,FALSE) -> Dick (55): 1882–1950 | M17: =VLOOKUP(G17,'Loyd List 1-190 - Edit'!$P$3:$AN$184,25,FALSE) -> 1 | N17: =VLOOKUP(G17,'Loyd List 1-190 - Edit'!$P$3:$AGI$184,26,FALSE) -> 56 | O17: =VLOOKUP(G17,'Loyd List 1-190 - Edit'!$P$3:$AM$184,22,FALSE) -> 9 | P17: Jeremy | S17: patrickloyd@cwgsy.net | V17: patrickloyd@cwgsy.net
A18: =A17+1 -> #REF! | B18: =COUNTIF('Loyd List 1-190 - Edit'!$R$3:$R$184,'Data check lookup table'!A18) -> 0 | G18: 151 | H18: =VLOOKUP(G18,namewithfather,2,FALSE) -> Elspeth (151): 1967– | I18: =VLOOKUP(G18,namewithfather,3,FALSE) -> 117 | J18: =VLOOKUP(I18,namewithfather,2,FALSE) -> Patrick (117): 1942– | K18: =VLOOKUP(I18,namewithfather,3,FALSE) -> 55 | L18: =VLOOKUP(K18,namewithfather,2,FALSE) -> Dick (55): 1882–1950 | M18: =VLOOKUP(G18,'Loyd List 1-190 - Edit'!$P$3:$AN$184,25,FALSE) -> 1 | N18: =VLOOKUP(G18,'Loyd List 1-190 - Edit'!$P$3:$AGI$184,26,FALSE) -> 55 | O18: =VLOOKUP(G18,'Loyd List 1-190 - Edit'!$P$3:$AM$184,22,FALSE) -> 5 | P18: Jeremy | S18: patrickloyd@cwgsy.net | V18: patrickloyd@cwgsy.net
A19: =A18+1 -> #REF! | B19: =COUNTIF('Loyd List 1-190 - Edit'!$R$3:$R$184,'Data check lookup table'!A19) -> 0 | G19: 153 | H19: =VLOOKUP(G19,namewithfather,2,FALSE) -> Richard (153): 1968– | I19: =VLOOKUP(G19,namewithfather,3,FALSE) -> 117 | J19: =VLOOKUP(I19,namewithfather,2,FALSE) -> Patrick (117): 1942– | K19: =VLOOKUP(I19,namewithfather,3,FALSE) -> 55 | L19: =VLOOKUP(K19,namewithfather,2,FALSE) -> Dick (55): 1882–1950 | M19: =VLOOKUP(G19,'Loyd List 1-190 - Edit'!$P$3:$AN$184,25,FALSE) -> 1 | N19: =VLOOKUP(G19,'Loyd List 1-190 - Edit'!$P$3:$AGI$184,26,FALSE) -> 54 | O19: =VLOOKUP(G19,'Loyd List 1-190 - Edit'!$P$3:$AM$184,22,FALSE) -> 6 | P19: Jeremy | S19: patrickloyd@cwgsy.net | V19: patrickloyd@cwgsy.net
A20: =A19+1 -> #REF! | B20: =COUNTIF('Loyd List 1-190 - Edit'!$R$3:$R$184,'Data check lookup table'!A20) -> 0 | G20: 138 | H20: =VLOOKUP(G20,namewithfather,2,FALSE) -> Thomas (138): 1959– | I20: =VLOOKUP(G20,namewithfather,3,FALSE) -> 100 | J20: =VLOOKUP(I20,namewithfather,2,FALSE) -> Christopher (100): 1923–2013 | K20: =VLOOKUP(I20,namewithfather,3,FALSE) -> 56 | L20: =VLOOKUP(K20,namewithfather,2,FALSE) -> Tommy (56): 1882–1944 | M20: =VLOOKUP(G20,'Loyd List 1-190 - Edit'!$P$3:$AN$184,25,FALSE) -> 1 | N20: =VLOOKUP(G20,'Loyd List 1-190 - Edit'!$P$3:$AGI$184,26,FALSE) -> 63 | O20: =VLOOKUP(G20,'Loyd List 1-190 - Edit'!$P$3:$AM$184,22,FALSE) -> 2 | P20: Jeremy | R20: 07770984123 | S20: tloyd@lockinge-estate.co.uk | U20: 138 | V20: tloyd@lockinge-estate.co.uk
A21: =A20+1 -> #REF! | B21: =COUNTIF('Loyd List 1-190 - Edit'!$R$3:$R$184,'Data check lookup table'!A21) -> 0 | G21: 143 | H21: =VLOOKUP(G21,namewithfather,2,FALSE) -> Harriet (143): 1962– | I21: =VLOOKUP(G21,namewithfather,3,FALSE) -> 100 | J21: =VLOOKUP(I21,namewithfather,2,FALSE) -> Christopher (100): 1923–2013 | K21: =VLOOKUP(I21,namewithfather,3,FALSE) -> 56 | L21: =VLOOKUP(K21,namewithfather,2,FALSE) -> Tommy (56): 1882–1944 | M21: =VLOOKUP(G21,'Loyd List 1-190 - Edit'!$P$3:$AN$184,25,FALSE) -> 1 | N21: =VLOOKUP(G21,'Loyd List 1-190 - Edit'!$P$3:$AGI$184,26,FALSE) -> 60 | O21: =VLOOKUP(G21,'Loyd List 1-190 - Edit'!$P$3:$AM$184,22,FALSE) -> 6 | P21: Jeremy | S21: tloyd@lockinge-estate.co.uk | U21: 138 | V21: tloyd@lockinge-estate.co.uk
A22: =A21+1 -> #REF! | B22: =COUNTIF('Loyd List 1-190 - Edit'!$R$3:$R$184,'Data check lookup table'!A22) -> 0 | G22: 150 | H22: =VLOOKUP(G22,namewithfather,2,FALSE) -> James (150): 1966– | I22: =VLOOKUP(G22,namewithfather,3,FALSE) -> 100 | J22: =VLOOKUP(I22,namewithfather,2,FALSE) -> Christopher (100): 1923–2013 | K22: =VLOOKUP(I22,namewithfather,3,FALSE) -> 56 | L22: =VLOOKUP(K22,namewithfather,2,FALSE) -> Tommy (56): 1882–1944 | M22: =VLOOKUP(G22,'Loyd List 1-190 - Edit'!$P$3:$AN$184,25,FALSE) -> 1 | N22: =VLOOKUP(G22,'Loyd List 1-190 - Edit'!$P$3:$AGI$184,26,FALSE) -> 55 | O22: =VLOOKUP(G22,'Loyd List 1-190 - Edit'!$P$3:$AM$184,22,FALSE) -> 9 | P22: Jeremy | S22: tloyd@lockinge-estate.co.uk | U22: 138 | V22: tloyd@lockinge-estate.co.uk
A23: =A22+1 -> #REF! | B23: =COUNTIF('Loyd List 1-190 - Edit'!$R$3:$R$184,'Data check lookup table'!A23) -> 0 | G23: 120 | H23: =VLOOKUP(G23,namewithfather,2,FALSE) -> Caroline (120): 1947–2022 | I23: =VLOOKUP(G23,namewithfather,3,FALSE) -> 96 | J23: =VLOOKUP(I23,namewithfather,2,FALSE) -> Edward (96): 1921–1977 | K23: =VLOOKUP(I23,namewithfather,3,FALSE) -> 66 | L23: =VLOOKUP(K23,namewithfather,2,FALSE) -> William (66): 1889–1947 | M23: =VLOOKUP(G23,'Loyd List 1-190 - Edit'!$P$3:$AN$184,25,FALSE) -> 13 | N23: =VLOOKUP(G23,'Loyd List 1-190 - Edit'!$P$3:$AGI$184,26,FALSE) -> 75 | O23: =VLOOKUP(G23,'Loyd List 1-190 - Edit'!$P$3:$AM$184,22,FALSE) -> 1 | P23: Dominic | S23: Deceased | V23: david.loyd@hotmail.com
A24: =A23+1 -> #REF! | B24: =COUNTIF('Loyd List 1-190 - Edit'!$R$3:$R$184,'Data check lookup table'!A24) -> 0 | G24: 121 | H24: =VLOOKUP(G24,namewithfather,2,FALSE) -> David (121): 1949– | I24: =VLOOKUP(G24,namewithfather,3,FALSE) -> 96 | J24: =VLOOKUP(I24,namewithfather,2,FALSE) -> Edward (96): 1921–1977 | K24: =VLOOKUP(I24,namewithfather,3,FALSE) -> 66 | L24: =VLOOKUP(K24,namewithfather,2,FALSE) -> William (66): 1889–1947 | M24: =VLOOKUP(G24,'Loyd List 1-190 - Edit'!$P$3:$AN$184,25,FALSE) -> 1 | N24: =VLOOKUP(G24,'Loyd List 1-190 - Edit'!$P$3:$AGI$184,26,FALSE) -> 73 | O24: =VLOOKUP(G24,'Loyd List 1-190 - Edit'!$P$3:$AM$184,22,FALSE) -> 1 | P24: Dominic | S24: david.loyd@hotmail.com | V24: david.loyd@hotmail.com
A25: =A24+1 -> #REF! | B25: =COUNTIF('Loyd List 1-190 - Edit'!$R$3:$R$184,'Data check lookup table'!A25) -> 0 | G25: 137 | H25: =VLOOKUP(G25,namewithfather,2,FALSE) -> Henrietta (137): 1959– | I25: =VLOOKUP(G25,namewithfather,3,FALSE) -> 99 | J25: =VLOOKUP(I25,namewithfather,2,FALSE) -> Peter (99): 1923–1974 | K25: =VLOOKUP(I25,namewithfather,3,FALSE) -> 66 | L25: =VLOOKUP(K25,namewithfather,2,FALSE) -> William (66): 1889–1947 | M25: =VLOOKUP(G25,'Loyd List 1-190 - Edit'!$P$3:$AN$184,25,FALSE) -> 1 | N25: =VLOOKUP(G25,'Loyd List 1-190 - Edit'!$P$3:$AGI$184,26,FALSE) -> 63 | O25: =VLOOKUP(G25,'Loyd List 1-190 - Edit'!$P$3:$AM$184,22,FALSE) -> 1 | P25: Dominic | R25: 07831134130 | S25: henrietta@cazloyd.com | V25: henrietta@cazloyd.com
A26: =A25+1 -> #REF! | B26: =COUNTIF('Loyd List 1-190 - Edit'!$R$3:$R$184,'Data check lookup table'!A26) -> 0 | G26: 144 | H26: =VLOOKUP(G26,namewithfather,2,FALSE) -> Andrew (144): 1962– | I26: =VLOOKUP(G26,namewithfather,3,FALSE) -> 99 | J26: =VLOOKUP(I26,namewithfather,2,FALSE) -> Peter (99): 1923–1974 | K26: =VLOOKUP(I26,namewithfather,3,FALSE) -> 66 | L26: =VLOOKUP(K26,namewithfather,2,FALSE) -> William (66): 1889–1947 | M26: =VLOOKUP(G26,'Loyd List 1-190 - Edit'!$P$3:$AN$184,25,FALSE) -> 1 | N26: =VLOOKUP(G26,'Loyd List 1-190 - Edit'!$P$3:$AGI$184,26,FALSE) -> 59 | O26: =VLOOKUP(G26,'Loyd List 1-190 - Edit'!$P$3:$AM$184,22,FALSE) -> 11 | P26: Dominic | R26: 07715122288 | S26: andrew@ltrcastles.com | V26: andrew@ltrcastles.com
A27: =A26+1 -> #REF! | B27: =COUNTIF('Loyd List 1-190 - Edit'!$R$3:$R$184,'Data check lookup table'!A27) -> 0 | G27: 124 | H27: =VLOOKUP(G27,namewithfather,2,FALSE) -> Rob (124): 1949– | I27: =VLOOKUP(G27,namewithfather,3,FALSE) -> 94 | J27: =VLOOKUP(I27,namewithfather,2,FALSE) -> Alwyne (94): 1920–2014 | K27: =VLOOKUP(I27,namewithfather,3,FALSE) -> 68 | L27: =VLOOKUP(K27,namewithfather,2,FALSE) -> Cecil (68): 1890–1963 | M27: =VLOOKUP(G27,'Loyd List 1-190 - Edit'!$P$3:$AN$184,25,FALSE) -> 1 | N27: =VLOOKUP(G27,'Loyd List 1-190 - Edit'!$P$3:$AGI$184,26,FALSE) -> 72 | O27: =VLOOKUP(G27,'Loyd List 1-190 - Edit'!$P$3:$AM$184,22,FALSE) -> 7 | P27: Dominic | S27: robloyd@icloud.com | V27: justtheonetoo@gmail.com
A28: =A27+1 -> #REF! | B28: =COUNTIF('Loyd List 1-190 - Edit'!$R$3:$R$184,'Data check lookup table'!A28) -> 0 | G28: 126 | H28: =VLOOKUP(G28,namewithfather,2,FALSE) -> Paddy (126): 1951– | I28: =VLOOKUP(G28,namewithfather,3,FALSE) -> 94 | J28: =VLOOKUP(I28,namewithfather,2,FALSE) -> Alwyne (94): 1920–2014 | K28: =VLOOKUP(I28,namewithfather,3,FALSE) -> 68 | L28: =VLOOKUP(K28,namewithfather,2,FALSE) -> Cecil (68): 1890–1963 | M28: =VLOOKUP(G28,'Loyd List 1-190 - Edit'!$P$3:$AN$184,25,FALSE) -> 1 | N28: =VLOOKUP(G28,'Loyd List 1-190 - Edit'!$P$3:$AGI$184,26,FALSE) -> 71 | O28: =VLOOKUP(G28,'Loyd List 1-190 - Edit'!$P$3:$AM$184,22,FALSE) -> 6 | P28: Dominic | S28: paddyloyd@talk21.com | V28: paddyloyd@talk21.com
A29: =A28+1 -> #REF! | B29: =COUNTIF('Loyd List 1-190 - Edit'!$R$3:$R$184,'Data check lookup table'!A29) -> 0 | G29: 131 | H29: =VLOOKUP(G29,namewithfather,2,FALSE) -> Dominic (131): 1953– | I29: =VLOOKUP(G29,namewithfather,3,FALSE) -> 94 | J29: =VLOOKUP(I29,namewithfather,2,FALSE) -> Alwyne (94): 1920–2014 | K29: =VLOOKUP(I29,namewithfather,3,FALSE) -> 68 | L29: =VLOOKUP(K29,namewithfather,2,FALSE) -> Cecil (68): 1890–1963 | M29: =VLOOKUP(G29,'Loyd List 1-190 - Edit'!$P$3:$AN$184,25,FALSE) -> 1 | N29: =VLOOKUP(G29,'Loyd List 1-190 - Edit'!$P$3:$AGI$184,26,FALSE) -> 69 | O29: =VLOOKUP(G29,'Loyd List 1-190 - Edit'!$P$3:$AM$184,22,FALSE) -> 3 | P29: Dominic | S29: dominicloyd@btinternet.com | T29: 126 Princess Anne Road, Boston, Lincolnshire, PE21 9AQ. | V29: dominicloyd@btinternet.com
A30: =A29+1 -> #REF! | B30: =COUNTIF('Loyd List 1-190 - Edit'!$R$3:$R$184,'Data check lookup table'!A30) -> 0 | G30: 136 | H30: =VLOOKUP(G30,namewithfather,2,FALSE) -> Tim (136): 1957– | I30: =VLOOKUP(G30,namewithfather,3,FALSE) -> 94 | J30: =VLOOKUP(I30,namewithfather,2,FALSE) -> Alwyne (94): 1920–2014 | K30: =VLOOKUP(I30,namewithfather,3,FALSE) -> 68 | L30: =VLOOKUP(K30,namewithfather,2,FALSE) -> Cecil (68): 1890–1963 | M30: =VLOOKUP(G30,'Loyd List 1-190 - Edit'!$P$3:$AN$184,25,FALSE) -> 1 | N30: =VLOOKUP(G30,'Loyd List 1-190 - Edit'!$P$3:$AGI$184,26,FALSE) -> 65 | O30: =VLOOKUP(G30,'Loyd List 1-190 - Edit'!$P$3:$AM$184,22,FALSE) -> 6 | P30: Dominic | S30: tim.loyd@btinternet.com | V30: tim.loyd@btinternet.com
A31: =A30+1 -> #REF! | B31: =COUNTIF('Loyd List 1-190 - Edit'!$R$3:$R$184,'Data check lookup table'!A31) -> 0 | G31: 139 | H31: =VLOOKUP(G31,namewithfather,2,FALSE) -> Alex (139): 1959– | I31: =VLOOKUP(G31,namewithfather,3,FALSE) -> 94 | J31: =VLOOKUP(I31,namewithfather,2,FALSE) -> Alwyne (94): 1920–2014 | K31: =VLOOKUP(I31,namewithfather,3,FALSE) -> 68 | L31: =VLOOKUP(K31,namewithfather,2,FALSE) -> Cecil (68): 1890–1963 | M31: =VLOOKUP(G31,'Loyd List 1-190 - Edit'!$P$3:$AN$184,25,FALSE) -> 1 | N31: =VLOOKUP(G31,'Loyd List 1-190 - Edit'!$P$3:$AGI$184,26,FALSE) -> 63 | O31: =VLOOKUP(G31,'Loyd List 1-190 - Edit'!$P$3:$AM$184,22,FALSE) -> 3 | P31: Dominic | S31: abloyd@aol.co.uk | V31: abloyd@aol.co.uk
A32: =A31+1 -> #REF! | B32: =COUNTIF('Loyd List 1-190 - Edit'!$R$3:$R$184,'Data check lookup table'!A32) -> 0 | G32: 142 | H32: =VLOOKUP(G32,namewithfather,2,FALSE) -> Rick (142): 1962– | I32: =VLOOKUP(G32,namewithfather,3,FALSE) -> 94 | J32: =VLOOKUP(I32,namewithfather,2,FALSE) -> Alwyne (94): 1920–2014 | K32: =VLOOKUP(I32,namewithfather,3,FALSE) -> 68 | L32: =VLOOKUP(K32,namewithfather,2,FALSE) -> Cecil (68): 1890–1963 | M32: =VLOOKUP(G32,'Loyd List 1-190 - Edit'!$P$3:$AN$184,25,FALSE) -> 1 | N32: =VLOOKUP(G32,'Loyd List 1-190 - Edit'!$P$3:$AGI$184,26,FALSE) -> 60 | O32: =VLOOKUP(G32,'Loyd List 1-190 - Edit'!$P$3:$AM$184,22,FALSE) -> 3 | P32: Dominic | S32: rick@changebynumbers.com | V32: rick@changebynumbers.com
A33: =A32+1 -> #REF! | B33: =COUNTIF('Loyd List 1-190 - Edit'!$R$3:$R$184,'Data check lookup table'!A33) -> 0 | G33: 125 | H33: =VLOOKUP(G33,namewithfather,2,FALSE) -> Rona (125): 1951– | I33: =VLOOKUP(G33,namewithfather,3,FALSE) -> 86 | J33: =VLOOKUP(I33,namewithfather,2,FALSE) -> Peter (86): 1913–2008 | K33: =VLOOKUP(I33,namewithfather,3,FALSE) -> 71 | L33: =VLOOKUP(K33,namewithfather,2,FALSE) -> Arthur (71): 1890–1974 | M33: =VLOOKUP(G33,'Loyd List 1-190 - Edit'!$P$3:$AN$184,25,FALSE) -> 1 | N33: =VLOOKUP(G33,'Loyd List 1-190 - Edit'!$P$3:$AGI$184,26,FALSE) -> 71 | O33: =VLOOKUP(G33,'Loyd List 1-190 - Edit'!$P$3:$AM$184,22,FALSE) -> 2 | P33: Dominic | S33: jockronahawkey@hotmail.com | V33: jockronahawkey@hotmail.com
A34: =A33+1 -> #REF! | B34: =COUNTIF('Loyd List 1-190 - Edit'!$R$3:$R$184,'Data check lookup table'!A34) -> 0 | G34: 130 | H34: =VLOOKUP(G34,namewithfather,2,FALSE) -> David (130): 1952– | I34: =VLOOKUP(G34,namewithfather,3,FALSE) -> 86 | J34: =VLOOKUP(I34,namewithfather,2,FALSE) -> Peter (86): 1913–2008 | K34: =VLOOKUP(I34,namewithfather,3,FALSE) -> 71 | L34: =VLOOKUP(K34,namewithfather,2,FALSE) -> Arthur (71): 1890–1974 | M34: =VLOOKUP(G34,'Loyd List 1-190 - Edit'!$P$3:$AN$184,25,FALSE) -> 1 | N34: =VLOOKUP(G34,'Loyd List 1-190 - Edit'!$P$3:$AGI$184,26,FALSE) -> 70 | O34: =VLOOKUP(G34,'Loyd List 1-190 - Edit'!$P$3:$AM$184,22,FALSE) -> 6 | P34: Dominic | S34: jdloyd1783@gmail.com | V34: jdloyd1783@gmail.com
A35: =A34+1 -> #REF! | B35: =COUNTIF('Loyd List 1-190 - Edit'!$R$3:$R$184,'Data check lookup table'!A35) -> 0 | G35: 135 | H35: =VLOOKUP(G35,namewithfather,2,FALSE) -> Jim (135): 1955– | I35: =VLOOKUP(G35,namewithfather,3,FALSE) -> 86 | J35: =VLOOKUP(I35,namewithfather,2,FALSE) -> Peter (86): 1913–2008 | K35: =VLOOKUP(I35,namewithfather,3,FALSE) -> 71 | L35: =VLOOKUP(K35,namewithfather,2,FALSE) -> Arthur (71): 1890–1974 | M35: =VLOOKUP(G35,'Loyd List 1-190 - Edit'!$P$3:$AN$184,25,FALSE) -> 1 | N35: =VLOOKUP(G35,'Loyd List 1-190 - Edit'!$P$3:$AGI$184,26,FALSE) -> 66 | O35: =VLOOKUP(G35,'Loyd List 1-190 - Edit'!$P$3:$AM$184,22,FALSE) -> 8 | P35: Dominic | S35: jimbrendaloyd1@gmail.com | V35: jimbrendaloyd1@gmail.com
A36: =A35+1 -> #REF! | B36: =COUNTIF('Loyd List 1-190 - Edit'!$R$3:$R$184,'Data check lookup table'!A36) -> 0 | G36: 141 | H36: =VLOOKUP(G36,namewithfather,2,FALSE) -> Alexandra (141): 1961– | I36: =VLOOKUP(G36,namewithfather,3,FALSE) -> 104 | J36: =VLOOKUP(I36,namewithfather,2,FALSE) -> Sir Julian (104): 1926–2018 | K36: =VLOOKUP(I36,namewithfather,3,FALSE) -> 72 | L36: =VLOOKUP(K36,namewithfather,2,FALSE) -> Charles (72): 1891–1973 | M36: =VLOOKUP(G36,'Loyd List 1-190 - Edit'!$P$3:$AN$184,25,FALSE) -> 1 | N36: =VLOOKUP(G36,'Loyd List 1-190 - Edit'!$P$3:$AGI$184,26,FALSE) -> 60 | O36: =VLOOKUP(G36,'Loyd List 1-190 - Edit'!$P$3:$AM$184,22,FALSE) -> 10 | P36: Jeremy | Q36: 02072280654 | R36: 07796178796 | S36: ambyatt@gmail.com | V36: ambyatt@gmail.com
A37: =A36+1 -> #REF! | B37: =COUNTIF('Loyd List 1-190 - Edit'!$R$3:$R$184,'Data check lookup table'!A37) -> 0 | G37: 146 | H37: =VLOOKUP(G37,namewithfather,2,FALSE) -> Charles (146): 1963– | I37: =VLOOKUP(G37,namewithfather,3,FALSE) -> 104 | J37: =VLOOKUP(I37,namewithfather,2,FALSE) -> Sir Julian (104): 1926–2018 | K37: =VLOOKUP(I37,namewithfather,3,FALSE) -> 72 | L37: =VLOOKUP(K37,namewithfather,2,FALSE) -> Charles (72): 1891–1973 | M37: =VLOOKUP(G37,'Loyd List 1-190 - Edit'!$P$3:$AN$184,25,FALSE) -> 1 | N37: =VLOOKUP(G37,'Loyd List 1-190 - Edit'!$P$3:$AGI$184,26,FALSE) -> 59 | O37: =VLOOKUP(G37,'Loyd List 1-190 - Edit'!$P$3:$AM$184,22,FALSE) -> 3 | P37: Jeremy | Q37: 01473 220435 | S37: c.loyde@icloud.com | V37: c.loyde@icloud.com
A38: =A37+1 -> #REF! | B38: =COUNTIF('Loyd List 1-190 - Edit'!$R$3:$R$184,'Data check lookup table'!A38) -> 0 | G38: 152 | H38: =VLOOKUP(G38,namewithfather,2,FALSE) -> Mary Rose (152): 1967– | I38: =VLOOKUP(G38,namewithfather,3,FALSE) -> 104 | J38: =VLOOKUP(I38,namewithfather,2,FALSE) -> Sir Julian (104): 1926–2018 | K38: =VLOOKUP(I38,namewithfather,3,FALSE) -> 72 | L38: =VLOOKUP(K38,namewithfather,2,FALSE) -> Charles (72): 1891–1973 | M38: =VLOOKUP(G38,'Loyd List 1-190 - Edit'!$P$3:$AN$184,25,FALSE) -> 1 | N38: =VLOOKUP(G38,'Loyd List 1-190 - Edit'!$P$3:$AGI$184,26,FALSE) -> 55 | O38: =VLOOKUP(G38,'Loyd List 1-190 - Edit'!$P$3:$AM$184,22,FALSE) -> 6 | P38: Jeremy | R38: 07768708288 | S38: maryrose@whitcomb.co.uk | V38: maryrose@whitcomb.co.uk
A39: =A38+1 -> #REF! | B39: =COUNTIF('Loyd List 1-190 - Edit'!$R$3:$R$184,'Data check lookup table'!A39) -> 0 | G39: 128 | H39: =VLOOKUP(G39,namewithfather,2,FALSE) -> Julie (128): 1952– | I39: =VLOOKUP(G39,namewithfather,3,FALSE) -> 98 | J39: =VLOOKUP(I39,namewithfather,2,FALSE) -> Peter (98): 1922–2022 | K39: =VLOOKUP(I39,namewithfather,3,FALSE) -> 77 | L39: =VLOOKUP(K39,namewithfather,2,FALSE) -> Wilfrid (77): 1893–1971 | M39: =VLOOKUP(G39,'Loyd List 1-190 - Edit'!$P$3:$AN$184,25,FALSE) -> 1 | N39: =VLOOKUP(G39,'Loyd List 1-190 - Edit'!$P$3:$AGI$184,26,FALSE) -> 70 | O39: =VLOOKUP(G39,'Loyd List 1-190 - Edit'!$P$3:$AM$184,22,FALSE) -> 4 | P39: Jeremy | S39: rosemaryloyd@gmail.com | V39: julieweb3004@gmail.com
A40: =A39+1 -> #REF! | B40: =COUNTIF('Loyd List 1-190 - Edit'!$R$3:$R$184,'Data check lookup table'!A40) -> 0 | G40: 134 | H40: =VLOOKUP(G40,namewithfather,2,FALSE) -> William (134): 1955– | I40: =VLOOKUP(G40,namewithfather,3,FALSE) -> 98 | J40: =VLOOKUP(I40,namewithfather,2,FALSE) -> Peter (98): 1922–2022 | K40: =VLOOKUP(I40,namewithfather,3,FALSE) -> 77 | L40: =VLOOKUP(K40,namewithfather,2,FALSE) -> Wilfrid (77): 1893–1971 | M40: =VLOOKUP(G40,'Loyd List 1-190 - Edit'!$P$3:$AN$184,25,FALSE) -> 1 | N40: =VLOOKUP(G40,'Loyd List 1-190 - Edit'!$P$3:$AGI$184,26,FALSE) -> 67 | O40: =VLOOKUP(G40,'Loyd List 1-190 - Edit'!$P$3:$AM$184,22,FALSE) -> 6 | P40: Jeremy | S40: rosemaryloyd@gmail.com | V40: williamloyd@uwclub.net
A41: =A40+1 -> #REF! | B41: =COUNTIF('Loyd List 1-190 - Edit'!$R$3:$R$184,'Data check lookup table'!A41) -> 0 | G41: 145 | H41: =VLOOKUP(G41,namewithfather,2,FALSE) -> Tony (145): 1963– | I41: =VLOOKUP(G41,namewithfather,3,FALSE) -> 98 | J41: =VLOOKUP(I41,namewithfather,2,FALSE) -> Peter (98): 1922–2022 | K41: =VLOOKUP(I41,namewithfather,3,FALSE) -> 77 | L41: =VLOOKUP(K41,namewithfather,2,FALSE) -> Wilfrid (77): 1893–1971 | M41: =VLOOKUP(G41,'Loyd List 1-190 - Edit'!$P$3:$AN$184,25,FALSE) -> 1 | N41: =VLOOKUP(G41,'Loyd List 1-190 - Edit'!$P$3:$AGI$184,26,FALSE) -> 59 | O41: =VLOOKUP(G41,'Loyd List 1-190 - Edit'!$P$3:$AM$184,22,FALSE) -> 2 | P41: Jeremy | S41: rosemaryloyd@gmail.com | V41: tonyloyd@mac.com
A42: =A41+1 -> #REF! | B42: =COUNTIF('Loyd List 1-190 - Edit'!$R$3:$R$184,'Data check lookup table'!A42) -> 0 | G42: 154 | H42: =VLOOKUP(G42,namewithfather,2,FALSE) -> Sophie (154): 1969– | I42: =VLOOKUP(G42,namewithfather,3,FALSE) -> 98 | J42: =VLOOKUP(I42,namewithfather,2,FALSE) -> Peter (98): 1922–2022 | K42: =VLOOKUP(I42,namewithfather,3,FALSE) -> 77 | L42: =VLOOKUP(K42,namewithfather,2,FALSE) -> Wilfrid (77): 1893–1971 | M42: =VLOOKUP(G42,'Loyd List 1-190 - Edit'!$P$3:$AN$184,25,FALSE) -> 1 | N42: =VLOOKUP(G42,'Loyd List 1-190 - Edit'!$P$3:$AGI$184,26,FALSE) -> 53 | O42: =VLOOKUP(G42,'Loyd List 1-190 - Edit'!$P$3:$AM$184,22,FALSE) -> 6 | P42: Jeremy | S42: rosemaryloyd@gmail.com | V42: sophie.newing@gmail.com
A43: =A42+1 -> #REF! | B43: =COUNTIF('Loyd List 1-190 - Edit'!$R$3:$R$184,'Data check lookup table'!A43) -> 0 | G43: 122 | H43: =VLOOKUP(G43,namewithfather,2,FALSE) -> Martin (122): 1949– | I43: =VLOOKUP(G43,namewithfather,3,FALSE) -> 105 | J43: =VLOOKUP(I43,namewithfather,2,FALSE) -> Geoffrey (105): 1926–2018 | K43: =VLOOKUP(I43,namewithfather,3,FALSE) -> 77 | L43: =VLOOKUP(K43,namewithfather,2,FALSE) -> Wilfrid (77): 1893–1971 | M43: =VLOOKUP(G43,'Loyd List 1-190 - Edit'!$P$3:$AN$184,25,FALSE) -> 1 | N43: =VLOOKUP(G43,'Loyd List 1-190 - Edit'!$P$3:$AGI$184,26,FALSE) -> 73 | O43: =VLOOKUP(G43,'Loyd List 1-190 - Edit'!$P$3:$AM$184,22,FALSE) -> 2 | P43: Jeremy | S43: jeremyloyd@hotmail.com | V43: jeremyloyd@hotmail.com
A44: =A43+1 -> #REF! | B44: =COUNTIF('Loyd List 1-190 - Edit'!$R$3:$R$184,'Data check lookup table'!A44) -> 0 | G44: 133 | H44: =VLOOKUP(G44,namewithfather,2,FALSE) -> Jeremy (133): 1954– | I44: =VLOOKUP(G44,namewithfather,3,FALSE) -> 105 | J44: =VLOOKUP(I44,namewithfather,2,FALSE) -> Geoffrey (105): 1926–2018 | K44: =VLOOKUP(I44,namewithfather,3,FALSE) -> 77 | L44: =VLOOKUP(K44,namewithfather,2,FALSE) -> Wilfrid (77): 1893–1971 | M44: =VLOOKUP(G44,'Loyd List 1-190 - Edit'!$P$3:$AN$184,25,FALSE) -> 1 | N44: =VLOOKUP(G44,'Loyd List 1-190 - Edit'!$P$3:$AGI$184,26,FALSE) -> 67 | O44: =VLOOKUP(G44,'Loyd List 1-190 - Edit'!$P$3:$AM$184,22,FALSE) -> 7 | P44: Jeremy | S44: jeremyloyd@hotmail.com | V44: jeremyloyd@hotmail.com
A45: =A44+1 -> #REF! | B45: =COUNTIF('Loyd List 1-190 - Edit'!$R$3:$R$184,'Data check lookup table'!A45) -> 0 | G45: 149 | H45: =VLOOKUP(G45,namewithfather,2,FALSE) -> Anthony (149): 1966– | I45: =VLOOKUP(G45,namewithfather,3,FALSE) -> 113 | J45: =VLOOKUP(I45,namewithfather,2,FALSE) -> Willie (113): 1937–1994 | K45: =VLOOKUP(I45,namewithfather,3,FALSE) -> 78 | L45: =VLOOKUP(K45,namewithfather,2,FALSE) -> Vivian (78): 1894–1972 | M45: =VLOOKUP(G45,'Loyd List 1-190 - Edit'!$P$3:$AN$184,25,FALSE) -> 1 | N45: =VLOOKUP(G45,'Loyd List 1-190 - Edit'!$P$3:$AGI$184,26,FALSE) -> 55 | O45: =VLOOKUP(G45,'Loyd List 1-190 - Edit'!$P$3:$AM$184,22,FALSE) -> 9 | P45: Dominic | S45: Anthonyloyd@gmail.com | V45: anthonyloyd@googlemail.com
A46: =A45+1 -> #REF! | B46: =COUNTIF('Loyd List 1-190 - Edit'!$R$3:$R$184,'Data check lookup table'!A46) -> 0 | G46: 157 | H46: =VLOOKUP(G46,namewithfather,2,FALSE) -> Tess (157): 1975– | I46: =VLOOKUP(G46,namewithfather,3,FALSE) -> 114 | J46: =VLOOKUP(I46,namewithfather,2,FALSE) -> Michael (114): 1938– | K46: =VLOOKUP(I46,namewithfather,3,FALSE) -> 80 | L46: =VLOOKUP(K46,namewithfather,2,FALSE) -> Eric (80): 1894–1963 | M46: =VLOOKUP(G46,'Loyd List 1-190 - Edit'!$P$3:$AN$184,25,FALSE) -> 1 | N46: =VLOOKUP(G46,'Loyd List 1-190 - Edit'!$P$3:$AGI$184,26,FALSE) -> 46 | O46: =VLOOKUP(G46,'Loyd List 1-190 - Edit'!$P$3:$AM$184,22,FALSE) -> 7 | P46: Jeremy | S46: mantlehill@aol.com | V46: mantlehill@aol.com
A47: =A46+1 -> #REF! | B47: =COUNTIF('Loyd List 1-190 - Edit'!$R$3:$R$184,'Data check lookup table'!A47) -> 0 | G47: 158 | H47: =VLOOKUP(G47,namewithfather,2,FALSE) -> Chloe (158): 1977– | I47: =VLOOKUP(G47,namewithfather,3,FALSE) -> 114 | J47: =VLOOKUP(I47,namewithfather,2,FALSE) -> Michael (114): 1938– | K47: =VLOOKUP(I47,namewithfather,3,FALSE) -> 80 | L47: =VLOOKUP(K47,namewithfather,2,FALSE) -> Eric (80): 1894–1963 | M47: =VLOOKUP(G47,'Loyd List 1-190 - Edit'!$P$3:$AN$184,25,FALSE) -> 1 | N47: =VLOOKUP(G47,'Loyd List 1-190 - Edit'!$P$3:$AGI$184,26,FALSE) -> 44 | O47: =VLOOKUP(G47,'Loyd List 1-190 - Edit'!$P$3:$AM$184,22,FALSE) -> 8 | P47: Jeremy | S47: mantlehill@aol.com | V47: mantlehill@aol.com
A48: =A47+1 -> #REF! | B48: =COUNTIF('Loyd List 1-190 - Edit'!$R$3:$R$184,'Data check lookup table'!A48) -> 0 | G48: 159 | H48: =VLOOKUP(G48,namewithfather,2,FALSE) -> Daisy (159): 1979– | I48: =VLOOKUP(G48,namewithfather,3,FALSE) -> 114 | J48: =VLOOKUP(I48,namewithfather,2,FALSE) -> Michael (114): 1938– | K48: =VLOOKUP(I48,namewithfather,3,FALSE) -> 80 | L48: =VLOOKUP(K48,namewithfather,2,FALSE) -> Eric (80): 1894–1963 | M48: =VLOOKUP(G48,'Loyd List 1-190 - Edit'!$P$3:$AN$184,25,FALSE) -> 1 | N48: =VLOOKUP(G48,'Loyd List 1-190 - Edit'!$P$3:$AGI$184,26,FALSE) -> 42 | O48: =VLOOKUP(G48,'Loyd List 1-190 - Edit'!$P$3:$AM$184,22,FALSE) -> 8 | P48: Jeremy | S48: mantlehill@aol.com | V48: mantlehill@aol.com
A49: =A48+1 -> #REF! | B49: =COUNTIF('Loyd List 1-190 - Edit'!$R$3:$R$184,'Data check lookup table'!A49) -> 0 | G49: 155 | H49: =VLOOKUP(G49,namewithfather,2,FALSE) -> William (155): 1973– | I49: =VLOOKUP(G49,namewithfather,3,FALSE) -> 119 | J49: =VLOOKUP(I49,namewithfather,2,FALSE) -> Peter (119): 1942– | K49: =VLOOKUP(I49,namewithfather,3,FALSE) -> 80 | L49: =VLOOKUP(K49,namewithfather,2,FALSE) -> Eric (80): 1894–1963 | M49: =VLOOKUP(G49,'Loyd List 1-190 - Edit'!$P$3:$AN$184,25,FALSE) -> 1 | N49: =VLOOKUP(G49,'Loyd List 1-190 - Edit'!$P$3:$AGI$184,26,FALSE) -> 49 | O49: =VLOOKUP(G49,'Loyd List 1-190 - Edit'!$P$3:$AM$184,22,FALSE) -> 4 | P49: Jeremy | S49: mantlehill@aol.com | V49: mantlehill@aol.com
A50: =A49+1 -> #REF! | B50: =COUNTIF('Loyd List 1-190 - Edit'!$R$3:$R$184,'Data check lookup table'!A50) -> 0 | G50: 156 | H50: =VLOOKUP(G50,namewithfather,2,FALSE) -> Amy (156): 1975– | I50: =VLOOKUP(G50,namewithfather,3,FALSE) -> 119 | J50: =VLOOKUP(I50,namewithfather,2,FALSE) -> Peter (119): 1942– | K50: =VLOOKUP(I50,namewithfather,3,FALSE) -> 80 | L50: =VLOOKUP(K50,namewithfather,2,FALSE) -> Eric (80): 1894–1963 | M50: =VLOOKUP(G50,'Loyd List 1-190 - Edit'!$P$3:$AN$184,25,FALSE) -> 1 | N50: =VLOOKUP(G50,'Loyd List 1-190 - Edit'!$P$3:$AGI$184,26,FALSE) -> 47 | O50: =VLOOKUP(G50,'Loyd List 1-190 - Edit'!$P$3:$AM$184,22,FALSE) -> 3 | P50: Jeremy | S50: mantlehill@aol.com | V50: mantlehill@aol.com
... A54: =A53+1 -> #REF! | B54: =COUNTIF('Loyd List 1-190 - Edit'!$R$3:$R$184,'Data check lookup table'!A54) -> 0 | G54: 173 | H54: =VLOOKUP(G54,namewithfather,2,FALSE) -> Curtis (173): 1992– | I54: =VLOOKUP(G54,namewithfather,3,FALSE) -> 135 | J54: =VLOOKUP(I54,namewithfather,2,FALSE) -> Jim (135): 1955– | K54: =VLOOKUP(I54,namewithfather,3,FALSE) -> 86 | L54: =VLOOKUP(K54,namewithfather,2,FALSE) -> Peter (86): 1913–2008 | M54: =VLOOKUP(G54,'Loyd List 1-190 - Edit'!$P$3:$AN$184,25,FALSE) -> 1 | N54: =VLOOKUP(G54,'Loyd List 1-190 - Edit'!$P$3:$AGI$184,26,FALSE) -> 30 | O54: =VLOOKUP(G54,'Loyd List 1-190 - Edit'!$P$3:$AM$184,22,FALSE) -> 1 | P54: Dominic | S54: jimbrendaloyd1@gmail.com | V54: jimbrendaloyd1@gmail.com
A55: =A54+1 -> #REF! | B55: =COUNTIF('Loyd List 1-190 - Edit'!$R$3:$R$184,'Data check lookup table'!A55) -> 0 | G55: 177 | H55: =VLOOKUP(G55,namewithfather,2,FALSE) -> Spencer (177): 1995– | I55: =VLOOKUP(G55,namewithfather,3,FALSE) -> 135 | J55: =VLOOKUP(I55,namewithfather,2,FALSE) -> Jim (135): 1955– | K55: =VLOOKUP(I55,namewithfather,3,FALSE) -> 86 | L55: =VLOOKUP(K55,namewithfather,2,FALSE) -> Peter (86): 1913–2008 | M55: =VLOOKUP(G55,'Loyd List 1-190 - Edit'!$P$3:$AN$184,25,FALSE) -> 1 | N55: =VLOOKUP(G55,'Loyd List 1-190 - Edit'!$P$3:$AGI$184,26,FALSE) -> 26 | O55: =VLOOKUP(G55,'Loyd List 1-190 - Edit'!$P$3:$AM$184,22,FALSE) -> 7 | P55: Dominic | R55: spennyloyd23@gmail.com | S55: jimbrendaloyd1@gmail.com | V55: jimbrendaloyd1@gmail.com
A56: =A55+1 -> #REF! | B56: =COUNTIF('Loyd List 1-190 - Edit'!$R$3:$R$184,'Data check lookup table'!A56) -> 0 | G56: 160 | H56: =VLOOKUP(G56,namewithfather,2,FALSE) -> John (160): 1982– | I56: =VLOOKUP(G56,namewithfather,3,FALSE) -> 131 | J56: =VLOOKUP(I56,namewithfather,2,FALSE) -> Dominic (131): 1953– | K56: =VLOOKUP(I56,namewithfather,3,FALSE) -> 94 | L56: =VLOOKUP(K56,namewithfather,2,FALSE) -> Alwyne (94): 1920–2014 | M56: =VLOOKUP(G56,'Loyd List 1-190 - Edit'!$P$3:$AN$184,25,FALSE) -> 1 | N56: =VLOOKUP(G56,'Loyd List 1-190 - Edit'!$P$3:$AGI$184,26,FALSE) -> 40 | O56: =VLOOKUP(G56,'Loyd List 1-190 - Edit'!$P$3:$AM$184,22,FALSE) -> 1 | P56: Dominic | S56: johnloyd@hotmail.com | V56: johnloyd@hotmail.com
A57: =A56+1 -> #REF! | B57: =COUNTIF('Loyd List 1-190 - Edit'!$R$3:$R$184,'Data check lookup table'!A57) -> 0 | G57: 162 | H57: =VLOOKUP(G57,namewithfather,2,FALSE) -> David (162): 1984– | I57: =VLOOKUP(G57,namewithfather,3,FALSE) -> 131 | J57: =VLOOKUP(I57,namewithfather,2,FALSE) -> Dominic (131): 1953– | K57: =VLOOKUP(I57,namewithfather,3,FALSE) -> 94 | L57: =VLOOKUP(K57,namewithfather,2,FALSE) -> Alwyne (94): 1920–2014 | M57: =VLOOKUP(G57,'Loyd List 1-190 - Edit'!$P$3:$AN$184,25,FALSE) -> 1 | N57: =VLOOKUP(G57,'Loyd List 1-190 - Edit'!$P$3:$AGI$184,26,FALSE) -> 38 | O57: =VLOOKUP(G57,'Loyd List 1-190 - Edit'!$P$3:$AM$184,22,FALSE) -> 4 | P57: Dominic | S57: loyddavid@hotmail.co | V57: loyddavid@hotmail.coM
A58: =A57+1 -> #REF! | B58: =COUNTIF('Loyd List 1-190 - Edit'!$R$3:$R$184,'Data check lookup table'!A58) -> 0 | G58: 167 | H58: =VLOOKUP(G58,namewithfather,2,FALSE) -> Ben (167): 1988– | I58: =VLOOKUP(G58,namewithfather,3,FALSE) -> 131 | J58: =VLOOKUP(I58,namewithfather,2,FALSE) -> Dominic (131): 1953– | K58: =VLOOKUP(I58,namewithfather,3,FALSE) -> 94 | L58: =VLOOKUP(K58,namewithfather,2,FALSE) -> Alwyne (94): 1920–2014 | M58: =VLOOKUP(G58,'Loyd List 1-190 - Edit'!$P$3:$AN$184,25,FALSE) -> 1 | N58: =VLOOKUP(G58,'Loyd List 1-190 - Edit'!$P$3:$AGI$184,26,FALSE) -> 34 | O58: =VLOOKUP(G58,'Loyd List 1-190 - Edit'!$P$3:$AM$184,22,FALSE) -> 3 | P58: Dominic | S58: streetb03@hotmail.com | V58: streetb03@hotmail.com
A59: =A58+1 -> #REF! | B59: =COUNTIF('Loyd List 1-190 - Edit'!$R$3:$R$184,'Data check lookup table'!A59) -> 0 | G59: 164 | H59: =VLOOKUP(G59,namewithfather,2,FALSE) -> Poppy (164): 1984– | I59: =VLOOKUP(G59,namewithfather,3,FALSE) -> 136 | J59: =VLOOKUP(I59,namewithfather,2,FALSE) -> Tim (136): 1957– | K59: =VLOOKUP(I59,namewithfather,3,FALSE) -> 94 | L59: =VLOOKUP(K59,namewithfather,2,FALSE) -> Alwyne (94): 1920–2014 | M59: =VLOOKUP(G59,'Loyd List 1-190 - Edit'!$P$3:$AN$184,25,FALSE) -> 1 | N59: =VLOOKUP(G59,'Loyd List 1-190 - Edit'!$P$3:$AGI$184,26,FALSE) -> 37 | O59: =VLOOKUP(G59,'Loyd List 1-190 - Edit'!$P$3:$AM$184,22,FALSE) -> 12 | P59: Dominic | R59: 07709450373 | S59: poppycl@hotmail.com | T59: 2, Spynie Heights, Elgin, Moray. IV30 4PB | V59: poppycl@hotmail.com
A60: =A59+1 -> #REF! | B60: =COUNTIF('Loyd List 1-190 - Edit'!$R$3:$R$184,'Data check lookup table'!A60) -> 0 | G60: 165 | H60: =VLOOKUP(G60,namewithfather,2,FALSE) -> Rose (165): 1986– | I60: =VLOOKUP(G60,namewithfather,3,FALSE) -> 136 | J60: =VLOOKUP(I60,namewithfather,2,FALSE) -> Tim (136): 1957– | K60: =VLOOKUP(I60,namewithfather,3,FALSE) -> 94 | L60: =VLOOKUP(K60,namewithfather,2,FALSE) -> Alwyne (94): 1920–2014 | M60: =VLOOKUP(G60,'Loyd List 1-190 - Edit'!$P$3:$AN$184,25,FALSE) -> 1 | N60: =VLOOKUP(G60,'Loyd List 1-190 - Edit'!$P$3:$AGI$184,26,FALSE) -> 35 | O60: =VLOOKUP(G60,'Loyd List 1-190 - Edit'!$P$3:$AM$184,22,FALSE) -> 7 | P60: Dominic | R60: 07754758915 | S60: rosepuri77@gmail.com | V60: rosepuri77@gmail.com
A61: =A60+1 -> #REF! | B61: =COUNTIF('Loyd List 1-190 - Edit'!$R$3:$R$184,'Data check lookup table'!A61) -> 0 | G61: 172 | H61: =VLOOKUP(G61,namewithfather,2,FALSE) -> Florina (172): 1991– | I61: =VLOOKUP(G61,namewithfather,3,FALSE) -> 136 | J61: =VLOOKUP(I61,namewithfather,2,FALSE) -> Tim (136): 1957– | K61: =VLOOKUP(I61,namewithfather,3,FALSE) -> 94 | L61: =VLOOKUP(K61,namewithfather,2,FALSE) -> Alwyne (94): 1920–2014 | M61: =VLOOKUP(G61,'Loyd List 1-190 - Edit'!$P$3:$AN$184,25,FALSE) -> 1 | N61: =VLOOKUP(G61,'Loyd List 1-190 - Edit'!$P$3:$AGI$184,26,FALSE) -> 30 | O61: =VLOOKUP(G61,'Loyd List 1-190 - Edit'!$P$3:$AM$184,22,FALSE) -> 12 | P61: Dominic | S61: florina.cl@btinternet.com | V61: florina.cl@btinternet.com
A62: =A61+1 -> #REF! | B62: =COUNTIF('Loyd List 1-190 - Edit'!$R$3:$R$184,'Data check lookup table'!A62) -> 0 | G62: 176 | H62: =VLOOKUP(G62,namewithfather,2,FALSE) -> Sam (176): 1994– | I62: =VLOOKUP(G62,namewithfather,3,FALSE) -> 142 | J62: =VLOOKUP(I62,namewithfather,2,FALSE) -> Rick (142): 1962– | K62: =VLOOKUP(I62,namewithfather,3,FALSE) -> 94 | L62: =VLOOKUP(K62,namewithfather,2,FALSE) -> Alwyne (94): 1920–2014 | M62: =VLOOKUP(G62,'Loyd List 1-190 - Edit'!$P$3:$AN$184,25,FALSE) -> 1 | N62: =VLOOKUP(G62,'Loyd List 1-190 - Edit'!$P$3:$AGI$184,26,FALSE) -> 28 | O62: =VLOOKUP(G62,'Loyd List 1-190 - Edit'!$P$3:$AM$184,22,FALSE) -> 1 | P62: Dominic | S62: samloyd@hotmail.co.uk | V62: samloyd@hotmail.co.uk
A63: =A62+1 -> #REF! | B63: =COUNTIF('Loyd List 1-190 - Edit'!$R$3:$R$184,'Data check lookup table'!A63) -> 0 | G63: 179 | H63: =VLOOKUP(G63,namewithfather,2,FALSE) -> Josh (179): 1996– | I63: =VLOOKUP(G63,namewithfather,3,FALSE) -> 142 | J63: =VLOOKUP(I63,namewithfather,2,FALSE) -> Rick (142): 1962– | K63: =VLOOKUP(I63,namewithfather,3,FALSE) -> 94 | L63: =VLOOKUP(K63,namewithfather,2,FALSE) -> Alwyne (94): 1920–2014 | M63: =VLOOKUP(G63,'Loyd List 1-190 - Edit'!$P$3:$AN$184,25,FALSE) -> 1 | N63: =VLOOKUP(G63,'Loyd List 1-190 - Edit'!$P$3:$AGI$184,26,FALSE) -> 25 | O63: =VLOOKUP(G63,'Loyd List 1-190 - Edit'!$P$3:$AM$184,22,FALSE) -> 12 | P63: Dominic | S63: joshloyd96@gmail.com | V63: joshloyd96@gmail.com
A64: =A63+1 -> #REF! | B64: =COUNTIF('Loyd List 1-190 - Edit'!$R$3:$R$184,'Data check lookup table'!A64) -> 0 | G64: 169 | H64: =VLOOKUP(G64,namewithfather,2,FALSE) -> James (169): 1988– | I64: =VLOOKUP(G64,namewithfather,3,FALSE) -> 121 | J64: =VLOOKUP(I64,namewithfather,2,FALSE) -> David (121): 1949– | K64: =VLOOKUP(I64,namewithfather,3,FALSE) -> 96 | L64: =VLOOKUP(K64,namewithfather,2,FALSE) -> Edward (96): 1921–1977 | M64: =VLOOKUP(G64,'Loyd List 1-190 - Edit'!$P$3:$AN$184,25,FALSE) -> 1 | N64: =VLOOKUP(G64,'Loyd List 1-190 - Edit'!$P$3:$AGI$184,26,FALSE) -> 33 | O64: =VLOOKUP(G64,'Loyd List 1-190 - Edit'!$P$3:$AM$184,22,FALSE) -> 9 | P64: Dominic | S64: loydie1988@gmail.com | V64: loydie1988@gmail.com
A65: =A64+1 -> #REF! | B65: =COUNTIF('Loyd List 1-190 - Edit'!$R$3:$R$184,'Data check lookup table'!A65) -> 0 | G65: 171 | H65: =VLOOKUP(G65,namewithfather,2,FALSE) -> Rupert (171): 1990– | I65: =VLOOKUP(G65,namewithfather,3,FALSE) -> 121 | J65: =VLOOKUP(I65,namewithfather,2,FALSE) -> David (121): 1949– | K65: =VLOOKUP(I65,namewithfather,3,FALSE) -> 96 | L65: =VLOOKUP(K65,namewithfather,2,FALSE) -> Edward (96): 1921–1977 | M65: =VLOOKUP(G65,'Loyd List 1-190 - Edit'!$P$3:$AN$184,25,FALSE) -> 1 | N65: =VLOOKUP(G65,'Loyd List 1-190 - Edit'!$P$3:$AGI$184,26,FALSE) -> 32 | O65: =VLOOKUP(G65,'Loyd List 1-190 - Edit'!$P$3:$AM$184,22,FALSE) -> 2 | P65: Dominic | S65: rupertloyd@hotmail.co.uk | V65: rupertloyd@hotmail.co.uk
A66: =A65+1 -> #REF! | B66: =COUNTIF('Loyd List 1-190 - Edit'!$R$3:$R$184,'Data check lookup table'!A66) -> 0 | G66: 174 | H66: =VLOOKUP(G66,namewithfather,2,FALSE) -> Tabitha (174): 1992– | I66: =VLOOKUP(G66,namewithfather,3,FALSE) -> 121 | J66: =VLOOKUP(I66,namewithfather,2,FALSE) -> David (121): 1949– | K66: =VLOOKUP(I66,namewithfather,3,FALSE) -> 96 | L66: =VLOOKUP(K66,namewithfather,2,FALSE) -> Edward (96): 1921–1977 | M66: =VLOOKUP(G66,'Loyd List 1-190 - Edit'!$P$3:$AN$184,25,FALSE) -> 1 | N66: =VLOOKUP(G66,'Loyd List 1-190 - Edit'!$P$3:$AGI$184,26,FALSE) -> 29 | O66: =VLOOKUP(G66,'Loyd List 1-190 - Edit'!$P$3:$AM$184,22,FALSE) -> 11 | P66: Dominic | S66: tabsloyd@hotmail.co.uk | V66: tabsloyd@hotmail.co.uk
A67: =A66+1 -> #REF! | B67: =COUNTIF('Loyd List 1-190 - Edit'!$R$3:$R$184,'Data check lookup table'!A67) -> 0 | G67: 168 | H67: =VLOOKUP(G67,namewithfather,2,FALSE) -> Camilla (168): 1988– | I67: =VLOOKUP(G67,namewithfather,3,FALSE) -> 138 | J67: =VLOOKUP(I67,namewithfather,2,FALSE) -> Thomas (138): 1959– | K67: =VLOOKUP(I67,namewithfather,3,FALSE) -> 100 | L67: =VLOOKUP(K67,namewithfather,2,FALSE) -> Christopher (100): 1923–2013 | M67: =VLOOKUP(G67,'Loyd List 1-190 - Edit'!$P$3:$AN$184,25,FALSE) -> 1 | N67: =VLOOKUP(G67,'Loyd List 1-190 - Edit'!$P$3:$AGI$184,26,FALSE) -> 34 | O67: =VLOOKUP(G67,'Loyd List 1-190 - Edit'!$P$3:$AM$184,22,FALSE) -> 5 | P67: Jeremy | S67: tloyd@lockinge-estate.co.uk | V67: tloyd@lockinge-estate.co.uk
A68: =A67+1 -> #REF! | B68: =COUNTIF('Loyd List 1-190 - Edit'!$R$3:$R$184,'Data check lookup table'!A68) -> 0 | G68: 170 | H68: =VLOOKUP(G68,namewithfather,2,FALSE) -> Sophie (170): 1989– | I68: =VLOOKUP(G68,namewithfather,3,FALSE) -> 138 | J68: =VLOOKUP(I68,namewithfather,2,FALSE) -> Thomas (138): 1959– | K68: =VLOOKUP(I68,namewithfather,3,FALSE) -> 100 | L68: =VLOOKUP(K68,namewithfather,2,FALSE) -> Christopher (100): 1923–2013 | M68: =VLOOKUP(G68,'Loyd List 1-190 - Edit'!$P$3:$AN$184,25,FALSE) -> 1 | N68: =VLOOKUP(G68,'Loyd List 1-190 - Edit'!$P$3:$AGI$184,26,FALSE) -> 32 | O68: =VLOOKUP(G68,'Loyd List 1-190 - Edit'!$P$3:$AM$184,22,FALSE) -> 12 | P68: Jeremy | S68: tloyd@lockinge-estate.co.uk | V68: tloyd@lockinge-estate.co.uk
A69: =A68+1 -> #REF! | B69: =COUNTIF('Loyd List 1-190 - Edit'!$R$3:$R$184,'Data check lookup table'!A69) -> 0 | G69: 175 | H69: =VLOOKUP(G69,namewithfather,2,FALSE) -> Kit (175): 1993– | I69: =VLOOKUP(G69,namewithfather,3,FALSE) -> 138 | J69: =VLOOKUP(I69,namewithfather,2,FALSE) -> Thomas (138): 1959– | K69: =VLOOKUP(I69,namewithfather,3,FALSE) -> 100 | L69: =VLOOKUP(K69,namewithfather,2,FALSE) -> Christopher (100): 1923–2013 | M69: =VLOOKUP(G69,'Loyd List 1-190 - Edit'!$P$3:$AN$184,25,FALSE) -> 1 | N69: =VLOOKUP(G69,'Loyd List 1-190 - Edit'!$P$3:$AGI$184,26,FALSE) -> 29 | O69: =VLOOKUP(G69,'Loyd List 1-190 - Edit'!$P$3:$AM$184,22,FALSE) -> 1 | P69: Jeremy | S69: tloyd@lockinge-estate.co.uk | V69: tloyd@lockinge-estate.co.uk
A70: =A69+1 -> #REF! | B70: =COUNTIF('Loyd List 1-190 - Edit'!$R$3:$R$184,'Data check lookup table'!A70) -> 0 | G70: 178 | H70: =VLOOKUP(G70,namewithfather,2,FALSE) -> William (178): 1996– | I70: =VLOOKUP(G70,namewithfather,3,FALSE) -> 150 | J70: =VLOOKUP(I70,namewithfather,2,FALSE) -> James (150): 1966– | K70: =VLOOKUP(I70,namewithfather,3,FALSE) -> 100 | L70: =VLOOKUP(K70,namewithfather,2,FALSE) -> Christopher (100): 1923–2013 | M70: =VLOOKUP(G70,'Loyd List 1-190 - Edit'!$P$3:$AN$184,25,FALSE) -> 1 | N70: =VLOOKUP(G70,'Loyd List 1-190 - Edit'!$P$3:$AGI$184,26,FALSE) -> 25 | O70: =VLOOKUP(G70,'Loyd List 1-190 - Edit'!$P$3:$AM$184,22,FALSE) -> 12 | P70: Jeremy | S70: tloyd@lockinge-estate.co.uk | V70: tloyd@lockinge-estate.co.uk
A71: =A70+1 -> #REF! | B71: =COUNTIF('Loyd List 1-190 - Edit'!$R$3:$R$184,'Data check lookup table'!A71) -> 0 | G71: 181 | H71: =VLOOKUP(G71,namewithfather,2,FALSE) -> Eliza (181): 1999– | I71: =VLOOKUP(G71,namewithfather,3,FALSE) -> 150 | J71: =VLOOKUP(I71,namewithfather,2,FALSE) -> James (150): 1966– | K71: =VLOOKUP(I71,namewithfather,3,FALSE) -> 100 | L71: =VLOOKUP(K71,namewithfather,2,FALSE) -> Christopher (100): 1923–2013 | M71: =VLOOKUP(G71,'Loyd List 1-190 - Edit'!$P$3:$AN$184,25,FALSE) -> 1 | N71: =VLOOKUP(G71,'Loyd List 1-190 - Edit'!$P$3:$AGI$184,26,FALSE) -> 23 | O71: =VLOOKUP(G71,'Loyd List 1-190 - Edit'!$P$3:$AM$184,22,FALSE) -> 2 | P71: Jeremy | S71: tloyd@lockinge-estate.co.uk | V71: tloyd@lockinge-estate.co.uk
A72: =A71+1 -> #REF! | B72: =COUNTIF('Loyd List 1-190 - Edit'!$R$3:$R$184,'Data check lookup table'!A72) -> 0 | G72: 180 | H72: =VLOOKUP(G72,namewithfather,2,FALSE) -> George (180): 1998– | I72: =VLOOKUP(G72,namewithfather,3,FALSE) -> 146 | J72: =VLOOKUP(I72,namewithfather,2,FALSE) -> Charles (146): 1963– | K72: =VLOOKUP(I72,namewithfather,3,FALSE) -> 104 | L72: =VLOOKUP(K72,namewithfather,2,FALSE) -> Sir Julian (104): 1926–2018 | M72: =VLOOKUP(G72,'Loyd List 1-190 - Edit'!$P$3:$AN$184,25,FALSE) -> 1 | N72: =VLOOKUP(G72,'Loyd List 1-190 - Edit'!$P$3:$AGI$184,26,FALSE) -> 23 | O72: =VLOOKUP(G72,'Loyd List 1-190 - Edit'!$P$3:$AM$184,22,FALSE) -> 11 | P72: Dominic | S72: c.loyde@icloud.com | V72: g.loydy@gmail.com
A73: =A72+1 -> #REF! | B73: =COUNTIF('Loyd List 1-190 - Edit'!$R$3:$R$184,'Data check lookup table'!A73) -> 0 | G73: 182 | H73: =VLOOKUP(G73,namewithfather,2,FALSE) -> Rosanna (182): 2000– | I73: =VLOOKUP(G73,namewithfather,3,FALSE) -> 146 | J73: =VLOOKUP(I73,namewithfather,2,FALSE) -> Charles (146): 1963– | K73: =VLOOKUP(I73,namewithfather,3,FALSE) -> 104 | L73: =VLOOKUP(K73,namewithfather,2,FALSE) -> Sir Julian (104): 1926–2018 | M73: =VLOOKUP(G73,'Loyd List 1-190 - Edit'!$P$3:$AN$184,25,FALSE) -> 1 | N73: =VLOOKUP(G73,'Loyd List 1-190 - Edit'!$P$3:$AGI$184,26,FALSE) -> 21 | O73: =VLOOKUP(G73,'Loyd List 1-190 - Edit'!$P$3:$AM$184,22,FALSE) -> 7 | P73: Dominic | R73: 07866852007 | S73: c.loyde@icloud.com | V73: rosie.loyd@gmail.com
A74: =A73+1 -> #REF! | B74: =COUNTIF('Loyd List 1-190 - Edit'!$R$3:$R$184,'Data check lookup table'!A74) -> 0
A75: =A74+1 -> #REF! | B75: =COUNTIF('Loyd List 1-190 - Edit'!$R$3:$R$184,'Data check lookup table'!A75) -> 0
A76: =A75+1 -> #REF! | B76: =COUNTIF('Loyd List 1-190 - Edit'!$R$3:$R$184,'Data check lookup table'!A76) -> 0
A77: =A76+1 -> #REF! | B77: =COUNTIF('Loyd List 1-190 - Edit'!$R$3:$R$184,'Data check lookup table'!A77) -> 0
A78: =A77+1 -> #REF! | B78: =COUNTIF('Loyd List 1-190 - Edit'!$R$3:$R$184,'Data check lookup table'!A78) -> 0
A79: =A78+1 -> #REF! | B79: =COUNTIF('Loyd List 1-190 - Edit'!$R$3:$R$184,'Data check lookup table'!A79) -> 0
A80: =A79+1 -> #REF! | B80: =COUNTIF('Loyd List 1-190 - Edit'!$R$3:$R$184,'Data check lookup table'!A80) -> 0
A81: =A80+1 -> #REF! | B81: =COUNTIF('Loyd List 1-190 - Edit'!$R$3:$R$184,'Data check lookup table'!A81) -> 0
A82: =A81+1 -> #REF! | B82: =COUNTIF('Loyd List 1-190 - Edit'!$R$3:$R$184,'Data check lookup table'!A82) -> 0
A83: =A82+1 -> #REF! | B83: =COUNTIF('Loyd List 1-190 - Edit'!$R$3:$R$184,'Data check lookup table'!A83) -> 0
A84: =A83+1 -> #REF! | B84: =COUNTIF('Loyd List 1-190 - Edit'!$R$3:$R$184,'Data check lookup table'!A84) -> 0
A85: =A84+1 -> #REF! | B85: =COUNTIF('Loyd List 1-190 - Edit'!$R$3:$R$184,'Data check lookup table'!A85) -> 0
... A173: =A172+1 -> #REF! | B173: =COUNTIF('Loyd List 1-190 - Edit'!$R$3:$R$184,'Data check lookup table'!A173) -> 0

Sheet Book Details - NO EDIT
B1: 3 | C1: 4 | D1: 5 | E1: 2 | F1: 6 | G1: 7 | H1: 8 | I1: 11 | J1: 13 | K1: 32 | L1: 16 | M1: 12 | N1: =M1 -> 12 | O1: =N1 -> 12 | P1: =O1 -> 12 | Q1: =P1 -> 12 | R1: =Q1 -> 12 | S1: 12 | W1: =LEN(C3) -> 0 | Z1: 4 | AJ1: 12 | AK1: 7 | AX1: 28 | AY1: 13
A2: ='Loyd List 1-190 - Edit'!C1 -> Loyd # | B2: =VLOOKUP($A2,'Loyd List 1-190 - Edit'!$C$1:$AQ$184,'Book Details - NO EDIT'!B$1,FALSE) -> 1st Name | C2: =VLOOKUP($A2,'Loyd List 1-190 - Edit'!$C$1:$AQ$184,'Book Details - NO EDIT'!C$1,FALSE) -> 2nd Name | D2: =VLOOKUP($A2,'Loyd List 1-190 - Edit'!$C$1:$AQ$184,'Book Details - NO EDIT'!D$1,FALSE) -> 3rd Name | E2: =VLOOKUP($A2,'Loyd List 1-190 - Edit'!$C$1:$AQ$184,'Book Details - NO EDIT'!E$1,FALSE) -> Surname | F2: =VLOOKUP($A2,'Loyd List 1-190 - Edit'!$C$1:$AQ$184,'Book Details - NO EDIT'!F$1,FALSE) -> Known as | G2: =VLOOKUP($A2,'Loyd List 1-190 - Edit'!$C$1:$AQ$184,'Book Details - NO EDIT'!G$1,FALSE) -> Year of Birth | H2: =VLOOKUP($A2,'Loyd List 1-190 - Edit'!$C$1:$AQ$184,'Book Details - NO EDIT'!H$1,FALSE) -> Year of Death | I2: =VLOOKUP($A2,'Loyd List 1-190 - Edit'!$C$1:$AQ$184,'Book Details - NO EDIT'!I$1,FALSE) -> Dob Entered | J2: =VLOOKUP($A2,'Loyd List 1-190 - Edit'!$C$1:$AQ$184,'Book Details - NO EDIT'!J$1,FALSE) -> DoD | K2: =VLOOKUP($A2,'Loyd List 1-190 - Edit'!$C$1:$AQ$220,'Book Details - NO EDIT'!K$1,FALSE) -> Sex | L2: =VLOOKUP($A2,'Loyd List 1-190 - Edit'!$C$1:$AQ$184,'Book Details - NO EDIT'!L$1,FALSE) -> Father's Loyd # | M2: GFather's Loyd # | N2: G GFather's Loyd # | O2: GG GFather's Loyd # | P2: GGG GFather's Loyd # | Q2: GGGG GFather's Loyd # | R2: GGGGG GFather's Loyd # | S2: GGGGGG GFather's Loyd # | T2: Generation | U2: Loyd # | V2: Known as & Dates | W2: Known as & Loyd # | X2: Known as & (Dates; & Loyd #) | Y2: Birth Full Name | Z2: Father's name (Known as, Dates, Loyd #) | AA2: Lineage | AB2: Siblings (Number & List) | AC2: Children (Number and list) | AD2: Grandchildren Full List | AE2: Grandchildren (Number & List) Part 1&2 | AF2: Grandchildren (Number & List) Part 3 | AG2: Number of Grandchildren | AH2: Mother | AI2: Husband/Wife | AJ2: =IF(VLOOKUP($A2,'Loyd List 1-190 - Edit'!$C$1:$AQ$184,'Book Details - NO EDIT'!AJ$1,FALSE)="","",(VLOOKUP($A2,'Loyd List 1-190 - Edit'!$C$1:$AQ$184,'Book Details - NO EDIT'!AJ$1,FALSE))) -> DoM | AK2: Marriage Details | AL2: =VLOOKUP(A2,'Updated Bios & Spouse Details'!$A$1:$J$200,5,FALSE) -> Additional Biographical Information (Short address) | AM2: DSP? | AW2: Residency | AX2: Age | AY2: Contact
A3: ='Loyd List 1-190 - Edit'!C3 -> 1 | B3: =VLOOKUP($A3,'Loyd List 1-190 - Edit'!$C$1:$AQ$220,'Book Details - NO EDIT'!B$1,FALSE) -> William | C3: =IF(VLOOKUP($A3,'Loyd List 1-190 - Edit'!$C$1:$AQ$220,'Book Details - NO EDIT'!C$1,FALSE)="","",VLOOKUP($A3,'Loyd List 1-190 - Edit'!$C$1:$AQ$220,'Book Details - NO EDIT'!C$1,FALSE)) | D3: =IF(VLOOKUP($A3,'Loyd List 1-190 - Edit'!$C$1:$AQ$220,'Book Details - NO EDIT'!D$1,FALSE)="","",VLOOKUP($A3,'Loyd List 1-190 - Edit'!$C$1:$AQ$220,'Book Details - NO EDIT'!D$1,FALSE)) | E3: =IF(VLOOKUP($A3,'Loyd List 1-190 - Edit'!$C$1:$AQ$220,'Book Details - NO EDIT'!E$1,FALSE)="","",VLOOKUP($A3,'Loyd List 1-190 - Edit'!$C$1:$AQ$220,'Book Details - NO EDIT'!E$1,FALSE)) -> LLOYD | F3: =IF(VLOOKUP($A3,'Loyd List 1-190 - Edit'!$C$1:$AQ$220,'Book Details - NO EDIT'!F$1,FALSE)="",B3,VLOOKUP($A3,'Loyd List 1-190 - Edit'!$C$1:$AQ$220,'Book Details - NO EDIT'!F$1,FALSE)) -> William | G3: =IF(VLOOKUP($A3,'Loyd List 1-190 - Edit'!$C$1:$AQ$220,'Book Details - NO EDIT'!G$1,FALSE)="","",VALUE(VLOOKUP($A3,'Loyd List 1-190 - Edit'!$C$1:$AQ$220,'Book Details - NO EDIT'!G$1,FALSE))) -> 1729 | H3: =IF(VLOOKUP($A3,'Loyd List 1-190 - Edit'!$C$1:$AQ$220,'Book Details - NO EDIT'!H$1,FALSE)="","",VALUE(VLOOKUP($A3,'Loyd List 1-190 - Edit'!$C$1:$AQ$220,'Book Details - NO EDIT'!H$1,FALSE))) -> 1800 | I3: =IF(VLOOKUP($A3,'Loyd List 1-190 - Edit'!$C$1:$AQ$220,'Book Details - NO EDIT'!I$1,FALSE)="","",(VLOOKUP($A3,'Loyd List 1-190 - Edit'!$C$1:$AQ$220,'Book Details - NO EDIT'!I$1,FALSE))) -> 20/09/1729 | J3: =IF(VLOOKUP($A3,'Loyd List 1-190 - Edit'!$C$1:$AQ$220,'Book Details - NO EDIT'!J$1,FALSE)="","",(VLOOKUP($A3,'Loyd List 1-190 - Edit'!$C$1:$AQ$220,'Book Details - NO EDIT'!J$1,FALSE))) -> 13/05/1800 | K3: =VLOOKUP($A3,'Loyd List 1-190 - Edit'!$C$1:$AQ$220,'Book Details - NO EDIT'!K$1,FALSE) -> Boy | L3: =VLOOKUP($A3,'Loyd List 1-190 - Edit'!$C$1:$AQ$220,'Book Details - NO EDIT'!L$1,FALSE) -> 0 | M3: Thomas Lloyd (1642–1725: #-1) | N3: =IF(ISNA(VLOOKUP(M3,$A$3:$L$220,N$1,FALSE)),"",(VLOOKUP(M3,$A$3:$L$220,N$1,FALSE))) | O3: =IF(ISNA(VLOOKUP(N3,$A$3:$L$220,O$1,FALSE)),"",(VLOOKUP(N3,$A$3:$L$220,O$1,FALSE))) | P3: =IF(ISNA(VLOOKUP(O3,$A$3:$L$220,P$1,FALSE)),"",(VLOOKUP(O3,$A$3:$L$220,P$1,FALSE))) | Q3: =IF(ISNA(VLOOKUP(P3,$A$3:$L$220,Q$1,FALSE)),"",(VLOOKUP(P3,$A$3:$L$220,Q$1,FALSE))) | R3: =IF(ISNA(VLOOKUP(Q3,$A$3:$L$220,R$1,FALSE)),"",(VLOOKUP(Q3,$A$3:$L$220,R$1,FALSE))) | S3: =IF(ISNA(VLOOKUP(R3,$A$3:$L$220,S$1,FALSE)),"",(VLOOKUP(R3,$A$3:$L$220,S$1,FALSE))) | T3: =IF(L3=1,1,IF(M3=1,2,IF(N3=1,3,IF(O3=1,4,IF(P3=1,5,IF(Q3=1,6,IF(R3=1,7,IF(S3=1,8,0)))))))) -> 0 | U3: =A3 -> 1 | V3: =_xlfn.CONCAT(F3," (",G3,"–",H3,")") -> William (1729–1800) | W3: =_xlfn.CONCAT(F3," (#",A3,")") -> William (#1) | X3: =_xlfn.CONCAT(F3," (",G3,"–",H3,": #",A3,")") -> William (1729–1800: #1) | Y3: =_xlfn.CONCAT(B3," ",IF(C3="",E3,_xlfn.CONCAT(C3," ",IF(D3="",E3,_xlfn.CONCAT(D3," ",E3))))) -> William LLOYD | Z3: Lewis Lloyd (c1690–1758: #0) | AA3: Lewis Lloyd (c1690 –1758; #0) Thomas Lloyd (1642–1725: #-1) | AB3: =VLOOKUP(U3,'Siblings of those BORN Loyd'!$A$2:$G$230,7,FALSE) -> 5 – Gwenllian Lloyd (1719 - c1800) Edward Lloyd (1721 - 1751) Elizabeth Lloyd (1726 - 1777) Jane Lloyd (recorded living in 1766) Catherine Lloyd (recorded living in 1766) | AC3: =IF(ISNA(IF(K3="Boy",VLOOKUP(A3,'Siblings of those BORN Loyd'!$AP$3:$AQ$70,2,FALSE),VLOOKUP(A3,'Children of Female Loyds'!$AR$5:$AT$60,3,FALSE))),AM3,IF(K3="Boy",VLOOKUP(A3,'Siblings of those BORN Loyd'!$AP$3:$AQ$70,2,FALSE),VLOOKUP(A3,'Children of Female Loyds'!$AR$5:$AT$60,3,FALSE))) -> 7 - Jane (1765–1832: #2); Lewis LOYD (1768–1858: #3); William (1770–1828: #4); Catherine (1772–1798: #5); Thomas (1775–1853: #6); Gwenllian (1777–1779: #7); Edward (1780–1863: #8) | AD3: =IF(AE3="d.s.p",_xlfn.CONCAT(AE3,"."),IF(AG3=0,"-",_xlfn.CONCAT(AG3," - ",AE3," ",AF3))) -> 19 - Samuel (1796–1883: #9); William (1809–1879: #10); Sarah (1810–1858: #11); Eliza (1810–1861: #12); Lewis (1811–1891: #13); Thomas (1812–1857: #14); Annie (1813–1834: #15); Maria (1814–1900: #16); Edward (1815–1815: #17); Kate (1815–1905: #18); Hannah (1817–1907: #19); John (1817–1818: #20); Lewis (1819–1841: #21); Edward (1820–1890: #22) ;William (1821–1885: #23); Fanny (1824–1856: #24) Lewis DAVIES or DANIEL (Unknown - Unknown: #2a) Ann DAVIES or DANIEL (Unknown - Unknown: #2b) William DAVIES or DANIEL (1800 - 1832: #2c) | AE3: =IF(ISNA(IF(K3="Boy",VLOOKUP(A3,'Grandchildren of Male Loyds'!$AQ$3:$AS$51,3,FALSE),VLOOKUP(A3,'Grandchildren of Female Loyds'!$AX$5:$AZ$63,3,FALSE))),AM3,IF(K3="Boy",VLOOKUP(A3,'Grandchildren of Male Loyds'!$AQ$3:$AS$51,3,FALSE),VLOOKUP(A3,'Grandchildren of Female Loyds'!$AX$5:$AZ$63,3,FALSE))) -> Samuel (1796–1883: #9); William (1809–1879: #10); Sarah (1810–1858: #11); Eliza (1810–1861: #12); Lewis (1811–1891: #13); Thomas (1812–1857: #14); Annie (1813–1834: #15); Maria (1814–1900: #16); Edward (1815–1815: #17); Kate (1815–1905: #18); Hannah (1817–1907: #19); John (1817–1818: #20); Lewis (1819–1841: #21); Edward (1820–1890: #22) ;William (1821–1885: #23); Fanny (1824–1856: #24) | AF3: =IF(ISNA(VLOOKUP(A3,'Grandchildren Loyd Daughters'!$BD$5:$BF$50,4,FALSE)),"",VLOOKUP(A3,'Grandchildren Loyd Daughters'!$BD$5:$BF$50,3,FALSE)) -> Lewis DAVIES or DANIEL (Unknown - Unknown: #2a) Ann DAVIES or DANIEL (Unknown - Unknown: #2b) William DAVIES or DANIEL (1800 - 1832: #2c) | AG3: =IF(ISNA(VLOOKUP(A3,'Grandchildren of Male Loyds'!$AQ$3:$AR$60,2,FALSE)),0,VLOOKUP(A3,'Grandchildren of Male Loyds'!$AQ$3:$AR$60,2,FALSE))+IF(ISNA(VLOOKUP(A3,'Grandchildren of Female Loyds'!$AX$5:$AY$50,2,FALSE)),0,VLOOKUP(A3,'Grandchildren of Female Loyds'!$AX$5:$AY$50,2,FALSE))+IF(ISNA(VLOOKUP(A3,'Grandchildren Loyd Daughters'!$BD$5:$BE$50,2,FALSE)),0,VLOOKUP(A3,'Grandchildren Loyd Daughters'!$BD$5:$BE$50,2,FALSE)) -> 19 | AH3: =VLOOKUP($U3,'Loyd List 1-190 - Edit'!$P$3:$AJ$220,21,FALSE) -> Jane (b. , d. 26/11/1761) | AI3: =VLOOKUP(A3,'Updated Bios & Spouse Details'!$A$1:$J$200,7,FALSE) -> Anne WILLIAM (b. 1738 , d. 24 May 1801) | AJ3: =IF(VLOOKUP($A3,'Loyd List 1-190 - Edit'!$C$1:$AQ$220,'Book Details - NO EDIT'!AJ$1,FALSE)="","",(VLOOKUP($A3,'Loyd List 1-190 - Edit'!$C$1:$AQ$220,'Book Details - NO EDIT'!AJ$1,FALSE))) -> 03/01/1765 | AK3: =VLOOKUP(A3,'Updated Bios & Spouse Details'!$A$1:$J$200,8,FALSE) -> Married Anne at Llanfair-ar-y-bryn, Llandovery, daughter of John WILLIAM of Llanfair-ar-y-bryn, Llandovery. Anne buried 28 May 1801 at Cilycwm. | AL3: =VLOOKUP(A3,'Updated Bios & Spouse Details'!$A$1:$J$200,5,FALSE) -> Yeoman of Cwm-y-to fach and afterwards (1795) of Court Henry [1] in the parish of Cilycwm, Carmarthenshire. 3rd and youngest son of Lewis LLOYD (c.1690–1758: #0) [2] of Cwm-y-to fach in the parish of Llanwrda. Baptised 20 Sep 1729 at Llanwrda. Died 13 May 1800. Buried 16 May 1800 at Cilycwm. Issue: 3 daughters, 4 sons. Will dated 8 July 1799, proved 24 May 1800 at Carmarthen. Original in National Library of Wales, Aberystwyth. Churchwarden Llanwrda 1766 and 1791 Tombstone in Cilycwm Churchyard. Issue: 4 sons, 3 daughters. Footnote: [1] Court Henry (spelt CWRT HENRY on first Ordnance Survey maps printed in 1865) was sold by Lord Overstone in 1881 for £1,000. [2] Lewis Lloyd died 24 Aug 1758. Buried 25 or 26 Aug 1758 at Llanwrda. Lewis' will dated 8 Jan 1757, proved 10 Jul 1760. Total assets £12-3 shillings. Original in the National Library of Wales, Aberystwyth (Testators’ Wills index St David’s Diocese). | AM3: =IF(AND(LEN(H3)>0,ISNA(IF(K3="Boy",VLOOKUP(A3,'Siblings of those BORN Loyd'!$AP$3:$AQ$70,2,FALSE),VLOOKUP(A3,'Children of Female Loyds'!$AR$5:$AS$60,2,FALSE)))),"d.s.p","") | AW3: =VLOOKUP(A3,'Updated Bios & Spouse Details'!$A$1:$J$193,6,FALSE) -> Wales | AX3: =VLOOKUP($A3,'Loyd List 1-190 - Edit'!$P$2:$AQ$220,AX$1,FALSE) -> 1 | AY3: =IF(ISNA(VLOOKUP(A3,'Data check lookup table'!$G$2:$V$73,13,FALSE))," - ",VLOOKUP(A3,'Data check lookup table'!$G$2:$V$73,13,FALSE)) -> - | AZ3: =TEXT(J3,"dd/mm/yyyy") -> 13/05/1800 | BI3: 13/05/1800
A4: ='Loyd List 1-190 - Edit'!C4 -> 2 | B4: =VLOOKUP($A4,'Loyd List 1-190 - Edit'!$C$1:$AQ$220,'Book Details - NO EDIT'!B$1,FALSE) -> Jane | C4: =IF(VLOOKUP($A4,'Loyd List 1-190 - Edit'!$C$1:$AQ$220,'Book Details - NO EDIT'!C$1,FALSE)="","",VLOOKUP($A4,'Loyd List 1-190 - Edit'!$C$1:$AQ$220,'Book Details - NO EDIT'!C$1,FALSE)) | D4: =IF(VLOOKUP($A4,'Loyd List 1-190 - Edit'!$C$1:$AQ$220,'Book Details - NO EDIT'!D$1,FALSE)="","",VLOOKUP($A4,'Loyd List 1-190 - Edit'!$C$1:$AQ$220,'Book Details - NO EDIT'!D$1,FALSE)) | E4: =IF(VLOOKUP($A4,'Loyd List 1-190 - Edit'!$C$1:$AQ$220,'Book Details - NO EDIT'!E$1,FALSE)="","",VLOOKUP($A4,'Loyd List 1-190 - Edit'!$C$1:$AQ$220,'Book Details - NO EDIT'!E$1,FALSE)) -> LLOYD | F4: =IF(VLOOKUP($A4,'Loyd List 1-190 - Edit'!$C$1:$AQ$220,'Book Details - NO EDIT'!F$1,FALSE)="",B4,VLOOKUP($A4,'Loyd List 1-190 - Edit'!$C$1:$AQ$220,'Book Details - NO EDIT'!F$1,FALSE)) -> Jane | G4: =IF(VLOOKUP($A4,'Loyd List 1-190 - Edit'!$C$1:$AQ$220,'Book Details - NO EDIT'!G$1,FALSE)="","",VALUE(VLOOKUP($A4,'Loyd List 1-190 - Edit'!$C$1:$AQ$220,'Book Details - NO EDIT'!G$1,FALSE))) -> 1765 | H4: =IF(VLOOKUP($A4,'Loyd List 1-190 - Edit'!$C$1:$AQ$220,'Book Details - NO EDIT'!H$1,FALSE)="","",VALUE(VLOOKUP($A4,'Loyd List 1-190 - Edit'!$C$1:$AQ$220,'Book Details - NO EDIT'!H$1,FALSE))) -> 1832 | I4: =IF(VLOOKUP($A4,'Loyd List 1-190 - Edit'!$C$1:$AQ$220,'Book Details - NO EDIT'!I$1,FALSE)="","",(VLOOKUP($A4,'Loyd List 1-190 - Edit'!$C$1:$AQ$220,'Book Details - NO EDIT'!I$1,FALSE))) -> 29/10/1765 | J4: =IF(VLOOKUP($A4,'Loyd List 1-190 - Edit'!$C$1:$AQ$220,'Book Details - NO EDIT'!J$1,FALSE)="","",(VLOOKUP($A4,'Loyd List 1-190 - Edit'!$C$1:$AQ$220,'Book Details - NO EDIT'!J$1,FALSE))) -> 11/05/1832 | K4: =VLOOKUP($A4,'Loyd List 1-190 - Edit'!$C$1:$AQ$220,'Book Details - NO EDIT'!K$1,FALSE) -> Girl | L4: =VLOOKUP($A4,'Loyd List 1-190 - Edit'!$C$1:$AQ$220,'Book Details - NO EDIT'!L$1,FALSE) -> 1 | M4: =IF(ISNA(VLOOKUP(L4,$A$3:$L$220,M$1,FALSE)),"",(VLOOKUP(L4,$A$3:$L$220,M$1,FALSE))) -> 0 | N4: =IF(ISNA(VLOOKUP(M4,$A$3:$L$220,N$1,FALSE)),"",(VLOOKUP(M4,$A$3:$L$220,N$1,FALSE))) | O4: =IF(ISNA(VLOOKUP(N4,$A$3:$L$220,O$1,FALSE)),"",(VLOOKUP(N4,$A$3:$L$220,O$1,FALSE))) | P4: =IF(ISNA(VLOOKUP(O4,$A$3:$L$220,P$1,FALSE)),"",(VLOOKUP(O4,$A$3:$L$220,P$1,FALSE))) | Q4: =IF(ISNA(VLOOKUP(P4,$A$3:$L$220,Q$1,FALSE)),"",(VLOOKUP(P4,$A$3:$L$220,Q$1,FALSE))) | R4: =IF(ISNA(VLOOKUP(Q4,$A$3:$L$220,R$1,FALSE)),"",(VLOOKUP(Q4,$A$3:$L$220,R$1,FALSE))) | S4: =IF(ISNA(VLOOKUP(R4,$A$3:$L$220,S$1,FALSE)),"",(VLOOKUP(R4,$A$3:$L$220,S$1,FALSE))) | T4: =IF(L4=1,1,IF(M4=1,2,IF(N4=1,3,IF(O4=1,4,IF(P4=1,5,IF(Q4=1,6,IF(R4=1,7,IF(S4=1,8,0)))))))) -> 1 | U4: =A4 -> 2 | V4: =_xlfn.CONCAT(F4," (",G4,"–",H4,")") -> Jane (1765–1832) | W4: =_xlfn.CONCAT(F4," (#",A4,")") -> Jane (#2) | X4: =_xlfn.CONCAT(F4," (",G4,"–",H4,": #",A4,")") -> Jane (1765–1832: #2) | Y4: =_xlfn.CONCAT(B4," ",IF(C4="",E4,_xlfn.CONCAT(C4," ",IF(D4="",E4,_xlfn.CONCAT(D4," ",E4))))) -> Jane LLOYD | Z4: =VLOOKUP(L4,$U$2:$X$230,Z$1,FALSE) -> William (1729–1800: #1) | AA4: =_xlfn.CONCAT(AN4," ",AO4," ",AP4," ",AQ4," ",AR4," ",AS4," ",AT4," ",AU4) -> William (1729–1800: #1) | AB4: =VLOOKUP(U4,'Siblings of those BORN Loyd'!$A$2:$G$230,7,FALSE) -> 6 – Lewis LOYD (1768–1858: #3) William (1770–1828: #4) Catherine (1772–1798: #5) Thomas (1775–1853: #6) Gwenllian (1777–1779: #7) Edward (1780–1863: #8) | AC4: =IF(ISNA(IF(K4="Boy",VLOOKUP(A4,'Siblings of those BORN Loyd'!$AP$3:$AQ$70,2,FALSE),VLOOKUP(A4,'Children of Female Loyds'!$AR$5:$AT$60,3,FALSE))),AM4,IF(K4="Boy",VLOOKUP(A4,'Siblings of those BORN Loyd'!$AP$3:$AQ$70,2,FALSE),VLOOKUP(A4,'Children of Female Loyds'!$AR$5:$AT$60,3,FALSE))) -> 3 - Lewis DAVIES or DANIEL (Unknown - Unknown: #2a) Ann DAVIES or DANIEL (Unknown - Unknown: #2b) William DAVIES or DANIEL (1800 - 1832: #2c) | AD4: =IF(AE4="d.s.p",_xlfn.CONCAT(AE4,"."),IF(AG4=0,"-",_xlfn.CONCAT(AG4," - ",AE4," ",AF4))) -> 2 - William DAVIES (Date unknown -1908: #2aa) Catherine DAVIES (1829 -1866: #2ca) | AE4: =IF(ISNA(IF(K4="Boy",VLOOKUP(A4,'Grandchildren of Male Loyds'!$AQ$3:$AS$51,3,FALSE),VLOOKUP(A4,'Grandchildren of Female Loyds'!$AX$5:$AZ$63,3,FALSE))),AM4,IF(K4="Boy",VLOOKUP(A4,'Grandchildren of Male Loyds'!$AQ$3:$AS$51,3,FALSE),VLOOKUP(A4,'Grandchildren of Female Loyds'!$AX$5:$AZ$63,3,FALSE))) -> William DAVIES (Date unknown -1908: #2aa) Catherine DAVIES (1829 -1866: #2ca) | AF4: =IF(ISNA(VLOOKUP(A4,'Grandchildren Loyd Daughters'!$BD$5:$BF$50,4,FALSE)),"",VLOOKUP(A4,'Grandchildren Loyd Daughters'!$BD$5:$BF$50,3,FALSE)) | AG4: =IF(ISNA(VLOOKUP(A4,'Grandchildren of Male Loyds'!$AQ$3:$AR$60,2,FALSE)),0,VLOOKUP(A4,'Grandchildren of Male Loyds'!$AQ$3:$AR$60,2,FALSE))+IF(ISNA(VLOOKUP(A4,'Grandchildren of Female Loyds'!$AX$5:$AY$50,2,FALSE)),0,VLOOKUP(A4,'Grandchildren of Female Loyds'!$AX$5:$AY$50,2,FALSE))+IF(ISNA(VLOOKUP(A4,'Grandchildren Loyd Daughters'!$BD$5:$BE$50,2,FALSE)),0,VLOOKUP(A4,'Grandchildren Loyd Daughters'!$BD$5:$BE$50,2,FALSE)) -> 2 | AH4: =VLOOKUP($U4,'Loyd List 1-190 - Edit'!$P$3:$AJ$220,21,FALSE) -> Anne WILLIAM (b. 1738, d. 24 May 1801) | AI4: =VLOOKUP(A4,'Updated Bios & Spouse Details'!$A$1:$J$200,7,FALSE) -> Lewis DANIEL or DAVIES | AJ4: =IF(VLOOKUP($A4,'Loyd List 1-190 - Edit'!$C$1:$AQ$220,'Book Details - NO EDIT'!AJ$1,FALSE)="","",(VLOOKUP($A4,'Loyd List 1-190 - Edit'!$C$1:$AQ$220,'Book Details - NO EDIT'!AJ$1,FALSE))) -> 03/02/1795 | AK4: =VLOOKUP(A4,'Updated Bios & Spouse Details'!$A$1:$J$200,8,FALSE) -> Married at Llanwrda,Lewis of Caio, Carmarthenshire, Yeoman, afterwards of Court Henry after her father’s death in 1800. | AL4: =VLOOKUP(A4,'Updated Bios & Spouse Details'!$A$1:$J$200,5,FALSE) -> Jane was the eldest daughter of William LLOYD (1729–1800: #1) of Court Henry, Cilycwm, Carmarthenshire. b. 29 Oct 1765, baptised 4 or 9 Nov 1765 at Llanwrda. Died 11 May 1832, buried at Cilycwm. Issue: 2 sons 1 daughter. | AM4: =IF(AND(LEN(H4)>0,ISNA(IF(K4="Boy",VLOOKUP(A4,'Siblings of those BORN Loyd'!$AP$3:$AQ$70,2,FALSE),VLOOKUP(A4,'Children of Female Loyds'!$AR$5:$AS$60,2,FALSE)))),"d.s.p","") | AN4: =(IF(OR(L4=0,LEN(L4)=0),"",_xlfn.CONCAT(VLOOKUP(L4,$U$3:$X$230,4,FALSE)))) -> William (1729–1800: #1) | AO4: =(IF(OR(M4=0,LEN(M4)=0),"",_xlfn.CONCAT(VLOOKUP(M4,$U$3:$X$230,4,FALSE)))) | AP4: =(IF(OR(N4=0,LEN(N4)=0),"",_xlfn.CONCAT(VLOOKUP(N4,$U$3:$X$230,4,FALSE)))) | AQ4: =(IF(OR(O4=0,LEN(O4)=0),"",_xlfn.CONCAT(VLOOKUP(O4,$U$3:$X$230,4,FALSE)))) | AR4: =(IF(OR(P4=0,LEN(P4)=0),"",_xlfn.CONCAT(VLOOKUP(P4,$U$3:$X$230,4,FALSE)))) | AS4: =(IF(OR(Q4=0,LEN(Q4)=0),"",_xlfn.CONCAT(VLOOKUP(Q4,$U$3:$X$230,4,FALSE)))) | AT4: =(IF(OR(R4=0,LEN(R4)=0),"",_xlfn.CONCAT(VLOOKUP(R4,$U$3:$X$230,4,FALSE)))) | AU4: =(IF(OR(S4=0,LEN(S4)=0),"",_xlfn.CONCAT(VLOOKUP(S4,$U$3:$X$230,4,FALSE)))) | AW4: =VLOOKUP(A4,'Updated Bios & Spouse Details'!$A$1:$J$193,6,FALSE) -> Wales | AX4: =VLOOKUP($A4,'Loyd List 1-190 - Edit'!$P$2:$AQ$220,AX$1,FALSE) -> 2 | AY4: =IF(ISNA(VLOOKUP(A4,'Data check lookup table'!$G$2:$V$73,13,FALSE))," - ",VLOOKUP(A4,'Data check lookup table'!$G$2:$V$73,13,FALSE)) -> - | AZ4: =TEXT(J4,"dd/mm/yyyy") -> 11/05/1832 | BA4: =(IF(OR(Q4=0,LEN(Q4)=0),"",_xlfn.CONCAT(", ",VLOOKUP(Q4,$U$3:$X$230,4,FALSE)))) | BB4: =(IF(OR(R4=0,LEN(R4)=0),"",_xlfn.CONCAT("; ",VLOOKUP(R4,$U$3:$X$230,4,FALSE)))) | BI4: 11/05/1832
A5: ='Loyd List 1-190 - Edit'!C5 -> 3 | B5: =VLOOKUP($A5,'Loyd List 1-190 - Edit'!$C$1:$AQ$220,'Book Details - NO EDIT'!B$1,FALSE) -> Lewis | C5: =IF(VLOOKUP($A5,'Loyd List 1-190 - Edit'!$C$1:$AQ$220,'Book Details - NO EDIT'!C$1,FALSE)="","",VLOOKUP($A5,'Loyd List 1-190 - Edit'!$C$1:$AQ$220,'Book Details - NO EDIT'!C$1,FALSE)) | D5: =IF(VLOOKUP($A5,'Loyd List 1-190 - Edit'!$C$1:$AQ$220,'Book Details - NO EDIT'!D$1,FALSE)="","",VLOOKUP($A5,'Loyd List 1-190 - Edit'!$C$1:$AQ$220,'Book Details - NO EDIT'!D$1,FALSE)) | E5: =IF(VLOOKUP($A5,'Loyd List 1-190 - Edit'!$C$1:$AQ$220,'Book Details - NO EDIT'!E$1,FALSE)="","",VLOOKUP($A5,'Loyd List 1-190 - Edit'!$C$1:$AQ$220,'Book Details - NO EDIT'!E$1,FALSE)) -> LOYD | F5: =IF(VLOOKUP($A5,'Loyd List 1-190 - Edit'!$C$1:$AQ$220,'Book Details - NO EDIT'!F$1,FALSE)="",B5,VLOOKUP($A5,'Loyd List 1-190 - Edit'!$C$1:$AQ$220,'Book Details - NO EDIT'!F$1,FALSE)) -> Lewis LOYD | G5: =IF(VLOOKUP($A5,'Loyd List 1-190 - Edit'!$C$1:$AQ$220,'Book Details - NO EDIT'!G$1,FALSE)="","",VALUE(VLOOKUP($A5,'Loyd List 1-190 - Edit'!$C$1:$AQ$220,'Book Details - NO EDIT'!G$1,FALSE))) -> 1768 | H5: =IF(VLOOKUP($A5,'Loyd List 1-190 - Edit'!$C$1:$AQ$220,'Book Details - NO EDIT'!H$1,FALSE)="","",VALUE(VLOOKUP($A5,'Loyd List 1-190 - Edit'!$C$1:$AQ$220,'Book Details - NO EDIT'!H$1,FALSE))) -> 1858 | I5: =IF(VLOOKUP($A5,'Loyd List 1-190 - Edit'!$C$1:$AQ$220,'Book Details - NO EDIT'!I$1,FALSE)="","",(VLOOKUP($A5,'Loyd List 1-190 - Edit'!$C$1:$AQ$220,'Book Details - NO EDIT'!I$1,FALSE))) -> 01/01/1768 | J5: =IF(VLOOKUP($A5,'Loyd List 1-190 - Edit'!$C$1:$AQ$220,'Book Details - NO EDIT'!J$1,FALSE)="","",(VLOOKUP($A5,'Loyd List 1-190 - Edit'!$C$1:$AQ$220,'Book Details - NO EDIT'!J$1,FALSE))) -> 13/05/1858 | K5: =VLOOKUP($A5,'Loyd List 1-190 - Edit'!$C$1:$AQ$220,'Book Details - NO EDIT'!K$1,FALSE) -> Boy | L5: =VLOOKUP($A5,'Loyd List 1-190 - Edit'!$C$1:$AQ$220,'Book Details - NO EDIT'!L$1,FALSE) -> 1 | M5: =IF(ISNA(VLOOKUP(L5,$A$3:$L$220,M$1,FALSE)),"",(VLOOKUP(L5,$A$3:$L$220,M$1,FALSE))) -> 0 | N5: =IF(ISNA(VLOOKUP(M5,$A$3:$L$220,N$1,FALSE)),"",(VLOOKUP(M5,$A$3:$L$220,N$1,FALSE))) | O5: =IF(ISNA(VLOOKUP(N5,$A$3:$L$220,O$1,FALSE)),"",(VLOOKUP(N5,$A$3:$L$220,O$1,FALSE))) | P5: =IF(ISNA(VLOOKUP(O5,$A$3:$L$220,P$1,FALSE)),"",(VLOOKUP(O5,$A$3:$L$220,P$1,FALSE))) | Q5: =IF(ISNA(VLOOKUP(P5,$A$3:$L$220,Q$1,FALSE)),"",(VLOOKUP(P5,$A$3:$L$220,Q$1,FALSE))) | R5: =IF(ISNA(VLOOKUP(Q5,$A$3:$L$220,R$1,FALSE)),"",(VLOOKUP(Q5,$A$3:$L$220,R$1,FALSE))) | S5: =IF(ISNA(VLOOKUP(R5,$A$3:$L$220,S$1,FALSE)),"",(VLOOKUP(R5,$A$3:$L$220,S$1,FALSE))) | T5: =IF(L5=1,1,IF(M5=1,2,IF(N5=1,3,IF(O5=1,4,IF(P5=1,5,IF(Q5=1,6,IF(R5=1,7,IF(S5=1,8,0)))))))) -> 1 | U5: =A5 -> 3 | V5: =_xlfn.CONCAT(F5," (",G5,"–",H5,")") -> Lewis LOYD (1768–1858) | W5: =_xlfn.CONCAT(F5," (#",A5,")") -> Lewis LOYD (#3) | X5: =_xlfn.CONCAT(F5," (",G5,"–",H5,": #",A5,")") -> Lewis LOYD (1768–1858: #3) | Y5: =_xlfn.CONCAT(B5," ",IF(C5="",E5,_xlfn.CONCAT(C5," ",IF(D5="",E5,_xlfn.CONCAT(D5," ",E5))))) -> Lewis LOYD | Z5: =VLOOKUP(L5,$U$2:$X$230,Z$1,FALSE) -> William (1729–1800: #1) | AA5: =_xlfn.CONCAT(AN5," ",AO5," ",AP5," ",AQ5," ",AR5," ",AS5," ",AT5," ",AU5) -> William (1729–1800: #1) | AB5: =VLOOKUP(U5,'Siblings of those BORN Loyd'!$A$2:$G$230,7,FALSE) -> 6 – Jane (1765–1832: #2) William (1770–1828: #4) Catherine (1772–1798: #5) Thomas (1775–1853: #6) Gwenllian (1777–1779: #7) Edward (1780–1863: #8) | AC5: =IF(ISNA(IF(K5="Boy",VLOOKUP(A5,'Siblings of those BORN Loyd'!$AP$3:$AQ$70,2,FALSE),VLOOKUP(A5,'Children of Female Loyds'!$AR$5:$AT$60,3,FALSE))),AM5,IF(K5="Boy",VLOOKUP(A5,'Siblings of those BORN Loyd'!$AP$3:$AQ$70,2,FALSE),VLOOKUP(A5,'Children of Female Loyds'!$AR$5:$AT$60,3,FALSE))) -> 1 - Samuel (1796–1883: #9) | AD5: =IF(AE5="d.s.p",_xlfn.CONCAT(AE5,"."),IF(AG5=0,"-",_xlfn.CONCAT(AG5," - ",AE5," ",AF5))) -> 2 - Henry (1832–1833: #25); The Hon Harriet (1837–1920: #26) | AE5: =IF(ISNA(IF(K5="Boy",VLOOKUP(A5,'Grandchildren of Male Loyds'!$AQ$3:$AS$51,3,FALSE),VLOOKUP(A5,'Grandchildren of Female Loyds'!$AX$5:$AZ$63,3,FALSE))),AM5,IF(K5="Boy",VLOOKUP(A5,'Grandchildren of Male Loyds'!$AQ$3:$AS$51,3,FALSE),VLOOKUP(A5,'Grandchildren of Female Loyds'!$AX$5:$AZ$63,3,FALSE))) -> Henry (1832–1833: #25); The Hon Harriet (1837–1920: #26) | AF5: =IF(ISNA(VLOOKUP(A5,'Grandchildren Loyd Daughters'!$BD$5:$BF$50,4,FALSE)),"",VLOOKUP(A5,'Grandchildren Loyd Daughters'!$BD$5:$BF$50,3,FALSE)) | AG5: =IF(ISNA(VLOOKUP(A5,'Grandchildren of Male Loyds'!$AQ$3:$AR$60,2,FALSE)),0,VLOOKUP(A5,'Grandchildren of Male Loyds'!$AQ$3:$AR$60,2,FALSE))+IF(ISNA(VLOOKUP(A5,'Grandchildren of Female Loyds'!$AX$5:$AY$50,2,FALSE)),0,VLOOKUP(A5,'Grandchildren of Female Loyds'!$AX$5:$AY$50,2,FALSE))+IF(ISNA(VLOOKUP(A5,'Grandchildren Loyd Daughters'!$BD$5:$BE$50,2,FALSE)),0,VLOOKUP(A5,'Grandchildren Loyd Daughters'!$BD$5:$BE$50,2,FALSE)) -> 2 | AH5: =VLOOKUP($U5,'Loyd List 1-190 - Edit'!$P$3:$AJ$220,21,FALSE) -> Anne WILLIAM (b. 1738, d. 24 May 1801) | AI5: =VLOOKUP(A5,'Updated Bios & Spouse Details'!$A$1:$J$200,7,FALSE) -> (1) Sarah JONES 7 (b. 9 Sep 1759, d. 1 Oct 1821). | AJ5: =IF(VLOOKUP($A5,'Loyd List 1-190 - Edit'!$C$1:$AQ$220,'Book Details - NO EDIT'!AJ$1,FALSE)="","",(VLOOKUP($A5,'Loyd List 1-190 - Edit'!$C$1:$AQ$220,'Book Details - NO EDIT'!AJ$1,FALSE))) -> 11/11/1793 | AK5: =VLOOKUP(A5,'Updated Bios & Spouse Details'!$A$1:$J$200,8,FALSE) -> (1) 11 Nov 1793 Sarah (b. 9 Sep 1759, d. 1 Oct 1821) at Broughton New Hall, daughter of John JONES (1713-75) banker and Tea dealer of Manchester and founder of the King Street Bank. Sarah buried at Cross Street Chapel, Manchester. (2) Married Mrs. Mary CHAMPION (d. 1 Feb 1835) on 21 Jan 1823. | AL5: =VLOOKUP(A5,'Updated Bios & Spouse Details'!$A$1:$J$200,5,FALSE) -> Lewis lived at 43 Lothbury, London and of Overstone Park, Northamptonshire. Eldest son of William LLOYD (1729–1800: #1) of Court Henry, Cilycwm, Carmarthenshire. Born 1 Jan 1768, baptised 5 Jan 1768 at Llanwrda. Educated at Mr. David PRICE’s school [5] at Llanycrwys near Lampeter and at the Presbyterian Academy of Carmarthen, Swansea (1785-89). Rode to Manchester in September 1789. Entered Manchester Unitarian College. Appointed Tutor in Belle Letters at Manchester 1790-92. Became Supply Preacher at Dob Lane Chapel, Failsworth, Manchester [6]. Also preached at Blackley where he met his future wife, Sarah Jones. Lewis joined the Bank before relocating to the London branch as partner with Daniel, Jones, Barker, Loyd & Co. 1793. Jones, Loyd, Hulme & Co. 1798. Jones, Loyd & Co. 1808. Retired from Bank 1844. Changed the family name to LOYD about 1795. Obtained the grant of arms 10 Apr 1835 on his appointment as High Sheriff of Northamptonshire, and registered it at the College of Arms in the name of his father in order to include his brothers and their descendants. Died 13 May 1858 at Overstone, buried at Overstone. Will dated 21 Nov 1843. Estate left to Lord OVERSTONE:- Land £1,172,091, Securities £701,102, Personal effects £5,639. Issue: (1st wife) 1 son (who later became Lord OVERSTONE). Portrait by Eden Upton EDDIS in possession of Christopher Lewis LOYD (1923–2013: #100). Able and far-sighted to a degree, this extraordinary man (Lewis LOYD), of whom unfortunately not very much is known, was endowed with a biting wit; when, in 1828, Frys & Chapman - Joseph Fry was the husband of the great reformer Mrs Elizabeth Fry (nee Gurney) - had to close its doors, he told a Quaker client who had been wise enough previously to withdraw his money and to entrust it to a “more sophisticated house”, “Thou wer’t right, friend: it is wiser to place thy money with a rich sinner than with a poor saint.” Overstone Library, Reading University. Footnotes: [5] When David PRICE’s youngest son, Lewis, died in London, his old pupil, Lewis LOYD, was at his bedside. [6] “At the time in question.....to get to Dob Lane Chapel from the College was quite a journey. Lewis Loyd made his way to it Sunday by Sunday, upon the identical little white pony which had carried him from Carmarthenshire to Manchester, trotting, not along a wearily-extended street, but between hedgerows and pastures. It was a wild and rebellious little animal, and until the time for its master’s return to Dawson Street in the evening, was turned into a meadow belonging to a Mr Barrett, a leading man at Dob Lane Chapel, and at whose house Lewis Loyd was usually the welcome guest. Another leading member of the Dob Lane congregation was a Mr Samuel Taylor, a merchant in Princess Street, whose residence was at Moston. It was from this old gentleman, if tradition be trustworthy, that Lewis Loyd received his first lessons in the inestimable and immortal science of how to get rich. Mr Taylor seems to have discovered very early that Lewis had a remarkable gift for figures and accounts. He certainly led him on to a realization of his native powers. Probably it was Mr Taylor who, after service one fine morning, presented the young preacher with a bank note in acknowledgment of the excellent way in which he acquitted himself in the pulpit. Money in those days was a scarce article with the budding Croesus. His salary, it is said, was £40 a year. He thanked the donor cordially, and added that on the same terms he would gladly pray for him every Sunday of the year. Whether it was at this particular period, or a trifle later, that Lewis Loyd was engaged in writing his tract upon Original Sin, there is no evidence to show. (The tract in question was one of a series of ‘Letters to the Inhabitants of Wigan occasioned by the Rev Mr Tawell’s Discourse on the Divinity of Jesus Christ, 1791’. The volume, which is rare, consists of one hundred and sixty pages (size 12mo), twelve of which are Lewis Loyd’s.)” - Grindon p 58-59. Roddy SALE (#97d), in 2021, has portrait of Samuel & William Jones (1746 – 1819) of Greenhill and William Jones (1757 – 1821) who owned Wolvey in Warwickshire (left to Lord Overstone). | AM5: =IF(AND(LEN(H5)>0,ISNA(IF(K5="Boy",VLOOKUP(A5,'Siblings of those BORN Loyd'!$AP$3:$AQ$70,2,FALSE),VLOOKUP(A5,'Children of Female Loyds'!$AR$5:$AS$60,2,FALSE)))),"d.s.p","") | AN5: =(IF(OR(L5=0,LEN(L5)=0),"",_xlfn.CONCAT(VLOOKUP(L5,$U$3:$X$230,4,FALSE)))) -> William (1729–1800: #1) | AO5: =(IF(OR(M5=0,LEN(M5)=0),"",_xlfn.CONCAT(VLOOKUP(M5,$U$3:$X$230,4,FALSE)))) | AP5: =(IF(OR(N5=0,LEN(N5)=0),"",_xlfn.CONCAT(VLOOKUP(N5,$U$3:$X$230,4,FALSE)))) | AQ5: =(IF(OR(O5=0,LEN(O5)=0),"",_xlfn.CONCAT(VLOOKUP(O5,$U$3:$X$230,4,FALSE)))) | AR5: =(IF(OR(P5=0,LEN(P5)=0),"",_xlfn.CONCAT(VLOOKUP(P5,$U$3:$X$230,4,FALSE)))) | AS5: =(IF(OR(Q5=0,LEN(Q5)=0),"",_xlfn.CONCAT(VLOOKUP(Q5,$U$3:$X$230,4,FALSE)))) | AT5: =(IF(OR(R5=0,LEN(R5)=0),"",_xlfn.CONCAT(VLOOKUP(R5,$U$3:$X$230,4,FALSE)))) | AU5: =(IF(OR(S5=0,LEN(S5)=0),"",_xlfn.CONCAT(VLOOKUP(S5,$U$3:$X$230,4,FALSE)))) | AW5: =VLOOKUP(A5,'Updated Bios & Spouse Details'!$A$1:$J$193,6,FALSE) -> Wales & England | AX5: =VLOOKUP($A5,'Loyd List 1-190 - Edit'!$P$2:$AQ$220,AX$1,FALSE) -> 3 | AY5: =IF(ISNA(VLOOKUP(A5,'Data check lookup table'!$G$2:$V$73,13,FALSE))," - ",VLOOKUP(A5,'Data check lookup table'!$G$2:$V$73,13,FALSE)) -> - | AZ5: =TEXT(J5,"dd/mm/yyyy") -> 13/05/1858 | BA5: =(IF(OR(Q5=0,LEN(Q5)=0),"",_xlfn.CONCAT(", ",VLOOKUP(Q5,$U$3:$X$230,4,FALSE)))) | BB5: =(IF(OR(R5=0,LEN(R5)=0),"",_xlfn.CONCAT("; ",VLOOKUP(R5,$U$3:$X$230,4,FALSE)))) | BI5: 13/05/1858
A6: ='Loyd List 1-190 - Edit'!C6 -> 4 | B6: =VLOOKUP($A6,'Loyd List 1-190 - Edit'!$C$1:$AQ$220,'Book Details - NO EDIT'!B$1,FALSE) -> William | C6: =IF(VLOOKUP($A6,'Loyd List 1-190 - Edit'!$C$1:$AQ$220,'Book Details - NO EDIT'!C$1,FALSE)="","",VLOOKUP($A6,'Loyd List 1-190 - Edit'!$C$1:$AQ$220,'Book Details - NO EDIT'!C$1,FALSE)) | D6: =IF(VLOOKUP($A6,'Loyd List 1-190 - Edit'!$C$1:$AQ$220,'Book Details - NO EDIT'!D$1,FALSE)="","",VLOOKUP($A6,'Loyd List 1-190 - Edit'!$C$1:$AQ$220,'Book Details - NO EDIT'!D$1,FALSE)) | E6: =IF(VLOOKUP($A6,'Loyd List 1-190 - Edit'!$C$1:$AQ$220,'Book Details - NO EDIT'!E$1,FALSE)="","",VLOOKUP($A6,'Loyd List 1-190 - Edit'!$C$1:$AQ$220,'Book Details - NO EDIT'!E$1,FALSE)) -> LOYD | F6: =IF(VLOOKUP($A6,'Loyd List 1-190 - Edit'!$C$1:$AQ$220,'Book Details - NO EDIT'!F$1,FALSE)="",B6,VLOOKUP($A6,'Loyd List 1-190 - Edit'!$C$1:$AQ$220,'Book Details - NO EDIT'!F$1,FALSE)) -> William | G6: =IF(VLOOKUP($A6,'Loyd List 1-190 - Edit'!$C$1:$AQ$220,'Book Details - NO EDIT'!G$1,FALSE)="","",VALUE(VLOOKUP($A6,'Loyd List 1-190 - Edit'!$C$1:$AQ$220,'Book Details - NO EDIT'!G$1,FALSE))) -> 1770 | H6: =IF(VLOOKUP($A6,'Loyd List 1-190 - Edit'!$C$1:$AQ$220,'Book Details - NO EDIT'!H$1,FALSE)="","",VALUE(VLOOKUP($A6,'Loyd List 1-190 - Edit'!$C$1:$AQ$220,'Book Details - NO EDIT'!H$1,FALSE))) -> 1828 | I6: =IF(VLOOKUP($A6,'Loyd List 1-190 - Edit'!$C$1:$AQ$220,'Book Details - NO EDIT'!I$1,FALSE)="","",(VLOOKUP($A6,'Loyd List 1-190 - Edit'!$C$1:$AQ$220,'Book Details - NO EDIT'!I$1,FALSE))) -> 07/05/1770 | J6: =IF(VLOOKUP($A6,'Loyd List 1-190 - Edit'!$C$1:$AQ$220,'Book Details - NO EDIT'!J$1,FALSE)="","",(VLOOKUP($A6,'Loyd List 1-190 - Edit'!$C$1:$AQ$220,'Book Details - NO EDIT'!J$1,FALSE))) -> 04/02/1828 | K6: =VLOOKUP($A6,'Loyd List 1-190 - Edit'!$C$1:$AQ$220,'Book Details - NO EDIT'!K$1,FALSE) -> Boy | L6: =VLOOKUP($A6,'Loyd List 1-190 - Edit'!$C$1:$AQ$220,'Book Details - NO EDIT'!L$1,FALSE) -> 1 | M6: =IF(ISNA(VLOOKUP(L6,$A$3:$L$220,M$1,FALSE)),"",(VLOOKUP(L6,$A$3:$L$220,M$1,FALSE))) -> 0 | N6: =IF(ISNA(VLOOKUP(M6,$A$3:$L$220,N$1,FALSE)),"",(VLOOKUP(M6,$A$3:$L$220,N$1,FALSE))) | O6: =IF(ISNA(VLOOKUP(N6,$A$3:$L$220,O$1,FALSE)),"",(VLOOKUP(N6,$A$3:$L$220,O$1,FALSE))) | P6: =IF(ISNA(VLOOKUP(O6,$A$3:$L$220,P$1,FALSE)),"",(VLOOKUP(O6,$A$3:$L$220,P$1,FALSE))) | Q6: =IF(ISNA(VLOOKUP(P6,$A$3:$L$220,Q$1,FALSE)),"",(VLOOKUP(P6,$A$3:$L$220,Q$1,FALSE))) | R6: =IF(ISNA(VLOOKUP(Q6,$A$3:$L$220,R$1,FALSE)),"",(VLOOKUP(Q6,$A$3:$L$220,R$1,FALSE))) | S6: =IF(ISNA(VLOOKUP(R6,$A$3:$L$220,S$1,FALSE)),"",(VLOOKUP(R6,$A$3:$L$220,S$1,FALSE))) | T6: =IF(L6=1,1,IF(M6=1,2,IF(N6=1,3,IF(O6=1,4,IF(P6=1,5,IF(Q6=1,6,IF(R6=1,7,IF(S6=1,8,0)))))))) -> 1 | U6: =A6 -> 4 | V6: =_xlfn.CONCAT(F6," (",G6,"–",H6,")") -> William (1770–1828) | W6: =_xlfn.CONCAT(F6," (#",A6,")") -> William (#4) | X6: =_xlfn.CONCAT(F6," (",G6,"–",H6,": #",A6,")") -> William (1770–1828: #4) | Y6: =_xlfn.CONCAT(B6," ",IF(C6="",E6,_xlfn.CONCAT(C6," ",IF(D6="",E6,_xlfn.CONCAT(D6," ",E6))))) -> William LOYD | Z6: =VLOOKUP(L6,$U$2:$X$230,Z$1,FALSE) -> William (1729–1800: #1) | AA6: =_xlfn.CONCAT(AN6," ",AO6," ",AP6," ",AQ6," ",AR6," ",AS6," ",AT6," ",AU6) -> William (1729–1800: #1) | AB6: =VLOOKUP(U6,'Siblings of those BORN Loyd'!$A$2:$G$230,7,FALSE) -> 6 – Jane (1765–1832: #2) Lewis LOYD (1768–1858: #3) Catherine (1772–1798: #5) Thomas (1775–1853: #6) Gwenllian (1777–1779: #7) Edward (1780–1863: #8) | AC6: =IF(ISNA(IF(K6="Boy",VLOOKUP(A6,'Siblings of those BORN Loyd'!$AP$3:$AQ$70,2,FALSE),VLOOKUP(A6,'Children of Female Loyds'!$AR$5:$AT$60,3,FALSE))),AM6,IF(K6="Boy",VLOOKUP(A6,'Siblings of those BORN Loyd'!$AP$3:$AQ$70,2,FALSE),VLOOKUP(A6,'Children of Female Loyds'!$AR$5:$AT$60,3,FALSE))) -> 7 - William (1809–1879: #10); Eliza (1810–1861: #12); Thomas (1812–1857: #14); Maria (1814–1900: #16); Edward (1815–1815: #17); John (1817–1818: #20); Lewis (1819–1841: #21) | AD6: =IF(AE6="d.s.p",_xlfn.CONCAT(AE6,"."),IF(AG6=0,"-",_xlfn.CONCAT(AG6," - ",AE6," ",AF6))) -> 8 - William (1843–1843: #27); The Rev Lewis (1844–1905: #28); Arthur (1845–1930: #29); Archie (1847–1922: #30); Frank (1848–1934: #32); Alfred (1849–1881: #33); Ted (1851–1922: #34); Annie (1853–1946: #37) | AE6: =IF(ISNA(IF(K6="Boy",VLOOKUP(A6,'Grandchildren of Male Loyds'!$AQ$3:$AS$51,3,FALSE),VLOOKUP(A6,'Grandchildren of Female Loyds'!$AX$5:$AZ$63,3,FALSE))),AM6,IF(K6="Boy",VLOOKUP(A6,'Grandchildren of Male Loyds'!$AQ$3:$AS$51,3,FALSE),VLOOKUP(A6,'Grandchildren of Female Loyds'!$AX$5:$AZ$63,3,FALSE))) -> William (1843–1843: #27); The Rev Lewis (1844–1905: #28); Arthur (1845–1930: #29); Archie (1847–1922: #30); Frank (1848–1934: #32); Alfred (1849–1881: #33); Ted (1851–1922: #34); Annie (1853–1946: #37) | AF6: =IF(ISNA(VLOOKUP(A6,'Grandchildren Loyd Daughters'!$BD$5:$BF$50,4,FALSE)),"",VLOOKUP(A6,'Grandchildren Loyd Daughters'!$BD$5:$BF$50,3,FALSE)) | AG6: =IF(ISNA(VLOOKUP(A6,'Grandchildren of Male Loyds'!$AQ$3:$AR$60,2,FALSE)),0,VLOOKUP(A6,'Grandchildren of Male Loyds'!$AQ$3:$AR$60,2,FALSE))+IF(ISNA(VLOOKUP(A6,'Grandchildren of Female Loyds'!$AX$5:$AY$50,2,FALSE)),0,VLOOKUP(A6,'Grandchildren of Female Loyds'!$AX$5:$AY$50,2,FALSE))+IF(ISNA(VLOOKUP(A6,'Grandchildren Loyd Daughters'!$BD$5:$BE$50,2,FALSE)),0,VLOOKUP(A6,'Grandchildren Loyd Daughters'!$BD$5:$BE$50,2,FALSE)) -> 8 | AH6: =VLOOKUP($U6,'Loyd List 1-190 - Edit'!$P$3:$AJ$220,21,FALSE) -> Anne WILLIAM (b. 1738, d. 24 May 1801) | AI6: =VLOOKUP(A6,'Updated Bios & Spouse Details'!$A$1:$J$200,7,FALSE) -> Martha KIRKMAN (b. 17 Nov 1775, d. 4 Feb 1857) | AJ6: =IF(VLOOKUP($A6,'Loyd List 1-190 - Edit'!$C$1:$AQ$220,'Book Details - NO EDIT'!AJ$1,FALSE)="","",(VLOOKUP($A6,'Loyd List 1-190 - Edit'!$C$1:$AQ$220,'Book Details - NO EDIT'!AJ$1,FALSE))) -> 05/01/1809 | AK6: =VLOOKUP(A6,'Updated Bios & Spouse Details'!$A$1:$J$200,8,FALSE) -> Married Martha, daughter of Thomas KIRKMAN of Manchester, at Manchester Collegiate Church (later Manchester Cathedral). Martha died at 17 Marlborough Place, St John’s Wood, London, and is buried at Kensal Green. | AL6: =VLOOKUP(A6,'Updated Bios & Spouse Details'!$A$1:$J$200,5,FALSE) -> William lived at 7 Bread Street, Cheapside and later of 13 Portland Place, Clapham Road, London. 2nd son of William LLOYD (1729–1800: #1) of Court Henry, Cilycwm, Carmarthenshire. Born 7 May 1770, baptised 11 or 14 May 1770 at Llanwrda. Warehouseman. He was the only one of the four brothers who was unsuccessful in business. The diaries of his son, William Kirkman LOYD (1809-1879: #10), recorded that in 1867 he received from his father’s solicitor various old papers connected with his father’s affairs which he destroyed in 1871 thus removing evidence of the extent of his father’s debts [8]. Died 17 Aug 1828, buried 25 Aug 1828 at Bunhill Fields, London EC1 in family grave (plan 15, grave no. 223). His gold watch is in possession of John Michael LOYD (1938- ). Issue: 5 sons, 2 daughters. Footnote: [8] In Oct 1864, Lord OVERSTONE (Samuel Jones LOYD 1796-1883) wrote “He carried on a concern of his own in which he was uniformly unsuccessful, and thus became the cause of much anxiety and serious loss to the other members of the family. ....To save the name of the family from dishonour it became necessary to discharge his trading debts - about £45,000 - and this burden was borne by the prosperous members of the family in the proportion in which they then shared the profits of the Banking business - ie My Father (#3), Myself (#9), and Mr Edw[ar]d Loyd (#8) - each one third” - O’Brien page 1053. | AM6: =IF(AND(LEN(H6)>0,ISNA(IF(K6="Boy",VLOOKUP(A6,'Siblings of those BORN Loyd'!$AP$3:$AQ$70,2,FALSE),VLOOKUP(A6,'Children of Female Loyds'!$AR$5:$AS$60,2,FALSE)))),"d.s.p","") | AN6: =(IF(OR(L6=0,LEN(L6)=0),"",_xlfn.CONCAT(VLOOKUP(L6,$U$3:$X$230,4,FALSE)))) -> William (1729–1800: #1) | AO6: =(IF(OR(M6=0,LEN(M6)=0),"",_xlfn.CONCAT(VLOOKUP(M6,$U$3:$X$230,4,FALSE)))) | AP6: =(IF(OR(N6=0,LEN(N6)=0),"",_xlfn.CONCAT(VLOOKUP(N6,$U$3:$X$230,4,FALSE)))) | AQ6: =(IF(OR(O6=0,LEN(O6)=0),"",_xlfn.CONCAT(VLOOKUP(O6,$U$3:$X$230,4,FALSE)))) | AR6: =(IF(OR(P6=0,LEN(P6)=0),"",_xlfn.CONCAT(VLOOKUP(P6,$U$3:$X$230,4,FALSE)))) | AS6: =(IF(OR(Q6=0,LEN(Q6)=0),"",_xlfn.CONCAT(VLOOKUP(Q6,$U$3:$X$230,4,FALSE)))) | AT6: =(IF(OR(R6=0,LEN(R6)=0),"",_xlfn.CONCAT(VLOOKUP(R6,$U$3:$X$230,4,FALSE)))) | AU6: =(IF(OR(S6=0,LEN(S6)=0),"",_xlfn.CONCAT(VLOOKUP(S6,$U$3:$X$230,4,FALSE)))) | AW6: =VLOOKUP(A6,'Updated Bios & Spouse Details'!$A$1:$J$193,6,FALSE) -> Wales & England | AX6: =VLOOKUP($A6,'Loyd List 1-190 - Edit'!$P$2:$AQ$220,AX$1,FALSE) -> 4 | AY6: =IF(ISNA(VLOOKUP(A6,'Data check lookup table'!$G$2:$V$73,13,FALSE))," - ",VLOOKUP(A6,'Data check lookup table'!$G$2:$V$73,13,FALSE)) -> - | AZ6: =TEXT(J6,"dd/mm/yyyy") -> 04/02/1828 | BA6: =(IF(OR(Q6=0,LEN(Q6)=0),"",_xlfn.CONCAT(", ",VLOOKUP(Q6,$U$3:$X$230,4,FALSE)))) | BB6: =(IF(OR(R6=0,LEN(R6)=0),"",_xlfn.CONCAT("; ",VLOOKUP(R6,$U$3:$X$230,4,FALSE)))) | BI6: 04/02/1828
A7: ='Loyd List 1-190 - Edit'!C7 -> 5 | B7: =VLOOKUP($A7,'Loyd List 1-190 - Edit'!$C$1:$AQ$220,'Book Details - NO EDIT'!B$1,FALSE) -> Catherine | C7: =IF(VLOOKUP($A7,'Loyd List 1-190 - Edit'!$C$1:$AQ$220,'Book Details - NO EDIT'!C$1,FALSE)="","",VLOOKUP($A7,'Loyd List 1-190 - Edit'!$C$1:$AQ$220,'Book Details - NO EDIT'!C$1,FALSE)) | D7: =IF(VLOOKUP($A7,'Loyd List 1-190 - Edit'!$C$1:$AQ$220,'Book Details - NO EDIT'!D$1,FALSE)="","",VLOOKUP($A7,'Loyd List 1-190 - Edit'!$C$1:$AQ$220,'Book Details - NO EDIT'!D$1,FALSE)) | E7: =IF(VLOOKUP($A7,'Loyd List 1-190 - Edit'!$C$1:$AQ$220,'Book Details - NO EDIT'!E$1,FALSE)="","",VLOOKUP($A7,'Loyd List 1-190 - Edit'!$C$1:$AQ$220,'Book Details - NO EDIT'!E$1,FALSE)) -> LLOYD | F7: =IF(VLOOKUP($A7,'Loyd List 1-190 - Edit'!$C$1:$AQ$220,'Book Details - NO EDIT'!F$1,FALSE)="",B7,VLOOKUP($A7,'Loyd List 1-190 - Edit'!$C$1:$AQ$220,'Book Details - NO EDIT'!F$1,FALSE)) -> Catherine | G7: =IF(VLOOKUP($A7,'Loyd List 1-190 - Edit'!$C$1:$AQ$220,'Book Details - NO EDIT'!G$1,FALSE)="","",VALUE(VLOOKUP($A7,'Loyd List 1-190 - Edit'!$C$1:$AQ$220,'Book Details - NO EDIT'!G$1,FALSE))) -> 1772 | H7: =IF(VLOOKUP($A7,'Loyd List 1-190 - Edit'!$C$1:$AQ$220,'Book Details - NO EDIT'!H$1,FALSE)="","",VALUE(VLOOKUP($A7,'Loyd List 1-190 - Edit'!$C$1:$AQ$220,'Book Details - NO EDIT'!H$1,FALSE))) -> 1798 | I7: =IF(VLOOKUP($A7,'Loyd List 1-190 - Edit'!$C$1:$AQ$220,'Book Details - NO EDIT'!I$1,FALSE)="","",(VLOOKUP($A7,'Loyd List 1-190 - Edit'!$C$1:$AQ$220,'Book Details - NO EDIT'!I$1,FALSE))) -> 19/02/1772 | J7: =IF(VLOOKUP($A7,'Loyd List 1-190 - Edit'!$C$1:$AQ$220,'Book Details - NO EDIT'!J$1,FALSE)="","",(VLOOKUP($A7,'Loyd List 1-190 - Edit'!$C$1:$AQ$220,'Book Details - NO EDIT'!J$1,FALSE))) -> 09/12/1798 | K7: =VLOOKUP($A7,'Loyd List 1-190 - Edit'!$C$1:$AQ$220,'Book Details - NO EDIT'!K$1,FALSE) -> Girl | L7: =VLOOKUP($A7,'Loyd List 1-190 - Edit'!$C$1:$AQ$220,'Book Details - NO EDIT'!L$1,FALSE) -> 1 | M7: =IF(ISNA(VLOOKUP(L7,$A$3:$L$220,M$1,FALSE)),"",(VLOOKUP(L7,$A$3:$L$220,M$1,FALSE))) -> 0 | N7: =IF(ISNA(VLOOKUP(M7,$A$3:$L$220,N$1,FALSE)),"",(VLOOKUP(M7,$A$3:$L$220,N$1,FALSE))) | O7: =IF(ISNA(VLOOKUP(N7,$A$3:$L$220,O$1,FALSE)),"",(VLOOKUP(N7,$A$3:$L$220,O$1,FALSE))) | P7: =IF(ISNA(VLOOKUP(O7,$A$3:$L$220,P$1,FALSE)),"",(VLOOKUP(O7,$A$3:$L$220,P$1,FALSE))) | Q7: =IF(ISNA(VLOOKUP(P7,$A$3:$L$220,Q$1,FALSE)),"",(VLOOKUP(P7,$A$3:$L$220,Q$1,FALSE))) | R7: =IF(ISNA(VLOOKUP(Q7,$A$3:$L$220,R$1,FALSE)),"",(VLOOKUP(Q7,$A$3:$L$220,R$1,FALSE))) | S7: =IF(ISNA(VLOOKUP(R7,$A$3:$L$220,S$1,FALSE)),"",(VLOOKUP(R7,$A$3:$L$220,S$1,FALSE))) | T7: =IF(L7=1,1,IF(M7=1,2,IF(N7=1,3,IF(O7=1,4,IF(P7=1,5,IF(Q7=1,6,IF(R7=1,7,IF(S7=1,8,0)))))))) -> 1 | U7: =A7 -> 5 | V7: =_xlfn.CONCAT(F7," (",G7,"–",H7,")") -> Catherine (1772–1798) | W7: =_xlfn.CONCAT(F7," (#",A7,")") -> Catherine (#5) | X7: =_xlfn.CONCAT(F7," (",G7,"–",H7,": #",A7,")") -> Catherine (1772–1798: #5) | Y7: =_xlfn.CONCAT(B7," ",IF(C7="",E7,_xlfn.CONCAT(C7," ",IF(D7="",E7,_xlfn.CONCAT(D7," ",E7))))) -> Catherine LLOYD | Z7: =VLOOKUP(L7,$U$2:$X$230,Z$1,FALSE) -> William (1729–1800: #1) | AA7: =_xlfn.CONCAT(AN7," ",AO7," ",AP7," ",AQ7," ",AR7," ",AS7," ",AT7," ",AU7) -> William (1729–1800: #1) | AB7: =VLOOKUP(U7,'Siblings of those BORN Loyd'!$A$2:$G$230,7,FALSE) -> 6 – Jane (1765–1832: #2) Lewis LOYD (1768–1858: #3) William (1770–1828: #4) Thomas (1775–1853: #6) Gwenllian (1777–1779: #7) Edward (1780–1863: #8) | AC7: =IF(ISNA(IF(K7="Boy",VLOOKUP(A7,'Siblings of those BORN Loyd'!$AP$3:$AQ$70,2,FALSE),VLOOKUP(A7,'Children of Female Loyds'!$AR$5:$AT$60,3,FALSE))),AM7,IF(K7="Boy",VLOOKUP(A7,'Siblings of those BORN Loyd'!$AP$3:$AQ$70,2,FALSE),VLOOKUP(A7,'Children of Female Loyds'!$AR$5:$AT$60,3,FALSE))) -> d.s.p | AD7: =IF(AE7="d.s.p",_xlfn.CONCAT(AE7,"."),IF(AG7=0,"-",_xlfn.CONCAT(AG7," - ",AE7," ",AF7))) -> d.s.p. | AE7: =IF(ISNA(IF(K7="Boy",VLOOKUP(A7,'Grandchildren of Male Loyds'!$AQ$3:$AS$51,3,FALSE),VLOOKUP(A7,'Grandchildren of Female Loyds'!$AX$5:$AZ$63,3,FALSE))),AM7,IF(K7="Boy",VLOOKUP(A7,'Grandchildren of Male Loyds'!$AQ$3:$AS$51,3,FALSE),VLOOKUP(A7,'Grandchildren of Female Loyds'!$AX$5:$AZ$63,3,FALSE))) -> d.s.p | AF7: =IF(ISNA(VLOOKUP(A7,'Grandchildren Loyd Daughters'!$BD$5:$BF$50,4,FALSE)),"",VLOOKUP(A7,'Grandchildren Loyd Daughters'!$BD$5:$BF$50,3,FALSE)) | AG7: =IF(ISNA(VLOOKUP(A7,'Grandchildren of Male Loyds'!$AQ$3:$AR$60,2,FALSE)),0,VLOOKUP(A7,'Grandchildren of Male Loyds'!$AQ$3:$AR$60,2,FALSE))+IF(ISNA(VLOOKUP(A7,'Grandchildren of Female Loyds'!$AX$5:$AY$50,2,FALSE)),0,VLOOKUP(A7,'Grandchildren of Female Loyds'!$AX$5:$AY$50,2,FALSE))+IF(ISNA(VLOOKUP(A7,'Grandchildren Loyd Daughters'!$BD$5:$BE$50,2,FALSE)),0,VLOOKUP(A7,'Grandchildren Loyd Daughters'!$BD$5:$BE$50,2,FALSE)) -> 0 | AH7: =VLOOKUP($U7,'Loyd List 1-190 - Edit'!$P$3:$AJ$220,21,FALSE) -> Anne WILLIAM (b. 1738, d. 24 May 1801) | AI7: =VLOOKUP(A7,'Updated Bios & Spouse Details'!$A$1:$J$200,7,FALSE) -> Unmarried | AJ7: =IF(VLOOKUP($A7,'Loyd List 1-190 - Edit'!$C$1:$AQ$220,'Book Details - NO EDIT'!AJ$1,FALSE)="","",(VLOOKUP($A7,'Loyd List 1-190 - Edit'!$C$1:$AQ$220,'Book Details - NO EDIT'!AJ$1,FALSE))) -> - | AK7: =VLOOKUP(A7,'Updated Bios & Spouse Details'!$A$1:$J$200,8,FALSE) -> - | AL7: =VLOOKUP(A7,'Updated Bios & Spouse Details'!$A$1:$J$200,5,FALSE) -> Catherine was the 2nd daughter of William LLOYD (1729–1800: #1) of Court Henry, Cilycwm, Carmarthenshire. Born 19th Feb 1772, and baptised 25 Feb 1772 at Llanwrda. Died, unmarried, 9 Dec 1798, buried 12 Dec 1798 at Cilycwm. DSP | AM7: =IF(AND(LEN(H7)>0,ISNA(IF(K7="Boy",VLOOKUP(A7,'Siblings of those BORN Loyd'!$AP$3:$AQ$70,2,FALSE),VLOOKUP(A7,'Children of Female Loyds'!$AR$5:$AS$60,2,FALSE)))),"d.s.p","") -> d.s.p | AN7: =(IF(OR(L7=0,LEN(L7)=0),"",_xlfn.CONCAT(VLOOKUP(L7,$U$3:$X$230,4,FALSE)))) -> William (1729–1800: #1) | AO7: =(IF(OR(M7=0,LEN(M7)=0),"",_xlfn.CONCAT(VLOOKUP(M7,$U$3:$X$230,4,FALSE)))) | AP7: =(IF(OR(N7=0,LEN(N7)=0),"",_xlfn.CONCAT(VLOOKUP(N7,$U$3:$X$230,4,FALSE)))) | AQ7: =(IF(OR(O7=0,LEN(O7)=0),"",_xlfn.CONCAT(VLOOKUP(O7,$U$3:$X$230,4,FALSE)))) | AR7: =(IF(OR(P7=0,LEN(P7)=0),"",_xlfn.CONCAT(VLOOKUP(P7,$U$3:$X$230,4,FALSE)))) | AS7: =(IF(OR(Q7=0,LEN(Q7)=0),"",_xlfn.CONCAT(VLOOKUP(Q7,$U$3:$X$230,4,FALSE)))) | AT7: =(IF(OR(R7=0,LEN(R7)=0),"",_xlfn.CONCAT(VLOOKUP(R7,$U$3:$X$230,4,FALSE)))) | AU7: =(IF(OR(S7=0,LEN(S7)=0),"",_xlfn.CONCAT(VLOOKUP(S7,$U$3:$X$230,4,FALSE)))) | AW7: =VLOOKUP(A7,'Updated Bios & Spouse Details'!$A$1:$J$193,6,FALSE) -> Wales | AX7: =VLOOKUP($A7,'Loyd List 1-190 - Edit'!$P$2:$AQ$220,AX$1,FALSE) -> 5 | AY7: =IF(ISNA(VLOOKUP(A7,'Data check lookup table'!$G$2:$V$73,13,FALSE))," - ",VLOOKUP(A7,'Data check lookup table'!$G$2:$V$73,13,FALSE)) -> - | AZ7: =TEXT(J7,"dd/mm/yyyy") -> 09/12/1798 | BA7: =(IF(OR(Q7=0,LEN(Q7)=0),"",_xlfn.CONCAT(", ",VLOOKUP(Q7,$U$3:$X$230,4,FALSE)))) | BB7: =(IF(OR(R7=0,LEN(R7)=0),"",_xlfn.CONCAT("; ",VLOOKUP(R7,$U$3:$X$230,4,FALSE)))) | BI7: 09/12/1798
A8: ='Loyd List 1-190 - Edit'!C8 -> 6 | B8: =VLOOKUP($A8,'Loyd List 1-190 - Edit'!$C$1:$AQ$220,'Book Details - NO EDIT'!B$1,FALSE) -> Thomas | C8: =IF(VLOOKUP($A8,'Loyd List 1-190 - Edit'!$C$1:$AQ$220,'Book Details - NO EDIT'!C$1,FALSE)="","",VLOOKUP($A8,'Loyd List 1-190 - Edit'!$C$1:$AQ$220,'Book Details - NO EDIT'!C$1,FALSE)) | D8: =IF(VLOOKUP($A8,'Loyd List 1-190 - Edit'!$C$1:$AQ$220,'Book Details - NO EDIT'!D$1,FALSE)="","",VLOOKUP($A8,'Loyd List 1-190 - Edit'!$C$1:$AQ$220,'Book Details - NO EDIT'!D$1,FALSE)) | E8: =IF(VLOOKUP($A8,'Loyd List 1-190 - Edit'!$C$1:$AQ$220,'Book Details - NO EDIT'!E$1,FALSE)="","",VLOOKUP($A8,'Loyd List 1-190 - Edit'!$C$1:$AQ$220,'Book Details - NO EDIT'!E$1,FALSE)) -> LOYD | F8: =IF(VLOOKUP($A8,'Loyd List 1-190 - Edit'!$C$1:$AQ$220,'Book Details - NO EDIT'!F$1,FALSE)="",B8,VLOOKUP($A8,'Loyd List 1-190 - Edit'!$C$1:$AQ$220,'Book Details - NO EDIT'!F$1,FALSE)) -> Thomas | G8: =IF(VLOOKUP($A8,'Loyd List 1-190 - Edit'!$C$1:$AQ$220,'Book Details - NO EDIT'!G$1,FALSE)="","",VALUE(VLOOKUP($A8,'Loyd List 1-190 - Edit'!$C$1:$AQ$220,'Book Details - NO EDIT'!G$1,FALSE))) -> 1775 | H8: =IF(VLOOKUP($A8,'Loyd List 1-190 - Edit'!$C$1:$AQ$220,'Book Details - NO EDIT'!H$1,FALSE)="","",VALUE(VLOOKUP($A8,'Loyd List 1-190 - Edit'!$C$1:$AQ$220,'Book Details - NO EDIT'!H$1,FALSE))) -> 1853 | I8: =IF(VLOOKUP($A8,'Loyd List 1-190 - Edit'!$C$1:$AQ$220,'Book Details - NO EDIT'!I$1,FALSE)="","",(VLOOKUP($A8,'Loyd List 1-190 - Edit'!$C$1:$AQ$220,'Book Details - NO EDIT'!I$1,FALSE))) -> 05/06/1775 | J8: =IF(VLOOKUP($A8,'Loyd List 1-190 - Edit'!$C$1:$AQ$220,'Book Details - NO EDIT'!J$1,FALSE)="","",(VLOOKUP($A8,'Loyd List 1-190 - Edit'!$C$1:$AQ$220,'Book Details - NO EDIT'!J$1,FALSE))) -> 28/01/1853 | K8: =VLOOKUP($A8,'Loyd List 1-190 - Edit'!$C$1:$AQ$220,'Book Details - NO EDIT'!K$1,FALSE) -> Boy | L8: =VLOOKUP($A8,'Loyd List 1-190 - Edit'!$C$1:$AQ$220,'Book Details - NO EDIT'!L$1,FALSE) -> 1 | M8: =IF(ISNA(VLOOKUP(L8,$A$3:$L$220,M$1,FALSE)),"",(VLOOKUP(L8,$A$3:$L$220,M$1,FALSE))) -> 0 | N8: =IF(ISNA(VLOOKUP(M8,$A$3:$L$220,N$1,FALSE)),"",(VLOOKUP(M8,$A$3:$L$220,N$1,FALSE))) | O8: =IF(ISNA(VLOOKUP(N8,$A$3:$L$220,O$1,FALSE)),"",(VLOOKUP(N8,$A$3:$L$220,O$1,FALSE))) | P8: =IF(ISNA(VLOOKUP(O8,$A$3:$L$220,P$1,FALSE)),"",(VLOOKUP(O8,$A$3:$L$220,P$1,FALSE))) | Q8: =IF(ISNA(VLOOKUP(P8,$A$3:$L$220,Q$1,FALSE)),"",(VLOOKUP(P8,$A$3:$L$220,Q$1,FALSE))) | R8: =IF(ISNA(VLOOKUP(Q8,$A$3:$L$220,R$1,FALSE)),"",(VLOOKUP(Q8,$A$3:$L$220,R$1,FALSE))) | S8: =IF(ISNA(VLOOKUP(R8,$A$3:$L$220,S$1,FALSE)),"",(VLOOKUP(R8,$A$3:$L$220,S$1,FALSE))) | T8: =IF(L8=1,1,IF(M8=1,2,IF(N8=1,3,IF(O8=1,4,IF(P8=1,5,IF(Q8=1,6,IF(R8=1,7,IF(S8=1,8,0)))))))) -> 1 | U8: =A8 -> 6 | V8: =_xlfn.CONCAT(F8," (",G8,"–",H8,")") -> Thomas (1775–1853) | W8: =_xlfn.CONCAT(F8," (#",A8,")") -> Thomas (#6) | X8: =_xlfn.CONCAT(F8," (",G8,"–",H8,": #",A8,")") -> Thomas (1775–1853: #6) | Y8: =_xlfn.CONCAT(B8," ",IF(C8="",E8,_xlfn.CONCAT(C8," ",IF(D8="",E8,_xlfn.CONCAT(D8," ",E8))))) -> Thomas LOYD | Z8: =VLOOKUP(L8,$U$2:$X$230,Z$1,FALSE) -> William (1729–1800: #1) | AA8: =_xlfn.CONCAT(AN8," ",AO8," ",AP8," ",AQ8," ",AR8," ",AS8," ",AT8," ",AU8) -> William (1729–1800: #1) | AB8: =VLOOKUP(U8,'Siblings of those BORN Loyd'!$A$2:$G$230,7,FALSE) -> 6 – Jane (1765–1832: #2) Lewis LOYD (1768–1858: #3) William (1770–1828: #4) Catherine (1772–1798: #5) Gwenllian (1777–1779: #7) Edward (1780–1863: #8) | AC8: =IF(ISNA(IF(K8="Boy",VLOOKUP(A8,'Siblings of those BORN Loyd'!$AP$3:$AQ$70,2,FALSE),VLOOKUP(A8,'Children of Female Loyds'!$AR$5:$AT$60,3,FALSE))),AM8,IF(K8="Boy",VLOOKUP(A8,'Siblings of those BORN Loyd'!$AP$3:$AQ$70,2,FALSE),VLOOKUP(A8,'Children of Female Loyds'!$AR$5:$AT$60,3,FALSE))) -> d.s.p | AD8: =IF(AE8="d.s.p",_xlfn.CONCAT(AE8,"."),IF(AG8=0,"-",_xlfn.CONCAT(AG8," - ",AE8," ",AF8))) -> d.s.p. | AE8: =IF(ISNA(IF(K8="Boy",VLOOKUP(A8,'Grandchildren of Male Loyds'!$AQ$3:$AS$51,3,FALSE),VLOOKUP(A8,'Grandchildren of Female Loyds'!$AX$5:$AZ$63,3,FALSE))),AM8,IF(K8="Boy",VLOOKUP(A8,'Grandchildren of Male Loyds'!$AQ$3:$AS$51,3,FALSE),VLOOKUP(A8,'Grandchildren of Female Loyds'!$AX$5:$AZ$63,3,FALSE))) -> d.s.p | AF8: =IF(ISNA(VLOOKUP(A8,'Grandchildren Loyd Daughters'!$BD$5:$BF$50,4,FALSE)),"",VLOOKUP(A8,'Grandchildren Loyd Daughters'!$BD$5:$BF$50,3,FALSE)) | AG8: =IF(ISNA(VLOOKUP(A8,'Grandchildren of Male Loyds'!$AQ$3:$AR$60,2,FALSE)),0,VLOOKUP(A8,'Grandchildren of Male Loyds'!$AQ$3:$AR$60,2,FALSE))+IF(ISNA(VLOOKUP(A8,'Grandchildren of Female Loyds'!$AX$5:$AY$50,2,FALSE)),0,VLOOKUP(A8,'Grandchildren of Female Loyds'!$AX$5:$AY$50,2,FALSE))+IF(ISNA(VLOOKUP(A8,'Grandchildren Loyd Daughters'!$BD$5:$BE$50,2,FALSE)),0,VLOOKUP(A8,'Grandchildren Loyd Daughters'!$BD$5:$BE$50,2,FALSE)) -> 0 | AH8: =VLOOKUP($U8,'Loyd List 1-190 - Edit'!$P$3:$AJ$220,21,FALSE) -> Anne WILLIAM (b. 1738, d. 24 May 1801) | AI8: =VLOOKUP(A8,'Updated Bios & Spouse Details'!$A$1:$J$200,7,FALSE) -> Unmarried | AJ8: =IF(VLOOKUP($A8,'Loyd List 1-190 - Edit'!$C$1:$AQ$220,'Book Details - NO EDIT'!AJ$1,FALSE)="","",(VLOOKUP($A8,'Loyd List 1-190 - Edit'!$C$1:$AQ$220,'Book Details - NO EDIT'!AJ$1,FALSE))) -> - | AK8: =VLOOKUP(A8,'Updated Bios & Spouse Details'!$A$1:$J$200,8,FALSE) -> - | AL8: =VLOOKUP(A8,'Updated Bios & Spouse Details'!$A$1:$J$200,5,FALSE) -> Thomas lived at Ardwick Terrace, Manchester. 3rd son of William LLOYD (1729–1800: #1) of Court Henry, Cilycwm, Carmarthenshire. Born 5 Jun 1775, and baptised 8 Jun 1775 at Llanwrda. Thomas became head of the Cannon Street calico printers, Loyd & Price in 1823, and afterwards Loyd, Buchan & Welsh. Died, unmarried, 28 Jan 1853 leaving property worth either, £80,000 [9] including at least £5,000 to his relations in Wales, or £35,000 [10]. Will dated 29 Nov 1845, proved 23 Jun 1853 P.C.C. “Never was there a more good-humoured or friendly man than Thomas Loyd. A bachelor to the end of his days - chatty, frank and communicative - he delighted in company and sensible conversation, and had no objection, like Cato of old, to warm his cold chastity every evening with mellow wine.” - Grindon page 89. Footnotes: [9] According to Grindon. [10] According to O'Brien. | AM8: =IF(AND(LEN(H8)>0,ISNA(IF(K8="Boy",VLOOKUP(A8,'Siblings of those BORN Loyd'!$AP$3:$AQ$70,2,FALSE),VLOOKUP(A8,'Children of Female Loyds'!$AR$5:$AS$60,2,FALSE)))),"d.s.p","") -> d.s.p | AN8: =(IF(OR(L8=0,LEN(L8)=0),"",_xlfn.CONCAT(VLOOKUP(L8,$U$3:$X$230,4,FALSE)))) -> William (1729–1800: #1) | AO8: =(IF(OR(M8=0,LEN(M8)=0),"",_xlfn.CONCAT(VLOOKUP(M8,$U$3:$X$230,4,FALSE)))) | AP8: =(IF(OR(N8=0,LEN(N8)=0),"",_xlfn.CONCAT(VLOOKUP(N8,$U$3:$X$230,4,FALSE)))) | AQ8: =(IF(OR(O8=0,LEN(O8)=0),"",_xlfn.CONCAT(VLOOKUP(O8,$U$3:$X$230,4,FALSE)))) | AR8: =(IF(OR(P8=0,LEN(P8)=0),"",_xlfn.CONCAT(VLOOKUP(P8,$U$3:$X$230,4,FALSE)))) | AS8: =(IF(OR(Q8=0,LEN(Q8)=0),"",_xlfn.CONCAT(VLOOKUP(Q8,$U$3:$X$230,4,FALSE)))) | AT8: =(IF(OR(R8=0,LEN(R8)=0),"",_xlfn.CONCAT(VLOOKUP(R8,$U$3:$X$230,4,FALSE)))) | AU8: =(IF(OR(S8=0,LEN(S8)=0),"",_xlfn.CONCAT(VLOOKUP(S8,$U$3:$X$230,4,FALSE)))) | AW8: =VLOOKUP(A8,'Updated Bios & Spouse Details'!$A$1:$J$193,6,FALSE) -> Wales & England | AX8: =VLOOKUP($A8,'Loyd List 1-190 - Edit'!$P$2:$AQ$220,AX$1,FALSE) -> 6 | AY8: =IF(ISNA(VLOOKUP(A8,'Data check lookup table'!$G$2:$V$73,13,FALSE))," - ",VLOOKUP(A8,'Data check lookup table'!$G$2:$V$73,13,FALSE)) -> - | AZ8: =TEXT(J8,"dd/mm/yyyy") -> 28/01/1853 | BA8: =(IF(OR(Q8=0,LEN(Q8)=0),"",_xlfn.CONCAT(", ",VLOOKUP(Q8,$U$3:$X$230,4,FALSE)))) | BB8: =(IF(OR(R8=0,LEN(R8)=0),"",_xlfn.CONCAT("; ",VLOOKUP(R8,$U$3:$X$230,4,FALSE)))) | BI8: 28/01/1853
A9: ='Loyd List 1-190 - Edit'!C9 -> 7 | B9: =VLOOKUP($A9,'Loyd List 1-190 - Edit'!$C$1:$AQ$220,'Book Details - NO EDIT'!B$1,FALSE) -> Gwenllian | C9: =IF(VLOOKUP($A9,'Loyd List 1-190 - Edit'!$C$1:$AQ$220,'Book Details - NO EDIT'!C$1,FALSE)="","",VLOOKUP($A9,'Loyd List 1-190 - Edit'!$C$1:$AQ$220,'Book Details - NO EDIT'!C$1,FALSE)) | D9: =IF(VLOOKUP($A9,'Loyd List 1-190 - Edit'!$C$1:$AQ$220,'Book Details - NO EDIT'!D$1,FALSE)="","",VLOOKUP($A9,'Loyd List 1-190 - Edit'!$C$1:$AQ$220,'Book Details - NO EDIT'!D$1,FALSE)) | E9: =IF(VLOOKUP($A9,'Loyd List 1-190 - Edit'!$C$1:$AQ$220,'Book Details - NO EDIT'!E$1,FALSE)="","",VLOOKUP($A9,'Loyd List 1-190 - Edit'!$C$1:$AQ$220,'Book Details - NO EDIT'!E$1,FALSE)) -> LLOYD | F9: =IF(VLOOKUP($A9,'Loyd List 1-190 - Edit'!$C$1:$AQ$220,'Book Details - NO EDIT'!F$1,FALSE)="",B9,VLOOKUP($A9,'Loyd List 1-190 - Edit'!$C$1:$AQ$220,'Book Details - NO EDIT'!F$1,FALSE)) -> Gwenllian | G9: =IF(VLOOKUP($A9,'Loyd List 1-190 - Edit'!$C$1:$AQ$220,'Book Details - NO EDIT'!G$1,FALSE)="","",VALUE(VLOOKUP($A9,'Loyd List 1-190 - Edit'!$C$1:$AQ$220,'Book Details - NO EDIT'!G$1,FALSE))) -> 1777 | H9: =IF(VLOOKUP($A9,'Loyd List 1-190 - Edit'!$C$1:$AQ$220,'Book Details - NO EDIT'!H$1,FALSE)="","",VALUE(VLOOKUP($A9,'Loyd List 1-190 - Edit'!$C$1:$AQ$220,'Book Details - NO EDIT'!H$1,FALSE))) -> 1779 | I9: =IF(VLOOKUP($A9,'Loyd List 1-190 - Edit'!$C$1:$AQ$220,'Book Details - NO EDIT'!I$1,FALSE)="","",(VLOOKUP($A9,'Loyd List 1-190 - Edit'!$C$1:$AQ$220,'Book Details - NO EDIT'!I$1,FALSE))) -> 19/10/1777 | J9: =IF(VLOOKUP($A9,'Loyd List 1-190 - Edit'!$C$1:$AQ$220,'Book Details - NO EDIT'!J$1,FALSE)="","",(VLOOKUP($A9,'Loyd List 1-190 - Edit'!$C$1:$AQ$220,'Book Details - NO EDIT'!J$1,FALSE))) -> 12/10/1779 | K9: =VLOOKUP($A9,'Loyd List 1-190 - Edit'!$C$1:$AQ$220,'Book Details - NO EDIT'!K$1,FALSE) -> Girl | L9: =VLOOKUP($A9,'Loyd List 1-190 - Edit'!$C$1:$AQ$220,'Book Details - NO EDIT'!L$1,FALSE) -> 1 | M9: =IF(ISNA(VLOOKUP(L9,$A$3:$L$220,M$1,FALSE)),"",(VLOOKUP(L9,$A$3:$L$220,M$1,FALSE))) -> 0 | N9: =IF(ISNA(VLOOKUP(M9,$A$3:$L$220,N$1,FALSE)),"",(VLOOKUP(M9,$A$3:$L$220,N$1,FALSE))) | O9: =IF(ISNA(VLOOKUP(N9,$A$3:$L$220,O$1,FALSE)),"",(VLOOKUP(N9,$A$3:$L$220,O$1,FALSE))) | P9: =IF(ISNA(VLOOKUP(O9,$A$3:$L$220,P$1,FALSE)),"",(VLOOKUP(O9,$A$3:$L$220,P$1,FALSE))) | Q9: =IF(ISNA(VLOOKUP(P9,$A$3:$L$220,Q$1,FALSE)),"",(VLOOKUP(P9,$A$3:$L$220,Q$1,FALSE))) | R9: =IF(ISNA(VLOOKUP(Q9,$A$3:$L$220,R$1,FALSE)),"",(VLOOKUP(Q9,$A$3:$L$220,R$1,FALSE))) | S9: =IF(ISNA(VLOOKUP(R9,$A$3:$L$220,S$1,FALSE)),"",(VLOOKUP(R9,$A$3:$L$220,S$1,FALSE))) | T9: =IF(L9=1,1,IF(M9=1,2,IF(N9=1,3,IF(O9=1,4,IF(P9=1,5,IF(Q9=1,6,IF(R9=1,7,IF(S9=1,8,0)))))))) -> 1 | U9: =A9 -> 7 | V9: =_xlfn.CONCAT(F9," (",G9,"–",H9,")") -> Gwenllian (1777–1779) | W9: =_xlfn.CONCAT(F9," (#",A9,")") -> Gwenllian (#7) | X9: =_xlfn.CONCAT(F9," (",G9,"–",H9,": #",A9,")") -> Gwenllian (1777–1779: #7) | Y9: =_xlfn.CONCAT(B9," ",IF(C9="",E9,_xlfn.CONCAT(C9," ",IF(D9="",E9,_xlfn.CONCAT(D9," ",E9))))) -> Gwenllian LLOYD | Z9: =VLOOKUP(L9,$U$2:$X$230,Z$1,FALSE) -> William (1729–1800: #1) | AA9: =_xlfn.CONCAT(AN9," ",AO9," ",AP9," ",AQ9," ",AR9," ",AS9," ",AT9," ",AU9) -> William (1729–1800: #1) | AB9: =VLOOKUP(U9,'Siblings of those BORN Loyd'!$A$2:$G$230,7,FALSE) -> 6 – Jane (1765–1832: #2) Lewis LOYD (1768–1858: #3) William (1770–1828: #4) Catherine (1772–1798: #5) Thomas (1775–1853: #6) Edward (1780–1863: #8) | AC9: =IF(ISNA(IF(K9="Boy",VLOOKUP(A9,'Siblings of those BORN Loyd'!$AP$3:$AQ$70,2,FALSE),VLOOKUP(A9,'Children of Female Loyds'!$AR$5:$AT$60,3,FALSE))),AM9,IF(K9="Boy",VLOOKUP(A9,'Siblings of those BORN Loyd'!$AP$3:$AQ$70,2,FALSE),VLOOKUP(A9,'Children of Female Loyds'!$AR$5:$AT$60,3,FALSE))) -> d.s.p | AD9: =IF(AE9="d.s.p",_xlfn.CONCAT(AE9,"."),IF(AG9=0,"-",_xlfn.CONCAT(AG9," - ",AE9," ",AF9))) -> d.s.p. | AE9: =IF(ISNA(IF(K9="Boy",VLOOKUP(A9,'Grandchildren of Male Loyds'!$AQ$3:$AS$51,3,FALSE),VLOOKUP(A9,'Grandchildren of Female Loyds'!$AX$5:$AZ$63,3,FALSE))),AM9,IF(K9="Boy",VLOOKUP(A9,'Grandchildren of Male Loyds'!$AQ$3:$AS$51,3,FALSE),VLOOKUP(A9,'Grandchildren of Female Loyds'!$AX$5:$AZ$63,3,FALSE))) -> d.s.p | AF9: =IF(ISNA(VLOOKUP(A9,'Grandchildren Loyd Daughters'!$BD$5:$BF$50,4,FALSE)),"",VLOOKUP(A9,'Grandchildren Loyd Daughters'!$BD$5:$BF$50,3,FALSE)) | AG9: =IF(ISNA(VLOOKUP(A9,'Grandchildren of Male Loyds'!$AQ$3:$AR$60,2,FALSE)),0,VLOOKUP(A9,'Grandchildren of Male Loyds'!$AQ$3:$AR$60,2,FALSE))+IF(ISNA(VLOOKUP(A9,'Grandchildren of Female Loyds'!$AX$5:$AY$50,2,FALSE)),0,VLOOKUP(A9,'Grandchildren of Female Loyds'!$AX$5:$AY$50,2,FALSE))+IF(ISNA(VLOOKUP(A9,'Grandchildren Loyd Daughters'!$BD$5:$BE$50,2,FALSE)),0,VLOOKUP(A9,'Grandchildren Loyd Daughters'!$BD$5:$BE$50,2,FALSE)) -> 0 | AH9: =VLOOKUP($U9,'Loyd List 1-190 - Edit'!$P$3:$AJ$220,21,FALSE) -> Anne WILLIAM (b. 1738, d. 24 May 1801) | AI9: =VLOOKUP(A9,'Updated Bios & Spouse Details'!$A$1:$J$200,7,FALSE) -> Unmarried | AJ9: =IF(VLOOKUP($A9,'Loyd List 1-190 - Edit'!$C$1:$AQ$220,'Book Details - NO EDIT'!AJ$1,FALSE)="","",(VLOOKUP($A9,'Loyd List 1-190 - Edit'!$C$1:$AQ$220,'Book Details - NO EDIT'!AJ$1,FALSE))) -> - | AK9: =VLOOKUP(A9,'Updated Bios & Spouse Details'!$A$1:$J$200,8,FALSE) -> - | AL9: =VLOOKUP(A9,'Updated Bios & Spouse Details'!$A$1:$J$200,5,FALSE) -> Gwenllian was the 3rd and youngest daughter of William LLOYD (1729-1800: #1) of Court Henry, Cilycwm, Carmarthenshire. Born 19 Oct 1777, and baptised 22 or 23 Oct 1777 at Llanwrda. Died 12 Oct 1779. Buried at Llanwrda. | AM9: =IF(AND(LEN(H9)>0,ISNA(IF(K9="Boy",VLOOKUP(A9,'Siblings of those BORN Loyd'!$AP$3:$AQ$70,2,FALSE),VLOOKUP(A9,'Children of Female Loyds'!$AR$5:$AS$60,2,FALSE)))),"d.s.p","") -> d.s.p | AN9: =(IF(OR(L9=0,LEN(L9)=0),"",_xlfn.CONCAT(VLOOKUP(L9,$U$3:$X$230,4,FALSE)))) -> William (1729–1800: #1) | AO9: =(IF(OR(M9=0,LEN(M9)=0),"",_xlfn.CONCAT(VLOOKUP(M9,$U$3:$X$230,4,FALSE)))) | AP9: =(IF(OR(N9=0,LEN(N9)=0),"",_xlfn.CONCAT(VLOOKUP(N9,$U$3:$X$230,4,FALSE)))) | AQ9: =(IF(OR(O9=0,LEN(O9)=0),"",_xlfn.CONCAT(VLOOKUP(O9,$U$3:$X$230,4,FALSE)))) | AR9: =(IF(OR(P9=0,LEN(P9)=0),"",_xlfn.CONCAT(VLOOKUP(P9,$U$3:$X$230,4,FALSE)))) | AS9: =(IF(OR(Q9=0,LEN(Q9)=0),"",_xlfn.CONCAT(VLOOKUP(Q9,$U$3:$X$230,4,FALSE)))) | AT9: =(IF(OR(R9=0,LEN(R9)=0),"",_xlfn.CONCAT(VLOOKUP(R9,$U$3:$X$230,4,FALSE)))) | AU9: =(IF(OR(S9=0,LEN(S9)=0),"",_xlfn.CONCAT(VLOOKUP(S9,$U$3:$X$230,4,FALSE)))) | AW9: =VLOOKUP(A9,'Updated Bios & Spouse Details'!$A$1:$J$193,6,FALSE) -> Wales | AX9: =VLOOKUP($A9,'Loyd List 1-190 - Edit'!$P$2:$AQ$220,AX$1,FALSE) -> 7 | AY9: =IF(ISNA(VLOOKUP(A9,'Data check lookup table'!$G$2:$V$73,13,FALSE))," - ",VLOOKUP(A9,'Data check lookup table'!$G$2:$V$73,13,FALSE)) -> - | AZ9: =TEXT(J9,"dd/mm/yyyy") -> 12/10/1779 | BA9: =(IF(OR(Q9=0,LEN(Q9)=0),"",_xlfn.CONCAT(", ",VLOOKUP(Q9,$U$3:$X$230,4,FALSE)))) | BB9: =(IF(OR(R9=0,LEN(R9)=0),"",_xlfn.CONCAT("; ",VLOOKUP(R9,$U$3:$X$230,4,FALSE)))) | BI9: 12/10/1779
A10: ='Loyd List 1-190 - Edit'!C10 -> 8 | B10: =VLOOKUP($A10,'Loyd List 1-190 - Edit'!$C$1:$AQ$220,'Book Details - NO EDIT'!B$1,FALSE) -> Edward | C10: =IF(VLOOKUP($A10,'Loyd List 1-190 - Edit'!$C$1:$AQ$220,'Book Details - NO EDIT'!C$1,FALSE)="","",VLOOKUP($A10,'Loyd List 1-190 - Edit'!$C$1:$AQ$220,'Book Details - NO EDIT'!C$1,FALSE)) | D10: =IF(VLOOKUP($A10,'Loyd List 1-190 - Edit'!$C$1:$AQ$220,'Book Details - NO EDIT'!D$1,FALSE)="","",VLOOKUP($A10,'Loyd List 1-190 - Edit'!$C$1:$AQ$220,'Book Details - NO EDIT'!D$1,FALSE)) | E10: =IF(VLOOKUP($A10,'Loyd List 1-190 - Edit'!$C$1:$AQ$220,'Book Details - NO EDIT'!E$1,FALSE)="","",VLOOKUP($A10,'Loyd List 1-190 - Edit'!$C$1:$AQ$220,'Book Details - NO EDIT'!E$1,FALSE)) -> LOYD | F10: =IF(VLOOKUP($A10,'Loyd List 1-190 - Edit'!$C$1:$AQ$220,'Book Details - NO EDIT'!F$1,FALSE)="",B10,VLOOKUP($A10,'Loyd List 1-190 - Edit'!$C$1:$AQ$220,'Book Details - NO EDIT'!F$1,FALSE)) -> Edward | G10: =IF(VLOOKUP($A10,'Loyd List 1-190 - Edit'!$C$1:$AQ$220,'Book Details - NO EDIT'!G$1,FALSE)="","",VALUE(VLOOKUP($A10,'Loyd List 1-190 - Edit'!$C$1:$AQ$220,'Book Details - NO EDIT'!G$1,FALSE))) -> 1780 | H10: =IF(VLOOKUP($A10,'Loyd List 1-190 - Edit'!$C$1:$AQ$220,'Book Details - NO EDIT'!H$1,FALSE)="","",VALUE(VLOOKUP($A10,'Loyd List 1-190 - Edit'!$C$1:$AQ$220,'Book Details - NO EDIT'!H$1,FALSE))) -> 1863 | I10: =IF(VLOOKUP($A10,'Loyd List 1-190 - Edit'!$C$1:$AQ$220,'Book Details - NO EDIT'!I$1,FALSE)="","",(VLOOKUP($A10,'Loyd List 1-190 - Edit'!$C$1:$AQ$220,'Book Details - NO EDIT'!I$1,FALSE))) -> 30/01/1780 | J10: =IF(VLOOKUP($A10,'Loyd List 1-190 - Edit'!$C$1:$AQ$220,'Book Details - NO EDIT'!J$1,FALSE)="","",(VLOOKUP($A10,'Loyd List 1-190 - Edit'!$C$1:$AQ$220,'Book Details - NO EDIT'!J$1,FALSE))) -> 30/01/1863 | K10: =VLOOKUP($A10,'Loyd List 1-190 - Edit'!$C$1:$AQ$220,'Book Details - NO EDIT'!K$1,FALSE) -> Boy | L10: =VLOOKUP($A10,'Loyd List 1-190 - Edit'!$C$1:$AQ$220,'Book Details - NO EDIT'!L$1,FALSE) -> 1 | M10: =IF(ISNA(VLOOKUP(L10,$A$3:$L$220,M$1,FALSE)),"",(VLOOKUP(L10,$A$3:$L$220,M$1,FALSE))) -> 0 | N10: =IF(ISNA(VLOOKUP(M10,$A$3:$L$220,N$1,FALSE)),"",(VLOOKUP(M10,$A$3:$L$220,N$1,FALSE))) | O10: =IF(ISNA(VLOOKUP(N10,$A$3:$L$220,O$1,FALSE)),"",(VLOOKUP(N10,$A$3:$L$220,O$1,FALSE))) | P10: =IF(ISNA(VLOOKUP(O10,$A$3:$L$220,P$1,FALSE)),"",(VLOOKUP(O10,$A$3:$L$220,P$1,FALSE))) | Q10: =IF(ISNA(VLOOKUP(P10,$A$3:$L$220,Q$1,FALSE)),"",(VLOOKUP(P10,$A$3:$L$220,Q$1,FALSE))) | R10: =IF(ISNA(VLOOKUP(Q10,$A$3:$L$220,R$1,FALSE)),"",(VLOOKUP(Q10,$A$3:$L$220,R$1,FALSE))) | S10: =IF(ISNA(VLOOKUP(R10,$A$3:$L$220,S$1,FALSE)),"",(VLOOKUP(R10,$A$3:$L$220,S$1,FALSE))) | T10: =IF(L10=1,1,IF(M10=1,2,IF(N10=1,3,IF(O10=1,4,IF(P10=1,5,IF(Q10=1,6,IF(R10=1,7,IF(S10=1,8,0)))))))) -> 1 | U10: =A10 -> 8 | V10: =_xlfn.CONCAT(F10," (",G10,"–",H10,")") -> Edward (1780–1863) | W10: =_xlfn.CONCAT(F10," (#",A10,")") -> Edward (#8) | X10: =_xlfn.CONCAT(F10," (",G10,"–",H10,": #",A10,")") -> Edward (1780–1863: #8) | Y10: =_xlfn.CONCAT(B10," ",IF(C10="",E10,_xlfn.CONCAT(C10," ",IF(D10="",E10,_xlfn.CONCAT(D10," ",E10))))) -> Edward LOYD | Z10: =VLOOKUP(L10,$U$2:$X$230,Z$1,FALSE) -> William (1729–1800: #1) | AA10: =_xlfn.CONCAT(AN10," ",AO10," ",AP10," ",AQ10," ",AR10," ",AS10," ",AT10," ",AU10) -> William (1729–1800: #1) | AB10: =VLOOKUP(U10,'Siblings of those BORN Loyd'!$A$2:$G$230,7,FALSE) -> 6 – Jane (1765–1832: #2) Lewis LOYD (1768–1858: #3) William (1770–1828: #4) Catherine (1772–1798: #5) Thomas (1775–1853: #6) Gwenllian (1777–1779: #7) | AC10: =IF(ISNA(IF(K10="Boy",VLOOKUP(A10,'Siblings of those BORN Loyd'!$AP$3:$AQ$70,2,FALSE),VLOOKUP(A10,'Children of Female Loyds'!$AR$5:$AT$60,3,FALSE))),AM10,IF(K10="Boy",VLOOKUP(A10,'Siblings of those BORN Loyd'!$AP$3:$AQ$70,2,FALSE),VLOOKUP(A10,'Children of Female Loyds'!$AR$5:$AT$60,3,FALSE))) -> 8 - Sarah (1810–1858: #11); Lewis (1811–1891: #13); Annie (1813–1834: #15); Kate (1815–1905: #18); Hannah (1817–1907: #19); Edward (1820–1890: #22); William (1821–1885: #23); Fanny (1824–1856: #24) | AD10: =IF(AE10="d.s.p",_xlfn.CONCAT(AE10,"."),IF(AG10=0,"-",_xlfn.CONCAT(AG10," - ",AE10," ",AF10))) -> 31 - Mary (1848–1934: #31); Lewis (1852–1908: #35); Elinor (1853–1895: #36); Gertrude (1854–1924: #38); Fa (1855–1927: #39); Harriet (1856–1921: #40); Frederic (1856–1936: #41); Dulcie (1858–1905: #42); Meg (1859–1936: #43); Harry (1861–1938: #44); Llewellyn (1861–1939: #45); William (1863–1923: #46); Caroline (1864–1940: #47); Caroline (1865–1938: #48) ;Mary (1867–1867: #49); Arthur (1868–1911: #50) Emma BENYON (1838 - 1913: #11a) Sarah BENYON (1839 - 1863: #11b) Henry BENYON (1841 - 1861: #11c) Fanny BENYON (1842 - 1845: #11d) Edward BENYON (1845 - 1903: #11e) Margaret NICOL (1844 - 1927: #18a) William NICOL (1846 - 1914: #18b) James NICOL (1848 - 1938: #18c) Sarah NICOL (1854 - 1943: #18d) Lewis NICOL (1858 - 1935: #18e) William ENTWISLE (1839 - 1860: #19a) Richard ENTWISLE (1840 - 1894: #19b) Frederica ENTWISLE (1842 - 1916: #19c) Bernard ENTWISLE (1847 - 1877: #19d) Edward ENTWISLE (1852 - 1881: #19e) | AE10: =IF(ISNA(IF(K10="Boy",VLOOKUP(A10,'Grandchildren of Male Loyds'!$AQ$3:$AS$51,3,FALSE),VLOOKUP(A10,'Grandchildren of Female Loyds'!$AX$5:$AZ$63,3,FALSE))),AM10,IF(K10="Boy",VLOOKUP(A10,'Grandchildren of Male Loyds'!$AQ$3:$AS$51,3,FALSE),VLOOKUP(A10,'Grandchildren of Female Loyds'!$AX$5:$AZ$63,3,FALSE))) -> Mary (1848–1934: #31); Lewis (1852–1908: #35); Elinor (1853–1895: #36); Gertrude (1854–1924: #38); Fa (1855–1927: #39); Harriet (1856–1921: #40); Frederic (1856–1936: #41); Dulcie (1858–1905: #42); Meg (1859–1936: #43); Harry (1861–1938: #44); Llewellyn (1861–1939: #45); William (1863–1923: #46); Caroline (1864–1940: #47); Caroline (1865–1938: #48) ;Mary (1867–1867: #49); Arthur (1868–1911: #50) | AF10: =IF(ISNA(VLOOKUP(A10,'Grandchildren Loyd Daughters'!$BD$5:$BF$50,4,FALSE)),"",VLOOKUP(A10,'Grandchildren Loyd Daughters'!$BD$5:$BF$50,3,FALSE)) -> Emma BENYON (1838 - 1913: #11a) Sarah BENYON (1839 - 1863: #11b) Henry BENYON (1841 - 1861: #11c) Fanny BENYON (1842 - 1845: #11d) Edward BENYON (1845 - 1903: #11e) Margaret NICOL (1844 - 1927: #18a) William NICOL (1846 - 1914: #18b) James NICOL (1848 - 1938: #18c) Sarah NICOL (1854 - 1943: #18d) Lewis NICOL (1858 - 1935: #18e) William ENTWISLE (1839 - 1860: #19a) Richard ENTWISLE (1840 - 1894: #19b) Frederica ENTWISLE (1842 - 1916: #19c) Bernard ENTWISLE (1847 - 1877: #19d) Edward ENTWISLE (1852 - 1881: #19e) | AG10: =IF(ISNA(VLOOKUP(A10,'Grandchildren of Male Loyds'!$AQ$3:$AR$60,2,FALSE)),0,VLOOKUP(A10,'Grandchildren of Male Loyds'!$AQ$3:$AR$60,2,FALSE))+IF(ISNA(VLOOKUP(A10,'Grandchildren of Female Loyds'!$AX$5:$AY$50,2,FALSE)),0,VLOOKUP(A10,'Grandchildren of Female Loyds'!$AX$5:$AY$50,2,FALSE))+IF(ISNA(VLOOKUP(A10,'Grandchildren Loyd Daughters'!$BD$5:$BE$50,2,FALSE)),0,VLOOKUP(A10,'Grandchildren Loyd Daughters'!$BD$5:$BE$50,2,FALSE)) -> 31 | AH10: =VLOOKUP($U10,'Loyd List 1-190 - Edit'!$P$3:$AJ$220,21,FALSE) -> Anne WILLIAM (b. 1738, d. 24 May 1801) | AI10: =VLOOKUP(A10,'Updated Bios & Spouse Details'!$A$1:$J$200,7,FALSE) -> Sarah TAYLOR (b.5 Jul 1785, d. 19 Jan 1863) | AJ10: =IF(VLOOKUP($A10,'Loyd List 1-190 - Edit'!$C$1:$AQ$220,'Book Details - NO EDIT'!AJ$1,FALSE)="","",(VLOOKUP($A10,'Loyd List 1-190 - Edit'!$C$1:$AQ$220,'Book Details - NO EDIT'!AJ$1,FALSE))) -> 17/08/1809 | AK10: =VLOOKUP(A10,'Updated Bios & Spouse Details'!$A$1:$J$200,8,FALSE) -> Married Sarah, 3rd daughter of Joseph TAYLOR of Lion Fold, Blackley, Lancashire. at Manchester Collegiate Church (later Manchester Cathedral). Sarah baptised, 7 Aug 1785, at Blackley Chapel. Buried at Addington, near Croydon. Sarah’s mother married again, after Joseph Taylor, Thomas Henshaw who set up the Henshaw Trust which still exists in 2022 after Sarah left £20k to the Henshaw Trust in her will. | AL10: =VLOOKUP(A10,'Updated Bios & Spouse Details'!$A$1:$J$200,5,FALSE) -> At different times Edward lived in King Street, Manchester, at Greenhill, Cheetham Hill, Manchester [11] and later at Coombe House, Coombe Lane, Croydon, Surrey. 4th and youngest son of William LLOYD (1729–1800: #1) of Court Henry, Cilycwm, Carmarthenshire. Born 30 Jan 1780 and baptised 3 Feb 1780 at Llanwrda. Educated probably at Mr. David PRICE’s school at Llanycrwys near Lampeter for a schoolmaster. Came to Manchester and entered Bank as a clerk, became head cashier and then partner. Member of the Billiard Club and Broughton Archers.[12] Became senior partner, Manchester branch, Jones Loyds Bank at 35 King Street, Manchester in 1821. Notable collector of modern English water colours and Dutch old masters. Died 30 Jan 1863 at Coombe House, buried at Addington, near Croydon. Estate worth £600,000. Will dated 9 Apr 1855, proved 18 Mar 1863 P.P.R.. Issue: 3 sons, 5 daughters. Roddy SALE (97d), in 2022, has portrait of Sarah Taylor (daughter of Joseph Taylor) who married Edward Loyd (#8). Footnote: [11] Greenhill, Cheetham Hill, Manchester was built, and lived in, by Samuel JONES who died 17 Mar 1819. It was then taken over by his partner at the bank, Edward LOYD, who lived there until he retired to Croydon in 1848. By 1877 the house had disappeared. Edward LOYD also owned the manor and huge estate of Minshull Vernon, near Nantwich in Cheshire, although he never live there himself. Some of the property was occupied by his wife’s relatives, and he was the joint benefactor of the church of St Peter, Leighton-cum-Minshull. Vernon Manor was rebuilt in 1849 to a design by Sir Gilbert Scott. On his death Edward left the estate to his eldest son, Lewis LOYD (1811–91: #13) who, in turn, on his death left it and other property in Cheshire to his grandson, Edward Henry LOYD (1861–1938: #44) who was also known as Harry. [12] “Mr Loyd’s devotedness to the bank was equalled by his attachment to his home ....he rarely allowed himself to be absent for more than a day or two. He was a member of the Billiard Club, but found his chief enjoyment in connection with that famous old body, the Broughton Archers. ... composed exclusively of gentlemen, the admission being almost as strict as to the Billiard Club..... all men who represented the weight and influence of the town. A meeting short of Edward Loyd perhaps was never known ... because ... on the archery ground he divested himself of all his cares, smoothed his ruffled plumage, and warmed and refreshed the very atmosphere with his boundless ‘bonhomie’. He was accustomed to present the club as often as needed with an aum (fifteen dozen) of hock ... Of this celebrated club Mr Edward Loyd may truthfully be declared to have been the life and soul ... as a member ... he did most to render it one of the most charming that ever existed. He was one of the muster upon the lawn at Holland House on the occasion of that celebrated festival when the Broughton Archers acted as body guard to the Queen.” Grindon page 153-57. “After the death of William Jones [the son of John Jones (1713–75)] and brother of Sarah, wife of Lewis Loyd (1768–1858: #3) in 1821, the King Street bank fell under the control, purely and solely, of Mr Edward Loyd who splendid management continued unbroken for the long period of twenty-seven years. [On 25 December 1848] the Manchester business was separated from the Metropolitan one, the ancient appellation of William Jones Loyd and co., disappeared; Mr Loyd, 68, retired, and the [his] responsibilities in Manchester were distributed amongst four new partners: Mr Loyd’s son Edward (1820 –90: #22), Mr William Entwisle, Mr Henry Barrett Bury and Mr Thomas Barlow Jervis. “On his retirement from the bank, Mr Loyd removed to Croydon in Surrey. His departure from Manchester touched a larger circle than has ever been affected in our town by the loss of the single member of the community. No man was better known or more generally respected. The many years he was accustomed to making his way to the bank with regularity so exact, riding a little brown pony, familiarly known along the road as “Jacob Faithful”, that his passing any given corner suffice to tell the time of day. Later on, disliking everything that savoured of show and vanity, he exchanged a pony for an unpretentious shut-up carriage. He never failed to enter the bank at 9am, and never left in the evening until the books were all made up and the cash was balanced to the uttermost penny. Many a time he had not scrupled to go in late to a dinner party, even at his own table, rather than neglect his duties at the desk. This did not come of any unworthy ‘amor nummi ; in Edward Loyd there was not the slightest taint of avarice; it was purely out of love of order and precision. This also rendered him indifferent to speculation, the desire to get rich by leaps, which, being a disorderly thing, he constantly discouraged……in his conduct towards others he was always kindly and amicable; he knew not what it was to be contentious, and sought, whenever the occasion arose, to promote peace. Grindon p 150 –53. ”In person Mr Edward Loyd was…well made, and compact. He had a fair, round, rosy, ample face, a fine old last–century castor countenance, a beautifully clear complexion, a baldhead, and lucid grey eyes. Come upon him wherever you might, he always had the air of a gentlemen – a certain refined simplicity tinged with stateliness." Grindon Page P 157. | AM10: =IF(AND(LEN(H10)>0,ISNA(IF(K10="Boy",VLOOKUP(A10,'Siblings of those BORN Loyd'!$AP$3:$AQ$70,2,FALSE),VLOOKUP(A10,'Children of Female Loyds'!$AR$5:$AS$60,2,FALSE)))),"d.s.p","") | AN10: =(IF(OR(L10=0,LEN(L10)=0),"",_xlfn.CONCAT(VLOOKUP(L10,$U$3:$X$230,4,FALSE)))) -> William (1729–1800: #1) | AO10: =(IF(OR(M10=0,LEN(M10)=0),"",_xlfn.CONCAT(VLOOKUP(M10,$U$3:$X$230,4,FALSE)))) | AP10: =(IF(OR(N10=0,LEN(N10)=0),"",_xlfn.CONCAT(VLOOKUP(N10,$U$3:$X$230,4,FALSE)))) | AQ10: =(IF(OR(O10=0,LEN(O10)=0),"",_xlfn.CONCAT(VLOOKUP(O10,$U$3:$X$230,4,FALSE)))) | AR10: =(IF(OR(P10=0,LEN(P10)=0),"",_xlfn.CONCAT(VLOOKUP(P10,$U$3:$X$230,4,FALSE)))) | AS10: =(IF(OR(Q10=0,LEN(Q10)=0),"",_xlfn.CONCAT(VLOOKUP(Q10,$U$3:$X$230,4,FALSE)))) | AT10: =(IF(OR(R10=0,LEN(R10)=0),"",_xlfn.CONCAT(VLOOKUP(R10,$U$3:$X$230,4,FALSE)))) | AU10: =(IF(OR(S10=0,LEN(S10)=0),"",_xlfn.CONCAT(VLOOKUP(S10,$U$3:$X$230,4,FALSE)))) | AW10: =VLOOKUP(A10,'Updated Bios & Spouse Details'!$A$1:$J$193,6,FALSE) -> Wales & England | AX10: =VLOOKUP($A10,'Loyd List 1-190 - Edit'!$P$2:$AQ$220,AX$1,FALSE) -> 8 | AY10: =IF(ISNA(VLOOKUP(A10,'Data check lookup table'!$G$2:$V$73,13,FALSE))," - ",VLOOKUP(A10,'Data check lookup table'!$G$2:$V$73,13,FALSE)) -> - | AZ10: =TEXT(J10,"dd/mm/yyyy") -> 30/01/1863 | BA10: =(IF(OR(Q10=0,LEN(Q10)=0),"",_xlfn.CONCAT(", ",VLOOKUP(Q10,$U$3:$X$230,4,FALSE)))) | BB10: =(IF(OR(R10=0,LEN(R10)=0),"",_xlfn.CONCAT("; ",VLOOKUP(R10,$U$3:$X$230,4,FALSE)))) | BI10: 30/01/1863
A11: ='Loyd List 1-190 - Edit'!C11 -> 9 | B11: =VLOOKUP($A11,'Loyd List 1-190 - Edit'!$C$1:$AQ$220,'Book Details - NO EDIT'!B$1,FALSE) -> Samuel | C11: =IF(VLOOKUP($A11,'Loyd List 1-190 - Edit'!$C$1:$AQ$220,'Book Details - NO EDIT'!C$1,FALSE)="","",VLOOKUP($A11,'Loyd List 1-190 - Edit'!$C$1:$AQ$220,'Book Details - NO EDIT'!C$1,FALSE)) -> Jones | D11: =IF(VLOOKUP($A11,'Loyd List 1-190 - Edit'!$C$1:$AQ$220,'Book Details - NO EDIT'!D$1,FALSE)="","",VLOOKUP($A11,'Loyd List 1-190 - Edit'!$C$1:$AQ$220,'Book Details - NO EDIT'!D$1,FALSE)) | E11: =IF(VLOOKUP($A11,'Loyd List 1-190 - Edit'!$C$1:$AQ$220,'Book Details - NO EDIT'!E$1,FALSE)="","",VLOOKUP($A11,'Loyd List 1-190 - Edit'!$C$1:$AQ$220,'Book Details - NO EDIT'!E$1,FALSE)) -> LOYD | F11: =IF(VLOOKUP($A11,'Loyd List 1-190 - Edit'!$C$1:$AQ$220,'Book Details - NO EDIT'!F$1,FALSE)="",B11,VLOOKUP($A11,'Loyd List 1-190 - Edit'!$C$1:$AQ$220,'Book Details - NO EDIT'!F$1,FALSE)) -> Samuel | G11: =IF(VLOOKUP($A11,'Loyd List 1-190 - Edit'!$C$1:$AQ$220,'Book Details - NO EDIT'!G$1,FALSE)="","",VALUE(VLOOKUP($A11,'Loyd List 1-190 - Edit'!$C$1:$AQ$220,'Book Details - NO EDIT'!G$1,FALSE))) -> 1796 | H11: =IF(VLOOKUP($A11,'Loyd List 1-190 - Edit'!$C$1:$AQ$220,'Book Details - NO EDIT'!H$1,FALSE)="","",VALUE(VLOOKUP($A11,'Loyd List 1-190 - Edit'!$C$1:$AQ$220,'Book Details - NO EDIT'!H$1,FALSE))) -> 1883 | I11: =IF(VLOOKUP($A11,'Loyd List 1-190 - Edit'!$C$1:$AQ$220,'Book Details - NO EDIT'!I$1,FALSE)="","",(VLOOKUP($A11,'Loyd List 1-190 - Edit'!$C$1:$AQ$220,'Book Details - NO EDIT'!I$1,FALSE))) -> 25/09/1796 | J11: =IF(VLOOKUP($A11,'Loyd List 1-190 - Edit'!$C$1:$AQ$220,'Book Details - NO EDIT'!J$1,FALSE)="","",(VLOOKUP($A11,'Loyd List 1-190 - Edit'!$C$1:$AQ$220,'Book Details - NO EDIT'!J$1,FALSE))) -> 17/11/1883 | K11: =VLOOKUP($A11,'Loyd List 1-190 - Edit'!$C$1:$AQ$220,'Book Details - NO EDIT'!K$1,FALSE) -> Boy | L11: =VLOOKUP($A11,'Loyd List 1-190 - Edit'!$C$1:$AQ$220,'Book Details - NO EDIT'!L$1,FALSE) -> 3 | M11: =IF(ISNA(VLOOKUP(L11,$A$3:$L$220,M$1,FALSE)),"",(VLOOKUP(L11,$A$3:$L$220,M$1,FALSE))) -> 1 | N11: =IF(ISNA(VLOOKUP(M11,$A$3:$L$220,N$1,FALSE)),"",(VLOOKUP(M11,$A$3:$L$220,N$1,FALSE))) -> 0 | O11: =IF(ISNA(VLOOKUP(N11,$A$3:$L$220,O$1,FALSE)),"",(VLOOKUP(N11,$A$3:$L$220,O$1,FALSE))) | P11: =IF(ISNA(VLOOKUP(O11,$A$3:$L$220,P$1,FALSE)),"",(VLOOKUP(O11,$A$3:$L$220,P$1,FALSE))) | Q11: =IF(ISNA(VLOOKUP(P11,$A$3:$L$220,Q$1,FALSE)),"",(VLOOKUP(P11,$A$3:$L$220,Q$1,FALSE))) | R11: =IF(ISNA(VLOOKUP(Q11,$A$3:$L$220,R$1,FALSE)),"",(VLOOKUP(Q11,$A$3:$L$220,R$1,FALSE))) | S11: =IF(ISNA(VLOOKUP(R11,$A$3:$L$220,S$1,FALSE)),"",(VLOOKUP(R11,$A$3:$L$220,S$1,FALSE))) | T11: =IF(L11=1,1,IF(M11=1,2,IF(N11=1,3,IF(O11=1,4,IF(P11=1,5,IF(Q11=1,6,IF(R11=1,7,IF(S11=1,8,0)))))))) -> 2 | U11: =A11 -> 9 | V11: =_xlfn.CONCAT(F11," (",G11,"–",H11,")") -> Samuel (1796–1883) | W11: =_xlfn.CONCAT(F11," (#",A11,")") -> Samuel (#9) | X11: =_xlfn.CONCAT(F11," (",G11,"–",H11,": #",A11,")") -> Samuel (1796–1883: #9) | Y11: =_xlfn.CONCAT(B11," ",IF(C11="",E11,_xlfn.CONCAT(C11," ",IF(D11="",E11,_xlfn.CONCAT(D11," ",E11))))) -> Samuel Jones LOYD | Z11: =VLOOKUP(L11,$U$2:$X$230,Z$1,FALSE) -> Lewis LOYD (1768–1858: #3) | AA11: =_xlfn.CONCAT(AN11," ",AO11," ",AP11," ",AQ11," ",AR11," ",AS11," ",AT11," ",AU11) -> Lewis LOYD (1768–1858: #3) William (1729–1800: #1) | AB11: =VLOOKUP(U11,'Siblings of those BORN Loyd'!$A$2:$G$230,7,FALSE) -> 0 – Only chlid | AC11: =IF(ISNA(IF(K11="Boy",VLOOKUP(A11,'Siblings of those BORN Loyd'!$AP$3:$AQ$70,2,FALSE),VLOOKUP(A11,'Children of Female Loyds'!$AR$5:$AT$60,3,FALSE))),AM11,IF(K11="Boy",VLOOKUP(A11,'Siblings of those BORN Loyd'!$AP$3:$AQ$70,2,FALSE),VLOOKUP(A11,'Children of Female Loyds'!$AR$5:$AT$60,3,FALSE))) -> 2 - Henry (1832–1833: #25); The Hon Harriet (1837–1920: #26) | AD11: =IF(AE11="d.s.p",_xlfn.CONCAT(AE11,"."),IF(AG11=0,"-",_xlfn.CONCAT(AG11," - ",AE11," ",AF11))) -> - | AE11: =IF(ISNA(IF(K11="Boy",VLOOKUP(A11,'Grandchildren of Male Loyds'!$AQ$3:$AS$51,3,FALSE),VLOOKUP(A11,'Grandchildren of Female Loyds'!$AX$5:$AZ$63,3,FALSE))),AM11,IF(K11="Boy",VLOOKUP(A11,'Grandchildren of Male Loyds'!$AQ$3:$AS$51,3,FALSE),VLOOKUP(A11,'Grandchildren of Female Loyds'!$AX$5:$AZ$63,3,FALSE))) | AF11: =IF(ISNA(VLOOKUP(A11,'Grandchildren Loyd Daughters'!$BD$5:$BF$50,4,FALSE)),"",VLOOKUP(A11,'Grandchildren Loyd Daughters'!$BD$5:$BF$50,3,FALSE)) | AG11: =IF(ISNA(VLOOKUP(A11,'Grandchildren of Male Loyds'!$AQ$3:$AR$60,2,FALSE)),0,VLOOKUP(A11,'Grandchildren of Male Loyds'!$AQ$3:$AR$60,2,FALSE))+IF(ISNA(VLOOKUP(A11,'Grandchildren of Female Loyds'!$AX$5:$AY$50,2,FALSE)),0,VLOOKUP(A11,'Grandchildren of Female Loyds'!$AX$5:$AY$50,2,FALSE))+IF(ISNA(VLOOKUP(A11,'Grandchildren Loyd Daughters'!$BD$5:$BE$50,2,FALSE)),0,VLOOKUP(A11,'Grandchildren Loyd Daughters'!$BD$5:$BE$50,2,FALSE)) -> 0 | AH11: =VLOOKUP($U11,'Loyd List 1-190 - Edit'!$P$3:$AJ$220,21,FALSE) -> Sarah JONES (b. 9 Sep 1759, d. 1 Oct 1821) | AI11: =VLOOKUP(A11,'Updated Bios & Spouse Details'!$A$1:$J$200,7,FALSE) -> Harriet WRIGHT (b. 1798/99, d. 6 Nov 1864) | AJ11: =IF(VLOOKUP($A11,'Loyd List 1-190 - Edit'!$C$1:$AQ$220,'Book Details - NO EDIT'!AJ$1,FALSE)="","",(VLOOKUP($A11,'Loyd List 1-190 - Edit'!$C$1:$AQ$220,'Book Details - NO EDIT'!AJ$1,FALSE))) -> 10/08/1829 | AK11: =VLOOKUP(A11,'Updated Bios & Spouse Details'!$A$1:$J$200,8,FALSE) -> Harriet, daughter of Ichabod WRIGHT of Mapperley Hall, Nottinghamshire. Buried at Lockinge, Nr. Wantage. Harriet Wright’s sister married Fredrick Paul IRBY ( Jan 1866). Their daughter later married Lewis Loyd (1811 - 1891: #13). The Wright’s also related to Foster-Harter, a cousin through Caroline Foster Loyd (1864 -1940: #47). | AL11: =VLOOKUP(A11,'Updated Bios & Spouse Details'!$A$1:$J$200,5,FALSE) -> Samuel, the 1st and last Baron OVERSTONE of Overstone and Fotheringhay both in the county of Northamptonshire, of Overstone Park [13], Northamptonshire, and of 2 Carlton Gardens, London SW1. Only son of Lewis LOYD (1768–1858: #3) of 43 Lothbury, London and of Overstone Park, Northamptonshire. Born 25 Sep 1796 at 43 Lothbury. Educated: Eton 1808/09-13 and Trinity College, Cambridge (MA 1818). Oxford (Hon DCL 1864). Career: Partner in Jones Loyds Bank 1817. MP for Hythe 1819-26. Partner in Jones Loyds Bank 1817. MP for Hythe 1819-26. Exchequer Bill (subsequently Public Works Loan) Commissioner 1831-75. Witness before Bank Charter Committee 1832. ‘Reflections and Further Reflections’ published 1837. Witness before Bank Charter Committee 1832. ‘Reflections and Further Reflections’ published 1837. Hand Loom Weavers Commissioner 1837-40. Appeared before Select Committee on Postage 1838. Articles published. Appeared before Committee on Banks of Issue 1840. Writer for Morning Chronicle 1840-1841. Appeared before Committee on Bills of Exchange 1841. Joined Anti Corn Law League 1843. Chairman of British Association for the relief of the Extreme Distress in Ireland and Scotland 1846-49. Commissioner for the Great Exhibition 1850. Raised to Peerage 5 Mar 1850 [14]. Trustee of National Gallery 1850. Senator of London University 1850-77. Letters to The Times signed ‘Mercator’ 1855-57. Exchequer Bill (subsequently Public Works Loan) Commissioner 1831-75. Decimal Coinage Commissioner 1855-60. Consulted by government over future of Act of 1844. Appeared before Committee on Bank Acts 1857. Active in opposition to GLADSTONE’s financial policy 1860. Member of Volunteer Commission 1862. Resigns from Senate of London University 1883. By c1881, Lord OVERSTONE was in receipt of an income that was equivalent to 0.02 per cent of total United Kingdom taxable income, and his investments in land comprised 0.1 per cent of the total land area of Britain. Although he was, therefore, the possessor of one of the largest fortunes of his day, he gave away considerable sums of money (averaging one-third of his total expenditure between 1863 and 1882) to relatives [15], friends and employees as well as to established charities. Died 17 Nov 1883 at 2 Carlton Gardens, London and buried at Lockinge, leaving Securities of £2,188,084, and Landed Property £3,114,262 (much settled on his son-in-law before his death). Issue: 1 son, 1 daughter. Portrait by Frank HOLL in possession of Christopher (1923–2013: #100) and subsequently with Thomas (1959– : #138). “The chief of the new commercial aristocracy is supposed to be Lord Overstone, one of the wealthiest subjects in the world, his fortune being estimated at five millions” - Great Governing Families of England 1865. Footnotes: [13] The building of the present large house was started in 1861 at the wish of Lady Overstone in place of the previous house which Lewis (1768–1858: #3) bought from the Kipling family. Three and a half years later Lady Overstone died and Lord Overstone disliked the new house so much that he lived almost entirely with his daughter and son-in-law at Lockinge and at 2 Carlton Gardens where his daughter and son-in-law also continued to live after Lord Overstone’s death. [14] Samuel's elevation to the peerage gave rise to the following lines: ‘The Banker Lord must have his name destroyed; The peerage must be pure, no peer a (l)Loyd; No longer by his City title known - Lord Overgold is now Lord Overstone’ - Grindon page 168. [15] His “papers contain many details of the extensive financial support which he gave to Mrs T K Loyd [widow of Thomas Kirkman LOYD (1812-57)] and her children. He seems to have supported them, paid for their education, and launched them on their careers” - O’Brien page 1057. | AM11: =IF(AND(LEN(H11)>0,ISNA(IF(K11="Boy",VLOOKUP(A11,'Siblings of those BORN Loyd'!$AP$3:$AQ$70,2,FALSE),VLOOKUP(A11,'Children of Female Loyds'!$AR$5:$AS$60,2,FALSE)))),"d.s.p","") | AN11: =(IF(OR(L11=0,LEN(L11)=0),"",_xlfn.CONCAT(VLOOKUP(L11,$U$3:$X$230,4,FALSE)))) -> Lewis LOYD (1768–1858: #3) | AO11: =(IF(OR(M11=0,LEN(M11)=0),"",_xlfn.CONCAT(VLOOKUP(M11,$U$3:$X$230,4,FALSE)))) -> William (1729–1800: #1) | AP11: =(IF(OR(N11=0,LEN(N11)=0),"",_xlfn.CONCAT(VLOOKUP(N11,$U$3:$X$230,4,FALSE)))) | AQ11: =(IF(OR(O11=0,LEN(O11)=0),"",_xlfn.CONCAT(VLOOKUP(O11,$U$3:$X$230,4,FALSE)))) | AR11: =(IF(OR(P11=0,LEN(P11)=0),"",_xlfn.CONCAT(VLOOKUP(P11,$U$3:$X$230,4,FALSE)))) | AS11: =(IF(OR(Q11=0,LEN(Q11)=0),"",_xlfn.CONCAT(VLOOKUP(Q11,$U$3:$X$230,4,FALSE)))) | AT11: =(IF(OR(R11=0,LEN(R11)=0),"",_xlfn.CONCAT(VLOOKUP(R11,$U$3:$X$230,4,FALSE)))) | AU11: =(IF(OR(S11=0,LEN(S11)=0),"",_xlfn.CONCAT(VLOOKUP(S11,$U$3:$X$230,4,FALSE)))) | AW11: =VLOOKUP(A11,'Updated Bios & Spouse Details'!$A$1:$J$193,6,FALSE) -> England | AX11: =VLOOKUP($A11,'Loyd List 1-190 - Edit'!$P$2:$AQ$220,AX$1,FALSE) -> 9 | AY11: =IF(ISNA(VLOOKUP(A11,'Data check lookup table'!$G$2:$V$73,13,FALSE))," - ",VLOOKUP(A11,'Data check lookup table'!$G$2:$V$73,13,FALSE)) -> - | AZ11: =TEXT(J11,"dd/mm/yyyy") -> 17/11/1883 | BA11: =(IF(OR(Q11=0,LEN(Q11)=0),"",_xlfn.CONCAT(", ",VLOOKUP(Q11,$U$3:$X$230,4,FALSE)))) | BB11: =(IF(OR(R11=0,LEN(R11)=0),"",_xlfn.CONCAT("; ",VLOOKUP(R11,$U$3:$X$230,4,FALSE)))) | BI11: 17/11/1883
A12: ='Loyd List 1-190 - Edit'!C12 -> 10 | B12: =VLOOKUP($A12,'Loyd List 1-190 - Edit'!$C$1:$AQ$220,'Book Details - NO EDIT'!B$1,FALSE) -> William | C12: =IF(VLOOKUP($A12,'Loyd List 1-190 - Edit'!$C$1:$AQ$220,'Book Details - NO EDIT'!C$1,FALSE)="","",VLOOKUP($A12,'Loyd List 1-190 - Edit'!$C$1:$AQ$220,'Book Details - NO EDIT'!C$1,FALSE)) -> Kirkman | D12: =IF(VLOOKUP($A12,'Loyd List 1-190 - Edit'!$C$1:$AQ$220,'Book Details - NO EDIT'!D$1,FALSE)="","",VLOOKUP($A12,'Loyd List 1-190 - Edit'!$C$1:$AQ$220,'Book Details - NO EDIT'!D$1,FALSE)) | E12: =IF(VLOOKUP($A12,'Loyd List 1-190 - Edit'!$C$1:$AQ$220,'Book Details - NO EDIT'!E$1,FALSE)="","",VLOOKUP($A12,'Loyd List 1-190 - Edit'!$C$1:$AQ$220,'Book Details - NO EDIT'!E$1,FALSE)) -> LOYD | F12: =IF(VLOOKUP($A12,'Loyd List 1-190 - Edit'!$C$1:$AQ$220,'Book Details - NO EDIT'!F$1,FALSE)="",B12,VLOOKUP($A12,'Loyd List 1-190 - Edit'!$C$1:$AQ$220,'Book Details - NO EDIT'!F$1,FALSE)) -> William | G12: =IF(VLOOKUP($A12,'Loyd List 1-190 - Edit'!$C$1:$AQ$220,'Book Details - NO EDIT'!G$1,FALSE)="","",VALUE(VLOOKUP($A12,'Loyd List 1-190 - Edit'!$C$1:$AQ$220,'Book Details - NO EDIT'!G$1,FALSE))) -> 1809 | H12: =IF(VLOOKUP($A12,'Loyd List 1-190 - Edit'!$C$1:$AQ$220,'Book Details - NO EDIT'!H$1,FALSE)="","",VALUE(VLOOKUP($A12,'Loyd List 1-190 - Edit'!$C$1:$AQ$220,'Book Details - NO EDIT'!H$1,FALSE))) -> 1879 | I12: =IF(VLOOKUP($A12,'Loyd List 1-190 - Edit'!$C$1:$AQ$220,'Book Details - NO EDIT'!I$1,FALSE)="","",(VLOOKUP($A12,'Loyd List 1-190 - Edit'!$C$1:$AQ$220,'Book Details - NO EDIT'!I$1,FALSE))) -> 09/10/1809 | J12: =IF(VLOOKUP($A12,'Loyd List 1-190 - Edit'!$C$1:$AQ$220,'Book Details - NO EDIT'!J$1,FALSE)="","",(VLOOKUP($A12,'Loyd List 1-190 - Edit'!$C$1:$AQ$220,'Book Details - NO EDIT'!J$1,FALSE))) -> 14/06/1879 | K12: =VLOOKUP($A12,'Loyd List 1-190 - Edit'!$C$1:$AQ$220,'Book Details - NO EDIT'!K$1,FALSE) -> Boy | L12: =VLOOKUP($A12,'Loyd List 1-190 - Edit'!$C$1:$AQ$220,'Book Details - NO EDIT'!L$1,FALSE) -> 4 | M12: =IF(ISNA(VLOOKUP(L12,$A$3:$L$220,M$1,FALSE)),"",(VLOOKUP(L12,$A$3:$L$220,M$1,FALSE))) -> 1 | N12: =IF(ISNA(VLOOKUP(M12,$A$3:$L$220,N$1,FALSE)),"",(VLOOKUP(M12,$A$3:$L$220,N$1,FALSE))) -> 0 | O12: =IF(ISNA(VLOOKUP(N12,$A$3:$L$220,O$1,FALSE)),"",(VLOOKUP(N12,$A$3:$L$220,O$1,FALSE))) | P12: =IF(ISNA(VLOOKUP(O12,$A$3:$L$220,P$1,FALSE)),"",(VLOOKUP(O12,$A$3:$L$220,P$1,FALSE))) | Q12: =IF(ISNA(VLOOKUP(P12,$A$3:$L$220,Q$1,FALSE)),"",(VLOOKUP(P12,$A$3:$L$220,Q$1,FALSE))) | R12: =IF(ISNA(VLOOKUP(Q12,$A$3:$L$220,R$1,FALSE)),"",(VLOOKUP(Q12,$A$3:$L$220,R$1,FALSE))) | S12: =IF(ISNA(VLOOKUP(R12,$A$3:$L$220,S$1,FALSE)),"",(VLOOKUP(R12,$A$3:$L$220,S$1,FALSE))) | T12: =IF(L12=1,1,IF(M12=1,2,IF(N12=1,3,IF(O12=1,4,IF(P12=1,5,IF(Q12=1,6,IF(R12=1,7,IF(S12=1,8,0)))))))) -> 2 | U12: =A12 -> 10 | V12: =_xlfn.CONCAT(F12," (",G12,"–",H12,")") -> William (1809–1879) | W12: =_xlfn.CONCAT(F12," (#",A12,")") -> William (#10) | X12: =_xlfn.CONCAT(F12," (",G12,"–",H12,": #",A12,")") -> William (1809–1879: #10) | Y12: =_xlfn.CONCAT(B12," ",IF(C12="",E12,_xlfn.CONCAT(C12," ",IF(D12="",E12,_xlfn.CONCAT(D12," ",E12))))) -> William Kirkman LOYD | Z12: =VLOOKUP(L12,$U$2:$X$230,Z$1,FALSE) -> William (1770–1828: #4) | AA12: =_xlfn.CONCAT(AN12," ",AO12," ",AP12," ",AQ12," ",AR12," ",AS12," ",AT12," ",AU12) -> William (1770–1828: #4) William (1729–1800: #1) | AB12: =VLOOKUP(U12,'Siblings of those BORN Loyd'!$A$2:$G$230,7,FALSE) -> 6 – Eliza (1810–1861: #12) Thomas (1812–1857: #14) Maria (1814–1900: #16) Edward (1815–1815: #17) John (1817–1818: #20) Lewis (1819–1841: #21) | AC12: =IF(ISNA(IF(K12="Boy",VLOOKUP(A12,'Siblings of those BORN Loyd'!$AP$3:$AQ$70,2,FALSE),VLOOKUP(A12,'Children of Female Loyds'!$AR$5:$AT$60,3,FALSE))),AM12,IF(K12="Boy",VLOOKUP(A12,'Siblings of those BORN Loyd'!$AP$3:$AQ$70,2,FALSE),VLOOKUP(A12,'Children of Female Loyds'!$AR$5:$AT$60,3,FALSE))) -> d.s.p | AD12: =IF(AE12="d.s.p",_xlfn.CONCAT(AE12,"."),IF(AG12=0,"-",_xlfn.CONCAT(AG12," - ",AE12," ",AF12))) -> d.s.p. | AE12: =IF(ISNA(IF(K12="Boy",VLOOKUP(A12,'Grandchildren of Male Loyds'!$AQ$3:$AS$51,3,FALSE),VLOOKUP(A12,'Grandchildren of Female Loyds'!$AX$5:$AZ$63,3,FALSE))),AM12,IF(K12="Boy",VLOOKUP(A12,'Grandchildren of Male Loyds'!$AQ$3:$AS$51,3,FALSE),VLOOKUP(A12,'Grandchildren of Female Loyds'!$AX$5:$AZ$63,3,FALSE))) -> d.s.p | AF12: =IF(ISNA(VLOOKUP(A12,'Grandchildren Loyd Daughters'!$BD$5:$BF$50,4,FALSE)),"",VLOOKUP(A12,'Grandchildren Loyd Daughters'!$BD$5:$BF$50,3,FALSE)) | AG12: =IF(ISNA(VLOOKUP(A12,'Grandchildren of Male Loyds'!$AQ$3:$AR$60,2,FALSE)),0,VLOOKUP(A12,'Grandchildren of Male Loyds'!$AQ$3:$AR$60,2,FALSE))+IF(ISNA(VLOOKUP(A12,'Grandchildren of Female Loyds'!$AX$5:$AY$50,2,FALSE)),0,VLOOKUP(A12,'Grandchildren of Female Loyds'!$AX$5:$AY$50,2,FALSE))+IF(ISNA(VLOOKUP(A12,'Grandchildren Loyd Daughters'!$BD$5:$BE$50,2,FALSE)),0,VLOOKUP(A12,'Grandchildren Loyd Daughters'!$BD$5:$BE$50,2,FALSE)) -> 0 | AH12: =VLOOKUP($U12,'Loyd List 1-190 - Edit'!$P$3:$AJ$220,21,FALSE) -> Martha KIRKMAN (b. 17 Nov 1775, d. 4 Feb 1857) | AI12: =VLOOKUP(A12,'Updated Bios & Spouse Details'!$A$1:$J$200,7,FALSE) -> Unmarried | AJ12: =IF(VLOOKUP($A12,'Loyd List 1-190 - Edit'!$C$1:$AQ$220,'Book Details - NO EDIT'!AJ$1,FALSE)="","",(VLOOKUP($A12,'Loyd List 1-190 - Edit'!$C$1:$AQ$220,'Book Details - NO EDIT'!AJ$1,FALSE))) -> - | AK12: =VLOOKUP(A12,'Updated Bios & Spouse Details'!$A$1:$J$200,8,FALSE) -> - | AL12: =VLOOKUP(A12,'Updated Bios & Spouse Details'!$A$1:$J$200,5,FALSE) -> Eldest son of William LOYD (1770–1828: #4) of 7 Bread Street, Cheapside, London EC2. Born 9 Oct 1809. Educated at the Charterhouse in London. Appointed a student at Addiscombe, the East India Company’s military college in Surrey in Jan 1824. Commissioned 2nd Lieutenant 18 Dec 1825. Sailed for Madras 8 Mar 1826, arrived 12 Jul 1826 (aged 16). Joined 3rd Battalion, Madras Artillery. Promoted Lieutenant 6 Aug 1827. Acting Staff Officer 1828/29. Adjutant, 2nd Battalion Sep 1831-Jan 1835. D Troop, Horse Brigade Jan 1835-Oct 1838. Appointed to Artillery of Nizam of Hyderabad Oct 1838. Gazetted Captain 1840. Active Service in 1841, 1849 and 1851. Gazetted Major Nov 1851. Active service in 1853. Retired with rank of Lieut Colonel, Madras Artillery 1854. Departed India 30 Aug 1854. Arrived London after 28 years service 20 Oct 1854. Became guardian of the seven young children of his brother Thomas Kirkman LOYD (1812–57: #14), killed in Indian Mutiny. He lived at: 17 Marlborough Place, St John’s Wood, London NW8. 1854-57; Brighton and elsewhere (1857-1860; 30 Leinster Square, London W2. (1860-64); 7 Gloucester Place, London. (1864-66); 45 Dover St, London W1. (1866-74); 7 Broadwater Down, Tunbridge Wells, Kent. (1874-79). William died, unmarried, 14 Jun 1879 and was buried 21 Jun 1879 in the Tunbridge Wells Cemetery. DSP Portrait by Eden Upton EDDIS in possession of Peter Haig LOYD (1922–2022: #98) until passed to William (1973– : #155). “After the Colonel had served continuously in the tropics for more than a quarter of a century, his health began to fail. In the autumn of 1853 he was granted, on medical recommendation, eight months leave of absence for the purpose of taking a sea voyage, and obtaining a change of air which, it was hoped, would restore his health. On the 1 Nov 1853 he started his eight months’ sick leave, and saw a railway train for the first time in his life at Bombay in the middle of the month. From Bombay he went to Ceylon where he met his brother, T K Loyd - my grandfather. They travelled together by sea to Calcutta where they remained for a short time. The Colonel returned alone by sea to Bombay, and went from there to Mahabaleshwar where he remained for three months. As might perhaps be expected, this continued sojourn in the tropics failed to restore him to health, and he had to leave India. He retired from the service with the rank and pension of a Lieut. Colonel. On 30 Aug 1854, he left Bombay by steamship for Suez. Thence he proceeded by the overland route to Alexandria where he embarked on an Austrian Lloyd steamer for Trieste. From there he travelled, by Venice, across Europe by train and diligence, reaching London on 20 Oct 1854 after twenty-eight years’ absence. To return to England in middle life with impaired health after an uninterrupted spell of service in India, seems to have been quite usual in those days. In order to understand properly the Colonel’s papers it is necessary to go back a little. His father, William (1809–1879: #4), was the only one of the four brothers who came from Wales in search of fortune to fail in business [and as a result of which] his brothers had assisted him and his family. When the Colonel returned from India, his surviving uncles were old men, and their sons and daughters thoroughly well established in England. His English diaries are very interesting because he moved about so much and had so many friends. One of the points which impresses...is the genius he possessed for enjoying the friendship of people of widely varying circumstances and interests. In spite of troubles and bereavements, not very good health and the inherent loneliness of the man with no family of his own, he must have had some very happy times: discovering his native Islands; constantly staying in the country houses of his relatives and friends; frequently travelling abroad; hunting and shooting a little in England; always helping those around him and delighting in their affection; and meeting through the Overstones and others much that was distinguished and interesting in English life. For his mind, informed by wide reading and by constant travel, his delightful personality and his innate goodness gave him the key to many worlds. The Colonel never married and the chief concern of his life became the guardianship of the seven children of his brother, my grandfather, who perished in the Indian Mutiny, leaving a widow and young family. The Colonel assumed a father’s responsibility to them and carried out this labour of love with unswerving devotion and unselfishness. In return he possessed their deep affection and lived to see them grow up and start in the professions he was at such pains to help them enter. Lord Overstone and his cousins stood behind the little group with their wise and generous support. The very difficult and delicate task of negotiating between the young family of his dead brother and his wealthy cousins devolved upon the Colonel. It is impossible to read [his] diaries without noticing the exceeding kindness of these cousins to the Colonel’s ‘wards’; not only financially but in other ways as well. All [these] circumstances....combined to save the Colonel from the lonely years in England that so often awaited men who had spent their youth and their health in India. His restlessness is manifested by his frequent changes of abode, as well as by his love of movement” - from notes of Reggie (1886–1961: #61). | AM12: =IF(AND(LEN(H12)>0,ISNA(IF(K12="Boy",VLOOKUP(A12,'Siblings of those BORN Loyd'!$AP$3:$AQ$70,2,FALSE),VLOOKUP(A12,'Children of Female Loyds'!$AR$5:$AS$60,2,FALSE)))),"d.s.p","") -> d.s.p | AN12: =(IF(OR(L12=0,LEN(L12)=0),"",_xlfn.CONCAT(VLOOKUP(L12,$U$3:$X$230,4,FALSE)))) -> William (1770–1828: #4) | AO12: =(IF(OR(M12=0,LEN(M12)=0),"",_xlfn.CONCAT(VLOOKUP(M12,$U$3:$X$230,4,FALSE)))) -> William (1729–1800: #1) | AP12: =(IF(OR(N12=0,LEN(N12)=0),"",_xlfn.CONCAT(VLOOKUP(N12,$U$3:$X$230,4,FALSE)))) | AQ12: =(IF(OR(O12=0,LEN(O12)=0),"",_xlfn.CONCAT(VLOOKUP(O12,$U$3:$X$230,4,FALSE)))) | AR12: =(IF(OR(P12=0,LEN(P12)=0),"",_xlfn.CONCAT(VLOOKUP(P12,$U$3:$X$230,4,FALSE)))) | AS12: =(IF(OR(Q12=0,LEN(Q12)=0),"",_xlfn.CONCAT(VLOOKUP(Q12,$U$3:$X$230,4,FALSE)))) | AT12: =(IF(OR(R12=0,LEN(R12)=0),"",_xlfn.CONCAT(VLOOKUP(R12,$U$3:$X$230,4,FALSE)))) | AU12: =(IF(OR(S12=0,LEN(S12)=0),"",_xlfn.CONCAT(VLOOKUP(S12,$U$3:$X$230,4,FALSE)))) | AW12: =VLOOKUP(A12,'Updated Bios & Spouse Details'!$A$1:$J$193,6,FALSE) -> England & India | AX12: =VLOOKUP($A12,'Loyd List 1-190 - Edit'!$P$2:$AQ$220,AX$1,FALSE) -> 10 | AY12: =IF(ISNA(VLOOKUP(A12,'Data check lookup table'!$G$2:$V$73,13,FALSE))," - ",VLOOKUP(A12,'Data check lookup table'!$G$2:$V$73,13,FALSE)) -> - | AZ12: =TEXT(J12,"dd/mm/yyyy") -> 14/06/1879 | BA12: =(IF(OR(Q12=0,LEN(Q12)=0),"",_xlfn.CONCAT(", ",VLOOKUP(Q12,$U$3:$X$230,4,FALSE)))) | BB12: =(IF(OR(R12=0,LEN(R12)=0),"",_xlfn.CONCAT("; ",VLOOKUP(R12,$U$3:$X$230,4,FALSE)))) | BI12: 14/06/1879
A13: ='Loyd List 1-190 - Edit'!C13 -> 11 | B13: =VLOOKUP($A13,'Loyd List 1-190 - Edit'!$C$1:$AQ$220,'Book Details - NO EDIT'!B$1,FALSE) -> Sarah | C13: =IF(VLOOKUP($A13,'Loyd List 1-190 - Edit'!$C$1:$AQ$220,'Book Details - NO EDIT'!C$1,FALSE)="","",VLOOKUP($A13,'Loyd List 1-190 - Edit'!$C$1:$AQ$220,'Book Details - NO EDIT'!C$1,FALSE)) | D13: =IF(VLOOKUP($A13,'Loyd List 1-190 - Edit'!$C$1:$AQ$220,'Book Details - NO EDIT'!D$1,FALSE)="","",VLOOKUP($A13,'Loyd List 1-190 - Edit'!$C$1:$AQ$220,'Book Details - NO EDIT'!D$1,FALSE)) | E13: =IF(VLOOKUP($A13,'Loyd List 1-190 - Edit'!$C$1:$AQ$220,'Book Details - NO EDIT'!E$1,FALSE)="","",VLOOKUP($A13,'Loyd List 1-190 - Edit'!$C$1:$AQ$220,'Book Details - NO EDIT'!E$1,FALSE)) -> LOYD | F13: =IF(VLOOKUP($A13,'Loyd List 1-190 - Edit'!$C$1:$AQ$220,'Book Details - NO EDIT'!F$1,FALSE)="",B13,VLOOKUP($A13,'Loyd List 1-190 - Edit'!$C$1:$AQ$220,'Book Details - NO EDIT'!F$1,FALSE)) -> Sarah | G13: =IF(VLOOKUP($A13,'Loyd List 1-190 - Edit'!$C$1:$AQ$220,'Book Details - NO EDIT'!G$1,FALSE)="","",VALUE(VLOOKUP($A13,'Loyd List 1-190 - Edit'!$C$1:$AQ$220,'Book Details - NO EDIT'!G$1,FALSE))) -> 1810 | H13: =IF(VLOOKUP($A13,'Loyd List 1-190 - Edit'!$C$1:$AQ$220,'Book Details - NO EDIT'!H$1,FALSE)="","",VALUE(VLOOKUP($A13,'Loyd List 1-190 - Edit'!$C$1:$AQ$220,'Book Details - NO EDIT'!H$1,FALSE))) -> 1858 | I13: =IF(VLOOKUP($A13,'Loyd List 1-190 - Edit'!$C$1:$AQ$220,'Book Details - NO EDIT'!I$1,FALSE)="","",(VLOOKUP($A13,'Loyd List 1-190 - Edit'!$C$1:$AQ$220,'Book Details - NO EDIT'!I$1,FALSE))) -> 30/05/1810 | J13: =IF(VLOOKUP($A13,'Loyd List 1-190 - Edit'!$C$1:$AQ$220,'Book Details - NO EDIT'!J$1,FALSE)="","",(VLOOKUP($A13,'Loyd List 1-190 - Edit'!$C$1:$AQ$220,'Book Details - NO EDIT'!J$1,FALSE))) -> 15/06/1858 | K13: =VLOOKUP($A13,'Loyd List 1-190 - Edit'!$C$1:$AQ$220,'Book Details - NO EDIT'!K$1,FALSE) -> Girl | L13: =VLOOKUP($A13,'Loyd List 1-190 - Edit'!$C$1:$AQ$220,'Book Details - NO EDIT'!L$1,FALSE) -> 8 | M13: =IF(ISNA(VLOOKUP(L13,$A$3:$L$220,M$1,FALSE)),"",(VLOOKUP(L13,$A$3:$L$220,M$1,FALSE))) -> 1 | N13: =IF(ISNA(VLOOKUP(M13,$A$3:$L$220,N$1,FALSE)),"",(VLOOKUP(M13,$A$3:$L$220,N$1,FALSE))) -> 0 | O13: =IF(ISNA(VLOOKUP(N13,$A$3:$L$220,O$1,FALSE)),"",(VLOOKUP(N13,$A$3:$L$220,O$1,FALSE))) | P13: =IF(ISNA(VLOOKUP(O13,$A$3:$L$220,P$1,FALSE)),"",(VLOOKUP(O13,$A$3:$L$220,P$1,FALSE))) | Q13: =IF(ISNA(VLOOKUP(P13,$A$3:$L$220,Q$1,FALSE)),"",(VLOOKUP(P13,$A$3:$L$220,Q$1,FALSE))) | R13: =IF(ISNA(VLOOKUP(Q13,$A$3:$L$220,R$1,FALSE)),"",(VLOOKUP(Q13,$A$3:$L$220,R$1,FALSE))) | S13: =IF(ISNA(VLOOKUP(R13,$A$3:$L$220,S$1,FALSE)),"",(VLOOKUP(R13,$A$3:$L$220,S$1,FALSE))) | T13: =IF(L13=1,1,IF(M13=1,2,IF(N13=1,3,IF(O13=1,4,IF(P13=1,5,IF(Q13=1,6,IF(R13=1,7,IF(S13=1,8,0)))))))) -> 2 | U13: =A13 -> 11 | V13: =_xlfn.CONCAT(F13," (",G13,"–",H13,")") -> Sarah (1810–1858) | W13: =_xlfn.CONCAT(F13," (#",A13,")") -> Sarah (#11) | X13: =_xlfn.CONCAT(F13," (",G13,"–",H13,": #",A13,")") -> Sarah (1810–1858: #11) | Y13: =_xlfn.CONCAT(B13," ",IF(C13="",E13,_xlfn.CONCAT(C13," ",IF(D13="",E13,_xlfn.CONCAT(D13," ",E13))))) -> Sarah LOYD | Z13: =VLOOKUP(L13,$U$2:$X$230,Z$1,FALSE) -> Edward (1780–1863: #8) | AA13: =_xlfn.CONCAT(AN13," ",AO13," ",AP13," ",AQ13," ",AR13," ",AS13," ",AT13," ",AU13) -> Edward (1780–1863: #8) William (1729–1800: #1) | AB13: =VLOOKUP(U13,'Siblings of those BORN Loyd'!$A$2:$G$230,7,FALSE) -> 7 – Lewis (1811–1891: #13) Annie (1813–1834: #15) Kate (1815–1905: #18) Hannah (1817–1907: #19) Edward (1820–1890: #22) William (1821–1885: #23) Fanny (1824–1856: #24) | AC13: =IF(ISNA(IF(K13="Boy",VLOOKUP(A13,'Siblings of those BORN Loyd'!$AP$3:$AQ$70,2,FALSE),VLOOKUP(A13,'Children of Female Loyds'!$AR$5:$AT$60,3,FALSE))),AM13,IF(K13="Boy",VLOOKUP(A13,'Siblings of those BORN Loyd'!$AP$3:$AQ$70,2,FALSE),VLOOKUP(A13,'Children of Female Loyds'!$AR$5:$AT$60,3,FALSE))) -> 5 - Emma BENYON (1838 - 1913: #11a) Sarah BENYON (1839 - 1863: #11b) Henry BENYON (1841 - 1861: #11c) Fanny BENYON (1842 - 1845: #11d) Edward BENYON (1845 - 1903: #11e) | AD13: =IF(AE13="d.s.p",_xlfn.CONCAT(AE13,"."),IF(AG13=0,"-",_xlfn.CONCAT(AG13," - ",AE13," ",AF13))) -> - | AE13: =IF(ISNA(IF(K13="Boy",VLOOKUP(A13,'Grandchildren of Male Loyds'!$AQ$3:$AS$51,3,FALSE),VLOOKUP(A13,'Grandchildren of Female Loyds'!$AX$5:$AZ$63,3,FALSE))),AM13,IF(K13="Boy",VLOOKUP(A13,'Grandchildren of Male Loyds'!$AQ$3:$AS$51,3,FALSE),VLOOKUP(A13,'Grandchildren of Female Loyds'!$AX$5:$AZ$63,3,FALSE))) | AF13: =IF(ISNA(VLOOKUP(A13,'Grandchildren Loyd Daughters'!$BD$5:$BF$50,4,FALSE)),"",VLOOKUP(A13,'Grandchildren Loyd Daughters'!$BD$5:$BF$50,3,FALSE)) | AG13: =IF(ISNA(VLOOKUP(A13,'Grandchildren of Male Loyds'!$AQ$3:$AR$60,2,FALSE)),0,VLOOKUP(A13,'Grandchildren of Male Loyds'!$AQ$3:$AR$60,2,FALSE))+IF(ISNA(VLOOKUP(A13,'Grandchildren of Female Loyds'!$AX$5:$AY$50,2,FALSE)),0,VLOOKUP(A13,'Grandchildren of Female Loyds'!$AX$5:$AY$50,2,FALSE))+IF(ISNA(VLOOKUP(A13,'Grandchildren Loyd Daughters'!$BD$5:$BE$50,2,FALSE)),0,VLOOKUP(A13,'Grandchildren Loyd Daughters'!$BD$5:$BE$50,2,FALSE)) -> 0 | AH13: =VLOOKUP($U13,'Loyd List 1-190 - Edit'!$P$3:$AJ$220,21,FALSE) -> Sarah TAYLOR (b.5 Jul 1785, d. 19 Jan 1863) | AI13: =VLOOKUP(A13,'Updated Bios & Spouse Details'!$A$1:$J$200,7,FALSE) -> Henry Bombonus BENYON (b. 3 Mar 1806, d. 25 Feb 1849) | AJ13: =IF(VLOOKUP($A13,'Loyd List 1-190 - Edit'!$C$1:$AQ$220,'Book Details - NO EDIT'!AJ$1,FALSE)="","",(VLOOKUP($A13,'Loyd List 1-190 - Edit'!$C$1:$AQ$220,'Book Details - NO EDIT'!AJ$1,FALSE))) -> 01/10/1835 | AK13: =VLOOKUP(A13,'Updated Bios & Spouse Details'!$A$1:$J$200,8,FALSE) -> Married Henry at the Collegiate Church, Manchester (later Manchester Cathedral). Henry buried with his daughter, Fanny, in a vault at Roundhay Church) of Roundhay Lodge, Leeds. | AL13: =VLOOKUP(A13,'Updated Bios & Spouse Details'!$A$1:$J$200,5,FALSE) -> Sarah was the eldest daughter of Edward (1780–1863: #8) of Coombe House, Coombe Lane, Croydon, Surrey. Born 30 May 1810. Died 15 Jun 1858, buried at Hollington, Nr. Hastings, Sussex. Roddy SALE (#97d), in 2022, has portrait of Sarah BENYON (1839 – 1863: #11b). Issue: 3 daughters, 2 sons. | AM13: =IF(AND(LEN(H13)>0,ISNA(IF(K13="Boy",VLOOKUP(A13,'Siblings of those BORN Loyd'!$AP$3:$AQ$70,2,FALSE),VLOOKUP(A13,'Children of Female Loyds'!$AR$5:$AS$60,2,FALSE)))),"d.s.p","") | AN13: =(IF(OR(L13=0,LEN(L13)=0),"",_xlfn.CONCAT(VLOOKUP(L13,$U$3:$X$230,4,FALSE)))) -> Edward (1780–1863: #8) | AO13: =(IF(OR(M13=0,LEN(M13)=0),"",_xlfn.CONCAT(VLOOKUP(M13,$U$3:$X$230,4,FALSE)))) -> William (1729–1800: #1) | AP13: =(IF(OR(N13=0,LEN(N13)=0),"",_xlfn.CONCAT(VLOOKUP(N13,$U$3:$X$230,4,FALSE)))) | AQ13: =(IF(OR(O13=0,LEN(O13)=0),"",_xlfn.CONCAT(VLOOKUP(O13,$U$3:$X$230,4,FALSE)))) | AR13: =(IF(OR(P13=0,LEN(P13)=0),"",_xlfn.CONCAT(VLOOKUP(P13,$U$3:$X$230,4,FALSE)))) | AS13: =(IF(OR(Q13=0,LEN(Q13)=0),"",_xlfn.CONCAT(VLOOKUP(Q13,$U$3:$X$230,4,FALSE)))) | AT13: =(IF(OR(R13=0,LEN(R13)=0),"",_xlfn.CONCAT(VLOOKUP(R13,$U$3:$X$230,4,FALSE)))) | AU13: =(IF(OR(S13=0,LEN(S13)=0),"",_xlfn.CONCAT(VLOOKUP(S13,$U$3:$X$230,4,FALSE)))) | AW13: =VLOOKUP(A13,'Updated Bios & Spouse Details'!$A$1:$J$193,6,FALSE) -> England | AX13: =VLOOKUP($A13,'Loyd List 1-190 - Edit'!$P$2:$AQ$220,AX$1,FALSE) -> 11 | AY13: =IF(ISNA(VLOOKUP(A13,'Data check lookup table'!$G$2:$V$73,13,FALSE))," - ",VLOOKUP(A13,'Data check lookup table'!$G$2:$V$73,13,FALSE)) -> - | AZ13: =TEXT(J13,"dd/mm/yyyy") -> 15/06/1858 | BA13: =(IF(OR(Q13=0,LEN(Q13)=0),"",_xlfn.CONCAT(", ",VLOOKUP(Q13,$U$3:$X$230,4,FALSE)))) | BB13: =(IF(OR(R13=0,LEN(R13)=0),"",_xlfn.CONCAT("; ",VLOOKUP(R13,$U$3:$X$230,4,FALSE)))) | BI13: 15/06/1858
A14: ='Loyd List 1-190 - Edit'!C14 -> 12 | B14: =VLOOKUP($A14,'Loyd List 1-190 - Edit'!$C$1:$AQ$220,'Book Details - NO EDIT'!B$1,FALSE) -> Eliza | C14: =IF(VLOOKUP($A14,'Loyd List 1-190 - Edit'!$C$1:$AQ$220,'Book Details - NO EDIT'!C$1,FALSE)="","",VLOOKUP($A14,'Loyd List 1-190 - Edit'!$C$1:$AQ$220,'Book Details - NO EDIT'!C$1,FALSE)) | D14: =IF(VLOOKUP($A14,'Loyd List 1-190 - Edit'!$C$1:$AQ$220,'Book Details - NO EDIT'!D$1,FALSE)="","",VLOOKUP($A14,'Loyd List 1-190 - Edit'!$C$1:$AQ$220,'Book Details - NO EDIT'!D$1,FALSE)) | E14: =IF(VLOOKUP($A14,'Loyd List 1-190 - Edit'!$C$1:$AQ$220,'Book Details - NO EDIT'!E$1,FALSE)="","",VLOOKUP($A14,'Loyd List 1-190 - Edit'!$C$1:$AQ$220,'Book Details - NO EDIT'!E$1,FALSE)) -> LOYD | F14: =IF(VLOOKUP($A14,'Loyd List 1-190 - Edit'!$C$1:$AQ$220,'Book Details - NO EDIT'!F$1,FALSE)="",B14,VLOOKUP($A14,'Loyd List 1-190 - Edit'!$C$1:$AQ$220,'Book Details - NO EDIT'!F$1,FALSE)) -> Eliza | G14: =IF(VLOOKUP($A14,'Loyd List 1-190 - Edit'!$C$1:$AQ$220,'Book Details - NO EDIT'!G$1,FALSE)="","",VALUE(VLOOKUP($A14,'Loyd List 1-190 - Edit'!$C$1:$AQ$220,'Book Details - NO EDIT'!G$1,FALSE))) -> 1810 | H14: =IF(VLOOKUP($A14,'Loyd List 1-190 - Edit'!$C$1:$AQ$220,'Book Details - NO EDIT'!H$1,FALSE)="","",VALUE(VLOOKUP($A14,'Loyd List 1-190 - Edit'!$C$1:$AQ$220,'Book Details - NO EDIT'!H$1,FALSE))) -> 1861 | I14: =IF(VLOOKUP($A14,'Loyd List 1-190 - Edit'!$C$1:$AQ$220,'Book Details - NO EDIT'!I$1,FALSE)="","",(VLOOKUP($A14,'Loyd List 1-190 - Edit'!$C$1:$AQ$220,'Book Details - NO EDIT'!I$1,FALSE))) -> 30/11/1810 | J14: =IF(VLOOKUP($A14,'Loyd List 1-190 - Edit'!$C$1:$AQ$220,'Book Details - NO EDIT'!J$1,FALSE)="","",(VLOOKUP($A14,'Loyd List 1-190 - Edit'!$C$1:$AQ$220,'Book Details - NO EDIT'!J$1,FALSE))) -> 03/10/1861 | K14: =VLOOKUP($A14,'Loyd List 1-190 - Edit'!$C$1:$AQ$220,'Book Details - NO EDIT'!K$1,FALSE) -> Girl | L14: =VLOOKUP($A14,'Loyd List 1-190 - Edit'!$C$1:$AQ$220,'Book Details - NO EDIT'!L$1,FALSE) -> 4 | M14: =IF(ISNA(VLOOKUP(L14,$A$3:$L$220,M$1,FALSE)),"",(VLOOKUP(L14,$A$3:$L$220,M$1,FALSE))) -> 1 | N14: =IF(ISNA(VLOOKUP(M14,$A$3:$L$220,N$1,FALSE)),"",(VLOOKUP(M14,$A$3:$L$220,N$1,FALSE))) -> 0 | O14: =IF(ISNA(VLOOKUP(N14,$A$3:$L$220,O$1,FALSE)),"",(VLOOKUP(N14,$A$3:$L$220,O$1,FALSE))) | P14: =IF(ISNA(VLOOKUP(O14,$A$3:$L$220,P$1,FALSE)),"",(VLOOKUP(O14,$A$3:$L$220,P$1,FALSE))) | Q14: =IF(ISNA(VLOOKUP(P14,$A$3:$L$220,Q$1,FALSE)),"",(VLOOKUP(P14,$A$3:$L$220,Q$1,FALSE))) | R14: =IF(ISNA(VLOOKUP(Q14,$A$3:$L$220,R$1,FALSE)),"",(VLOOKUP(Q14,$A$3:$L$220,R$1,FALSE))) | S14: =IF(ISNA(VLOOKUP(R14,$A$3:$L$220,S$1,FALSE)),"",(VLOOKUP(R14,$A$3:$L$220,S$1,FALSE))) | T14: =IF(L14=1,1,IF(M14=1,2,IF(N14=1,3,IF(O14=1,4,IF(P14=1,5,IF(Q14=1,6,IF(R14=1,7,IF(S14=1,8,0)))))))) -> 2 | U14: =A14 -> 12 | V14: =_xlfn.CONCAT(F14," (",G14,"–",H14,")") -> Eliza (1810–1861) | W14: =_xlfn.CONCAT(F14," (#",A14,")") -> Eliza (#12) | X14: =_xlfn.CONCAT(F14," (",G14,"–",H14,": #",A14,")") -> Eliza (1810–1861: #12) | Y14: =_xlfn.CONCAT(B14," ",IF(C14="",E14,_xlfn.CONCAT(C14," ",IF(D14="",E14,_xlfn.CONCAT(D14," ",E14))))) -> Eliza LOYD | Z14: =VLOOKUP(L14,$U$2:$X$230,Z$1,FALSE) -> William (1770–1828: #4) | AA14: =_xlfn.CONCAT(AN14," ",AO14," ",AP14," ",AQ14," ",AR14," ",AS14," ",AT14," ",AU14) -> William (1770–1828: #4) William (1729–1800: #1) | AB14: =VLOOKUP(U14,'Siblings of those BORN Loyd'!$A$2:$G$230,7,FALSE) -> 6 – William (1809–1879: #10) Thomas (1812–1857: #14) Maria (1814–1900: #16) Edward (1815–1815: #17) John (1817–1818: #20) Lewis (1819–1841: #21) | AC14: =IF(ISNA(IF(K14="Boy",VLOOKUP(A14,'Siblings of those BORN Loyd'!$AP$3:$AQ$70,2,FALSE),VLOOKUP(A14,'Children of Female Loyds'!$AR$5:$AT$60,3,FALSE))),AM14,IF(K14="Boy",VLOOKUP(A14,'Siblings of those BORN Loyd'!$AP$3:$AQ$70,2,FALSE),VLOOKUP(A14,'Children of Female Loyds'!$AR$5:$AT$60,3,FALSE))) -> d.s.p | AD14: =IF(AE14="d.s.p",_xlfn.CONCAT(AE14,"."),IF(AG14=0,"-",_xlfn.CONCAT(AG14," - ",AE14," ",AF14))) -> d.s.p. | AE14: =IF(ISNA(IF(K14="Boy",VLOOKUP(A14,'Grandchildren of Male Loyds'!$AQ$3:$AS$51,3,FALSE),VLOOKUP(A14,'Grandchildren of Female Loyds'!$AX$5:$AZ$63,3,FALSE))),AM14,IF(K14="Boy",VLOOKUP(A14,'Grandchildren of Male Loyds'!$AQ$3:$AS$51,3,FALSE),VLOOKUP(A14,'Grandchildren of Female Loyds'!$AX$5:$AZ$63,3,FALSE))) -> d.s.p | AF14: =IF(ISNA(VLOOKUP(A14,'Grandchildren Loyd Daughters'!$BD$5:$BF$50,4,FALSE)),"",VLOOKUP(A14,'Grandchildren Loyd Daughters'!$BD$5:$BF$50,3,FALSE)) | AG14: =IF(ISNA(VLOOKUP(A14,'Grandchildren of Male Loyds'!$AQ$3:$AR$60,2,FALSE)),0,VLOOKUP(A14,'Grandchildren of Male Loyds'!$AQ$3:$AR$60,2,FALSE))+IF(ISNA(VLOOKUP(A14,'Grandchildren of Female Loyds'!$AX$5:$AY$50,2,FALSE)),0,VLOOKUP(A14,'Grandchildren of Female Loyds'!$AX$5:$AY$50,2,FALSE))+IF(ISNA(VLOOKUP(A14,'Grandchildren Loyd Daughters'!$BD$5:$BE$50,2,FALSE)),0,VLOOKUP(A14,'Grandchildren Loyd Daughters'!$BD$5:$BE$50,2,FALSE)) -> 0 | AH14: =VLOOKUP($U14,'Loyd List 1-190 - Edit'!$P$3:$AJ$220,21,FALSE) -> Martha KIRKMAN (b. 17 Nov 1775, d. 4 Feb 1857) | AI14: =VLOOKUP(A14,'Updated Bios & Spouse Details'!$A$1:$J$200,7,FALSE) -> Unmarried | AJ14: =IF(VLOOKUP($A14,'Loyd List 1-190 - Edit'!$C$1:$AQ$220,'Book Details - NO EDIT'!AJ$1,FALSE)="","",(VLOOKUP($A14,'Loyd List 1-190 - Edit'!$C$1:$AQ$220,'Book Details - NO EDIT'!AJ$1,FALSE))) -> - | AK14: =VLOOKUP(A14,'Updated Bios & Spouse Details'!$A$1:$J$200,8,FALSE) -> - | AL14: =VLOOKUP(A14,'Updated Bios & Spouse Details'!$A$1:$J$200,5,FALSE) -> Eliza was the elder daughter of William (1770–1828: #4) of 7 Bread Street, Cheapside, London EC2. Born 30 Nov 1810. Died, unmarried, 3 Oct 1861 at 30 Leinster Square, London W2. DSP | AM14: =IF(AND(LEN(H14)>0,ISNA(IF(K14="Boy",VLOOKUP(A14,'Siblings of those BORN Loyd'!$AP$3:$AQ$70,2,FALSE),VLOOKUP(A14,'Children of Female Loyds'!$AR$5:$AS$60,2,FALSE)))),"d.s.p","") -> d.s.p | AN14: =(IF(OR(L14=0,LEN(L14)=0),"",_xlfn.CONCAT(VLOOKUP(L14,$U$3:$X$230,4,FALSE)))) -> William (1770–1828: #4) | AO14: =(IF(OR(M14=0,LEN(M14)=0),"",_xlfn.CONCAT(VLOOKUP(M14,$U$3:$X$230,4,FALSE)))) -> William (1729–1800: #1) | AP14: =(IF(OR(N14=0,LEN(N14)=0),"",_xlfn.CONCAT(VLOOKUP(N14,$U$3:$X$230,4,FALSE)))) | AQ14: =(IF(OR(O14=0,LEN(O14)=0),"",_xlfn.CONCAT(VLOOKUP(O14,$U$3:$X$230,4,FALSE)))) | AR14: =(IF(OR(P14=0,LEN(P14)=0),"",_xlfn.CONCAT(VLOOKUP(P14,$U$3:$X$230,4,FALSE)))) | AS14: =(IF(OR(Q14=0,LEN(Q14)=0),"",_xlfn.CONCAT(VLOOKUP(Q14,$U$3:$X$230,4,FALSE)))) | AT14: =(IF(OR(R14=0,LEN(R14)=0),"",_xlfn.CONCAT(VLOOKUP(R14,$U$3:$X$230,4,FALSE)))) | AU14: =(IF(OR(S14=0,LEN(S14)=0),"",_xlfn.CONCAT(VLOOKUP(S14,$U$3:$X$230,4,FALSE)))) | AW14: =VLOOKUP(A14,'Updated Bios & Spouse Details'!$A$1:$J$193,6,FALSE) -> England | AX14: =VLOOKUP($A14,'Loyd List 1-190 - Edit'!$P$2:$AQ$220,AX$1,FALSE) -> 12 | AY14: =IF(ISNA(VLOOKUP(A14,'Data check lookup table'!$G$2:$V$73,13,FALSE))," - ",VLOOKUP(A14,'Data check lookup table'!$G$2:$V$73,13,FALSE)) -> - | AZ14: =TEXT(J14,"dd/mm/yyyy") -> 03/10/1861 | BA14: =(IF(OR(Q14=0,LEN(Q14)=0),"",_xlfn.CONCAT(", ",VLOOKUP(Q14,$U$3:$X$230,4,FALSE)))) | BB14: =(IF(OR(R14=0,LEN(R14)=0),"",_xlfn.CONCAT("; ",VLOOKUP(R14,$U$3:$X$230,4,FALSE)))) | BI14: 03/10/1861
A15: ='Loyd List 1-190 - Edit'!C15 -> 13 | B15: =VLOOKUP($A15,'Loyd List 1-190 - Edit'!$C$1:$AQ$220,'Book Details - NO EDIT'!B$1,FALSE) -> Lewis | C15: =IF(VLOOKUP($A15,'Loyd List 1-190 - Edit'!$C$1:$AQ$220,'Book Details - NO EDIT'!C$1,FALSE)="","",VLOOKUP($A15,'Loyd List 1-190 - Edit'!$C$1:$AQ$220,'Book Details - NO EDIT'!C$1,FALSE)) | D15: =IF(VLOOKUP($A15,'Loyd List 1-190 - Edit'!$C$1:$AQ$220,'Book Details - NO EDIT'!D$1,FALSE)="","",VLOOKUP($A15,'Loyd List 1-190 - Edit'!$C$1:$AQ$220,'Book Details - NO EDIT'!D$1,FALSE)) | E15: =IF(VLOOKUP($A15,'Loyd List 1-190 - Edit'!$C$1:$AQ$220,'Book Details - NO EDIT'!E$1,FALSE)="","",VLOOKUP($A15,'Loyd List 1-190 - Edit'!$C$1:$AQ$220,'Book Details - NO EDIT'!E$1,FALSE)) -> LOYD | F15: =IF(VLOOKUP($A15,'Loyd List 1-190 - Edit'!$C$1:$AQ$220,'Book Details - NO EDIT'!F$1,FALSE)="",B15,VLOOKUP($A15,'Loyd List 1-190 - Edit'!$C$1:$AQ$220,'Book Details - NO EDIT'!F$1,FALSE)) -> Lewis | G15: =IF(VLOOKUP($A15,'Loyd List 1-190 - Edit'!$C$1:$AQ$220,'Book Details - NO EDIT'!G$1,FALSE)="","",VALUE(VLOOKUP($A15,'Loyd List 1-190 - Edit'!$C$1:$AQ$220,'Book Details - NO EDIT'!G$1,FALSE))) -> 1811 | H15: =IF(VLOOKUP($A15,'Loyd List 1-190 - Edit'!$C$1:$AQ$220,'Book Details - NO EDIT'!H$1,FALSE)="","",VALUE(VLOOKUP($A15,'Loyd List 1-190 - Edit'!$C$1:$AQ$220,'Book Details - NO EDIT'!H$1,FALSE))) -> 1891 | I15: =IF(VLOOKUP($A15,'Loyd List 1-190 - Edit'!$C$1:$AQ$220,'Book Details - NO EDIT'!I$1,FALSE)="","",(VLOOKUP($A15,'Loyd List 1-190 - Edit'!$C$1:$AQ$220,'Book Details - NO EDIT'!I$1,FALSE))) -> 10/08/1811 | J15: =IF(VLOOKUP($A15,'Loyd List 1-190 - Edit'!$C$1:$AQ$220,'Book Details - NO EDIT'!J$1,FALSE)="","",(VLOOKUP($A15,'Loyd List 1-190 - Edit'!$C$1:$AQ$220,'Book Details - NO EDIT'!J$1,FALSE))) -> 19/07/1891 | K15: =VLOOKUP($A15,'Loyd List 1-190 - Edit'!$C$1:$AQ$220,'Book Details - NO EDIT'!K$1,FALSE) -> Boy | L15: =VLOOKUP($A15,'Loyd List 1-190 - Edit'!$C$1:$AQ$220,'Book Details - NO EDIT'!L$1,FALSE) -> 8 | M15: =IF(ISNA(VLOOKUP(L15,$A$3:$L$220,M$1,FALSE)),"",(VLOOKUP(L15,$A$3:$L$220,M$1,FALSE))) -> 1 | N15: =IF(ISNA(VLOOKUP(M15,$A$3:$L$220,N$1,FALSE)),"",(VLOOKUP(M15,$A$3:$L$220,N$1,FALSE))) -> 0 | O15: =IF(ISNA(VLOOKUP(N15,$A$3:$L$220,O$1,FALSE)),"",(VLOOKUP(N15,$A$3:$L$220,O$1,FALSE))) | P15: =IF(ISNA(VLOOKUP(O15,$A$3:$L$220,P$1,FALSE)),"",(VLOOKUP(O15,$A$3:$L$220,P$1,FALSE))) | Q15: =IF(ISNA(VLOOKUP(P15,$A$3:$L$220,Q$1,FALSE)),"",(VLOOKUP(P15,$A$3:$L$220,Q$1,FALSE))) | R15: =IF(ISNA(VLOOKUP(Q15,$A$3:$L$220,R$1,FALSE)),"",(VLOOKUP(Q15,$A$3:$L$220,R$1,FALSE))) | S15: =IF(ISNA(VLOOKUP(R15,$A$3:$L$220,S$1,FALSE)),"",(VLOOKUP(R15,$A$3:$L$220,S$1,FALSE))) | T15: =IF(L15=1,1,IF(M15=1,2,IF(N15=1,3,IF(O15=1,4,IF(P15=1,5,IF(Q15=1,6,IF(R15=1,7,IF(S15=1,8,0)))))))) -> 2 | U15: =A15 -> 13 | V15: =_xlfn.CONCAT(F15," (",G15,"–",H15,")") -> Lewis (1811–1891) | W15: =_xlfn.CONCAT(F15," (#",A15,")") -> Lewis (#13) | X15: =_xlfn.CONCAT(F15," (",G15,"–",H15,": #",A15,")") -> Lewis (1811–1891: #13) | Y15: =_xlfn.CONCAT(B15," ",IF(C15="",E15,_xlfn.CONCAT(C15," ",IF(D15="",E15,_xlfn.CONCAT(D15," ",E15))))) -> Lewis LOYD | Z15: =VLOOKUP(L15,$U$2:$X$230,Z$1,FALSE) -> Edward (1780–1863: #8) | AA15: =_xlfn.CONCAT(AN15," ",AO15," ",AP15," ",AQ15," ",AR15," ",AS15," ",AT15," ",AU15) -> Edward (1780–1863: #8) William (1729–1800: #1) | AB15: =VLOOKUP(U15,'Siblings of those BORN Loyd'!$A$2:$G$230,7,FALSE) -> 7 – Sarah (1810–1858: #11) Annie (1813–1834: #15) Kate (1815–1905: #18) Hannah (1817–1907: #19) Edward (1820–1890: #22) William (1821–1885: #23) Fanny (1824–1856: #24) | AC15: =IF(ISNA(IF(K15="Boy",VLOOKUP(A15,'Siblings of those BORN Loyd'!$AP$3:$AQ$70,2,FALSE),VLOOKUP(A15,'Children of Female Loyds'!$AR$5:$AT$60,3,FALSE))),AM15,IF(K15="Boy",VLOOKUP(A15,'Siblings of those BORN Loyd'!$AP$3:$AQ$70,2,FALSE),VLOOKUP(A15,'Children of Female Loyds'!$AR$5:$AT$60,3,FALSE))) -> d.s.p | AD15: =IF(AE15="d.s.p",_xlfn.CONCAT(AE15,"."),IF(AG15=0,"-",_xlfn.CONCAT(AG15," - ",AE15," ",AF15))) -> d.s.p. | AE15: =IF(ISNA(IF(K15="Boy",VLOOKUP(A15,'Grandchildren of Male Loyds'!$AQ$3:$AS$51,3,FALSE),VLOOKUP(A15,'Grandchildren of Female Loyds'!$AX$5:$AZ$63,3,FALSE))),AM15,IF(K15="Boy",VLOOKUP(A15,'Grandchildren of Male Loyds'!$AQ$3:$AS$51,3,FALSE),VLOOKUP(A15,'Grandchildren of Female Loyds'!$AX$5:$AZ$63,3,FALSE))) -> d.s.p | AF15: =IF(ISNA(VLOOKUP(A15,'Grandchildren Loyd Daughters'!$BD$5:$BF$50,4,FALSE)),"",VLOOKUP(A15,'Grandchildren Loyd Daughters'!$BD$5:$BF$50,3,FALSE)) | AG15: =IF(ISNA(VLOOKUP(A15,'Grandchildren of Male Loyds'!$AQ$3:$AR$60,2,FALSE)),0,VLOOKUP(A15,'Grandchildren of Male Loyds'!$AQ$3:$AR$60,2,FALSE))+IF(ISNA(VLOOKUP(A15,'Grandchildren of Female Loyds'!$AX$5:$AY$50,2,FALSE)),0,VLOOKUP(A15,'Grandchildren of Female Loyds'!$AX$5:$AY$50,2,FALSE))+IF(ISNA(VLOOKUP(A15,'Grandchildren Loyd Daughters'!$BD$5:$BE$50,2,FALSE)),0,VLOOKUP(A15,'Grandchildren Loyd Daughters'!$BD$5:$BE$50,2,FALSE)) -> 0 | AH15: =VLOOKUP($U15,'Loyd List 1-190 - Edit'!$P$3:$AJ$220,21,FALSE) -> Sarah TAYLOR (b.5 Jul 1785, d. 19 Jan 1863) | AI15: =VLOOKUP(A15,'Updated Bios & Spouse Details'!$A$1:$J$200,7,FALSE) -> Frances Harriet IRBY (b. 25 Feb 1817, d. 27 Jan 1902) | AJ15: =IF(VLOOKUP($A15,'Loyd List 1-190 - Edit'!$C$1:$AQ$220,'Book Details - NO EDIT'!AJ$1,FALSE)="","",(VLOOKUP($A15,'Loyd List 1-190 - Edit'!$C$1:$AQ$220,'Book Details - NO EDIT'!AJ$1,FALSE))) -> 19/06/1845 | AK15: =VLOOKUP(A15,'Updated Bios & Spouse Details'!$A$1:$J$200,8,FALSE) -> Married at St George’s, Hanover Square, London. Frances eldest daughter of Rear Admiral The Hon Frederick Paul IRBY CB of Boyland Hall, Norfolk. Frances's mother, Frances WRIGHT, was Lady OVERSTONE’S sister. | AL15: =VLOOKUP(A15,'Updated Bios & Spouse Details'!$A$1:$J$200,5,FALSE) -> Lewis lived at 20 Hyde Park Gardens, London SW7 and at Monk’s Orchard, West Wickham, Kent. Eldest son of Edward (1780–1863: #8) of Coombe House, Coombe Lane, Croydon, Surrey. Born 10 Aug 1811 and baptised 4 Sept 1811 at St Ann’s, Manchester. Educated: Eton and Trinity College, Cambridge. Career: Banker in the London house of Jones Loyd & Co. JP Surrey. High Sheriff 1863. Commissioner of Lieutenancy for the City of London. Founded the church of St John the Evangelist, Waterloo Road, Cheetham, Manchester at a cost of £20,000 and endowed benefice with income of £200 per annum. Died 19 Jul 1891, buried at Addington, Nr. Croydon, Surrey. DSP Will dated 1885. Estate £598,798. Roddy SALE (#97d), in 2022, has IRBY family tree (from Lewis). Frank Sale (#97ea) visited the church, which transferred to the New Testament, but has a revisionary clause that if the church should close then the property reverts to the Loyd estate. Roddy also has portrait of Lewis as a young man. | AM15: =IF(AND(LEN(H15)>0,ISNA(IF(K15="Boy",VLOOKUP(A15,'Siblings of those BORN Loyd'!$AP$3:$AQ$70,2,FALSE),VLOOKUP(A15,'Children of Female Loyds'!$AR$5:$AS$60,2,FALSE)))),"d.s.p","") -> d.s.p | AN15: =(IF(OR(L15=0,LEN(L15)=0),"",_xlfn.CONCAT(VLOOKUP(L15,$U$3:$X$230,4,FALSE)))) -> Edward (1780–1863: #8) | AO15: =(IF(OR(M15=0,LEN(M15)=0),"",_xlfn.CONCAT(VLOOKUP(M15,$U$3:$X$230,4,FALSE)))) -> William (1729–1800: #1) | AP15: =(IF(OR(N15=0,LEN(N15)=0),"",_xlfn.CONCAT(VLOOKUP(N15,$U$3:$X$230,4,FALSE)))) | AQ15: =(IF(OR(O15=0,LEN(O15)=0),"",_xlfn.CONCAT(VLOOKUP(O15,$U$3:$X$230,4,FALSE)))) | AR15: =(IF(OR(P15=0,LEN(P15)=0),"",_xlfn.CONCAT(VLOOKUP(P15,$U$3:$X$230,4,FALSE)))) | AS15: =(IF(OR(Q15=0,LEN(Q15)=0),"",_xlfn.CONCAT(VLOOKUP(Q15,$U$3:$X$230,4,FALSE)))) | AT15: =(IF(OR(R15=0,LEN(R15)=0),"",_xlfn.CONCAT(VLOOKUP(R15,$U$3:$X$230,4,FALSE)))) | AU15: =(IF(OR(S15=0,LEN(S15)=0),"",_xlfn.CONCAT(VLOOKUP(S15,$U$3:$X$230,4,FALSE)))) | AW15: =VLOOKUP(A15,'Updated Bios & Spouse Details'!$A$1:$J$193,6,FALSE) -> England | AX15: =VLOOKUP($A15,'Loyd List 1-190 - Edit'!$P$2:$AQ$220,AX$1,FALSE) -> 13 | AY15: =IF(ISNA(VLOOKUP(A15,'Data check lookup table'!$G$2:$V$73,13,FALSE))," - ",VLOOKUP(A15,'Data check lookup table'!$G$2:$V$73,13,FALSE)) -> - | AZ15: =TEXT(J15,"dd/mm/yyyy") -> 19/07/1891 | BA15: =(IF(OR(Q15=0,LEN(Q15)=0),"",_xlfn.CONCAT(", ",VLOOKUP(Q15,$U$3:$X$230,4,FALSE)))) | BB15: =(IF(OR(R15=0,LEN(R15)=0),"",_xlfn.CONCAT("; ",VLOOKUP(R15,$U$3:$X$230,4,FALSE)))) | BI15: 19/07/1891
... A99: ='Loyd List 1-190 - Edit'!C99 -> 97 | B99: =VLOOKUP($A99,'Loyd List 1-190 - Edit'!$C$1:$AQ$220,'Book Details - NO EDIT'!B$1,FALSE) -> Audrey | C99: =IF(VLOOKUP($A99,'Loyd List 1-190 - Edit'!$C$1:$AQ$220,'Book Details - NO EDIT'!C$1,FALSE)="","",VLOOKUP($A99,'Loyd List 1-190 - Edit'!$C$1:$AQ$220,'Book Details - NO EDIT'!C$1,FALSE)) -> Janet | D99: =IF(VLOOKUP($A99,'Loyd List 1-190 - Edit'!$C$1:$AQ$220,'Book Details - NO EDIT'!D$1,FALSE)="","",VLOOKUP($A99,'Loyd List 1-190 - Edit'!$C$1:$AQ$220,'Book Details - NO EDIT'!D$1,FALSE)) -> Isabel | E99: =IF(VLOOKUP($A99,'Loyd List 1-190 - Edit'!$C$1:$AQ$220,'Book Details - NO EDIT'!E$1,FALSE)="","",VLOOKUP($A99,'Loyd List 1-190 - Edit'!$C$1:$AQ$220,'Book Details - NO EDIT'!E$1,FALSE)) -> LOYD | F99: =IF(VLOOKUP($A99,'Loyd List 1-190 - Edit'!$C$1:$AQ$220,'Book Details - NO EDIT'!F$1,FALSE)="",B99,VLOOKUP($A99,'Loyd List 1-190 - Edit'!$C$1:$AQ$220,'Book Details - NO EDIT'!F$1,FALSE)) -> Audrey | G99: =IF(VLOOKUP($A99,'Loyd List 1-190 - Edit'!$C$1:$AQ$220,'Book Details - NO EDIT'!G$1,FALSE)="","",VALUE(VLOOKUP($A99,'Loyd List 1-190 - Edit'!$C$1:$AQ$220,'Book Details - NO EDIT'!G$1,FALSE))) -> 1922 | H99: =IF(VLOOKUP($A99,'Loyd List 1-190 - Edit'!$C$1:$AQ$220,'Book Details - NO EDIT'!H$1,FALSE)="","",VALUE(VLOOKUP($A99,'Loyd List 1-190 - Edit'!$C$1:$AQ$220,'Book Details - NO EDIT'!H$1,FALSE))) -> 2005 | I99: =IF(VLOOKUP($A99,'Loyd List 1-190 - Edit'!$C$1:$AQ$220,'Book Details - NO EDIT'!I$1,FALSE)="","",(VLOOKUP($A99,'Loyd List 1-190 - Edit'!$C$1:$AQ$220,'Book Details - NO EDIT'!I$1,FALSE))) -> 8184 | J99: =IF(VLOOKUP($A99,'Loyd List 1-190 - Edit'!$C$1:$AQ$220,'Book Details - NO EDIT'!J$1,FALSE)="","",(VLOOKUP($A99,'Loyd List 1-190 - Edit'!$C$1:$AQ$220,'Book Details - NO EDIT'!J$1,FALSE))) -> 04/10/2005 | K99: =VLOOKUP($A99,'Loyd List 1-190 - Edit'!$C$1:$AQ$220,'Book Details - NO EDIT'!K$1,FALSE) -> Girl | L99: =VLOOKUP($A99,'Loyd List 1-190 - Edit'!$C$1:$AQ$220,'Book Details - NO EDIT'!L$1,FALSE) -> 53 | M99: =IF(ISNA(VLOOKUP(L99,$A$3:$L$220,M$1,FALSE)),"",(VLOOKUP(L99,$A$3:$L$220,M$1,FALSE))) -> 41 | N99: =IF(ISNA(VLOOKUP(M99,$A$3:$L$220,N$1,FALSE)),"",(VLOOKUP(M99,$A$3:$L$220,N$1,FALSE))) -> 22 | O99: =IF(ISNA(VLOOKUP(N99,$A$3:$L$220,O$1,FALSE)),"",(VLOOKUP(N99,$A$3:$L$220,O$1,FALSE))) -> 8 | P99: =IF(ISNA(VLOOKUP(O99,$A$3:$L$220,P$1,FALSE)),"",(VLOOKUP(O99,$A$3:$L$220,P$1,FALSE))) -> 1 | Q99: =IF(ISNA(VLOOKUP(P99,$A$3:$L$220,Q$1,FALSE)),"",(VLOOKUP(P99,$A$3:$L$220,Q$1,FALSE))) -> 0 | R99: =IF(ISNA(VLOOKUP(Q99,$A$3:$L$220,R$1,FALSE)),"",(VLOOKUP(Q99,$A$3:$L$220,R$1,FALSE))) | S99: =IF(ISNA(VLOOKUP(R99,$A$3:$L$220,S$1,FALSE)),"",(VLOOKUP(R99,$A$3:$L$220,S$1,FALSE))) | T99: =IF(L99=1,1,IF(M99=1,2,IF(N99=1,3,IF(O99=1,4,IF(P99=1,5,IF(Q99=1,6,IF(R99=1,7,IF(S99=1,8,0)))))))) -> 5 | U99: =A99 -> 97 | V99: =_xlfn.CONCAT(F99," (",G99,"–",H99,")") -> Audrey (1922–2005) | W99: =_xlfn.CONCAT(F99," (#",A99,")") -> Audrey (#97) | X99: =_xlfn.CONCAT(F99," (",G99,"–",H99,": #",A99,")") -> Audrey (1922–2005: #97) | Y99: =_xlfn.CONCAT(B99," ",IF(C99="",E99,_xlfn.CONCAT(C99," ",IF(D99="",E99,_xlfn.CONCAT(D99," ",E99))))) -> Audrey Janet Isabel LOYD | Z99: =VLOOKUP(L99,$U$2:$X$230,Z$1,FALSE) -> Edward (1881–1962: #53) | AA99: =_xlfn.CONCAT(AN99," ",AO99," ",AP99," ",AQ99," ",AR99," ",AS99," ",AT99," ",AU99) -> Edward (1881–1962: #53) Frederic (1856–1936: #41) Edward (1820–1890: #22) Edward (1780–1863: #8) William (1729–1800: #1) | AB99: =VLOOKUP(U99,'Siblings of those BORN Loyd'!$A$2:$G$230,7,FALSE) -> 0 – Only chlid | AC99: =IF(ISNA(IF(K99="Boy",VLOOKUP(A99,'Siblings of those BORN Loyd'!$AP$3:$AQ$70,2,FALSE),VLOOKUP(A99,'Children of Female Loyds'!$AR$5:$AT$60,3,FALSE))),AM99,IF(K99="Boy",VLOOKUP(A99,'Siblings of those BORN Loyd'!$AP$3:$AQ$70,2,FALSE),VLOOKUP(A99,'Children of Female Loyds'!$AR$5:$AT$60,3,FALSE))) -> 5 - Julian SALE (1951 - : #97a) Iona SALE (1954 - : #97b) Charles SALE (1956 - 1957: #97c) Roddy SALE (1959 - : #97d) Edward SALE (1963 - : #97e) | AD99: =IF(AE99="d.s.p",_xlfn.CONCAT(AE99,"."),IF(AG99=0,"-",_xlfn.CONCAT(AG99," - ",AE99," ",AF99))) -> 5 - Alexander SALE (1991 -: #97aa) Oliver SALE (1995 -: #97ab) Frank SALE (1995 -: #97ea) Connie SALE (1997 -: #97eb) Grace SALE (2002 -0: #97ec) | AE99: =IF(ISNA(IF(K99="Boy",VLOOKUP(A99,'Grandchildren of Male Loyds'!$AQ$3:$AS$51,3,FALSE),VLOOKUP(A99,'Grandchildren of Female Loyds'!$AX$5:$AZ$63,3,FALSE))),AM99,IF(K99="Boy",VLOOKUP(A99,'Grandchildren of Male Loyds'!$AQ$3:$AS$51,3,FALSE),VLOOKUP(A99,'Grandchildren of Female Loyds'!$AX$5:$AZ$63,3,FALSE))) -> Alexander SALE (1991 -: #97aa) Oliver SALE (1995 -: #97ab) Frank SALE (1995 -: #97ea) Connie SALE (1997 -: #97eb) Grace SALE (2002 -0: #97ec) | AF99: =IF(ISNA(VLOOKUP(A99,'Grandchildren Loyd Daughters'!$BD$5:$BF$50,4,FALSE)),"",VLOOKUP(A99,'Grandchildren Loyd Daughters'!$BD$5:$BF$50,3,FALSE)) | AG99: =IF(ISNA(VLOOKUP(A99,'Grandchildren of Male Loyds'!$AQ$3:$AR$60,2,FALSE)),0,VLOOKUP(A99,'Grandchildren of Male Loyds'!$AQ$3:$AR$60,2,FALSE))+IF(ISNA(VLOOKUP(A99,'Grandchildren of Female Loyds'!$AX$5:$AY$50,2,FALSE)),0,VLOOKUP(A99,'Grandchildren of Female Loyds'!$AX$5:$AY$50,2,FALSE))+IF(ISNA(VLOOKUP(A99,'Grandchildren Loyd Daughters'!$BD$5:$BE$50,2,FALSE)),0,VLOOKUP(A99,'Grandchildren Loyd Daughters'!$BD$5:$BE$50,2,FALSE)) -> 5 | AH99: =VLOOKUP($U99,'Loyd List 1-190 - Edit'!$P$3:$AJ$220,21,FALSE) -> Kathleen Elizabeth Lilian DONOVAN (b. 21 Mar 1896, d. 7 Dec 1983) | AI99: =VLOOKUP(A99,'Updated Bios & Spouse Details'!$A$1:$J$200,7,FALSE) -> Robert Edward Walker SALE (b. 26 Nov 1913, d. 11 Aug 1983) | AJ99: =IF(VLOOKUP($A99,'Loyd List 1-190 - Edit'!$C$1:$AQ$220,'Book Details - NO EDIT'!AJ$1,FALSE)="","",(VLOOKUP($A99,'Loyd List 1-190 - Edit'!$C$1:$AQ$220,'Book Details - NO EDIT'!AJ$1,FALSE))) -> 18753 | AK99: =VLOOKUP(A99,'Updated Bios & Spouse Details'!$A$1:$J$200,8,FALSE) -> Robert, baptised in Bombay by the Rev, later the Rt Rev, Philip (1884 - 1952: #58) Bishop of Nasik and Bishop of St Albans, MC, Lieut Colonel, Welsh Guards, son of the late Edward Little SALE of Brownshill Court, Painswick, Gloucestershire. Late Collector of Bombay and of Belgaum, Indian Civil Service. | AL99: =VLOOKUP(A99,'Updated Bios & Spouse Details'!$A$1:$J$200,5,FALSE) -> Audrey lived at Dowdeswell Home Farm, Andoversford, Gloucestershire and was the only child of Edward (1881–1962: #53). Born 28 May 1922. Had safe keeping of old Welsh Bible with entries about LLOYD family in Carmarthenshire in 18th Century and other old family papers, and the blunderbuss belonging to Edward (1780–1863: #8) for use by his coachman if attacked on the turnpikes. Died 4 Oct 2005. Issue: 1 daughter, 3 sons | AM99: =IF(AND(LEN(H99)>0,ISNA(IF(K99="Boy",VLOOKUP(A99,'Siblings of those BORN Loyd'!$AP$3:$AQ$70,2,FALSE),VLOOKUP(A99,'Children of Female Loyds'!$AR$5:$AS$60,2,FALSE)))),"d.s.p","") | AN99: =(IF(OR(L99=0,LEN(L99)=0),"",_xlfn.CONCAT(VLOOKUP(L99,$U$3:$X$230,4,FALSE)))) -> Edward (1881–1962: #53) | AO99: =(IF(OR(M99=0,LEN(M99)=0),"",_xlfn.CONCAT(VLOOKUP(M99,$U$3:$X$230,4,FALSE)))) -> Frederic (1856–1936: #41) | AP99: =(IF(OR(N99=0,LEN(N99)=0),"",_xlfn.CONCAT(VLOOKUP(N99,$U$3:$X$230,4,FALSE)))) -> Edward (1820–1890: #22) | AQ99: =(IF(OR(O99=0,LEN(O99)=0),"",_xlfn.CONCAT(VLOOKUP(O99,$U$3:$X$230,4,FALSE)))) -> Edward (1780–1863: #8) | AR99: =(IF(OR(P99=0,LEN(P99)=0),"",_xlfn.CONCAT(VLOOKUP(P99,$U$3:$X$230,4,FALSE)))) -> William (1729–1800: #1) | AS99: =(IF(OR(Q99=0,LEN(Q99)=0),"",_xlfn.CONCAT(VLOOKUP(Q99,$U$3:$X$230,4,FALSE)))) | AT99: =(IF(OR(R99=0,LEN(R99)=0),"",_xlfn.CONCAT(VLOOKUP(R99,$U$3:$X$230,4,FALSE)))) | AU99: =(IF(OR(S99=0,LEN(S99)=0),"",_xlfn.CONCAT(VLOOKUP(S99,$U$3:$X$230,4,FALSE)))) | AW99: =VLOOKUP(A99,'Updated Bios & Spouse Details'!$A$1:$J$193,6,FALSE) -> England | AX99: =VLOOKUP($A99,'Loyd List 1-190 - Edit'!$P$2:$AQ$220,AX$1,FALSE) -> 97 | AY99: =IF(ISNA(VLOOKUP(A99,'Data check lookup table'!$G$2:$V$73,13,FALSE))," - ",VLOOKUP(A99,'Data check lookup table'!$G$2:$V$73,13,FALSE)) -> Deceased | AZ99: =TEXT(J99,"dd/mm/yyyy") -> 04/10/2005 | BA99: =(IF(OR(Q99=0,LEN(Q99)=0),"",_xlfn.CONCAT(", ",VLOOKUP(Q99,$U$3:$X$230,4,FALSE)))) | BB99: =(IF(OR(R99=0,LEN(R99)=0),"",_xlfn.CONCAT("; ",VLOOKUP(R99,$U$3:$X$230,4,FALSE)))) | BI99: 04/10/2005
A100: ='Loyd List 1-190 - Edit'!C100 -> 98 | B100: =VLOOKUP($A100,'Loyd List 1-190 - Edit'!$C$1:$AQ$220,'Book Details - NO EDIT'!B$1,FALSE) -> Peter | C100: =IF(VLOOKUP($A100,'Loyd List 1-190 - Edit'!$C$1:$AQ$220,'Book Details - NO EDIT'!C$1,FALSE)="","",VLOOKUP($A100,'Loyd List 1-190 - Edit'!$C$1:$AQ$220,'Book Details - NO EDIT'!C$1,FALSE)) -> Haig | D100: =IF(VLOOKUP($A100,'Loyd List 1-190 - Edit'!$C$1:$AQ$220,'Book Details - NO EDIT'!D$1,FALSE)="","",VLOOKUP($A100,'Loyd List 1-190 - Edit'!$C$1:$AQ$220,'Book Details - NO EDIT'!D$1,FALSE)) | E100: =IF(VLOOKUP($A100,'Loyd List 1-190 - Edit'!$C$1:$AQ$220,'Book Details - NO EDIT'!E$1,FALSE)="","",VLOOKUP($A100,'Loyd List 1-190 - Edit'!$C$1:$AQ$220,'Book Details - NO EDIT'!E$1,FALSE)) -> LOYD | F100: =IF(VLOOKUP($A100,'Loyd List 1-190 - Edit'!$C$1:$AQ$220,'Book Details - NO EDIT'!F$1,FALSE)="",B100,VLOOKUP($A100,'Loyd List 1-190 - Edit'!$C$1:$AQ$220,'Book Details - NO EDIT'!F$1,FALSE)) -> Peter | G100: =IF(VLOOKUP($A100,'Loyd List 1-190 - Edit'!$C$1:$AQ$220,'Book Details - NO EDIT'!G$1,FALSE)="","",VALUE(VLOOKUP($A100,'Loyd List 1-190 - Edit'!$C$1:$AQ$220,'Book Details - NO EDIT'!G$1,FALSE))) -> 1922 | H100: =IF(VLOOKUP($A100,'Loyd List 1-190 - Edit'!$C$1:$AQ$220,'Book Details - NO EDIT'!H$1,FALSE)="","",VALUE(VLOOKUP($A100,'Loyd List 1-190 - Edit'!$C$1:$AQ$220,'Book Details - NO EDIT'!H$1,FALSE))) -> 2022 | I100: =IF(VLOOKUP($A100,'Loyd List 1-190 - Edit'!$C$1:$AQ$220,'Book Details - NO EDIT'!I$1,FALSE)="","",(VLOOKUP($A100,'Loyd List 1-190 - Edit'!$C$1:$AQ$220,'Book Details - NO EDIT'!I$1,FALSE))) -> 8318 | J100: =IF(VLOOKUP($A100,'Loyd List 1-190 - Edit'!$C$1:$AQ$220,'Book Details - NO EDIT'!J$1,FALSE)="","",(VLOOKUP($A100,'Loyd List 1-190 - Edit'!$C$1:$AQ$220,'Book Details - NO EDIT'!J$1,FALSE))) -> 13/05/2022 | K100: =VLOOKUP($A100,'Loyd List 1-190 - Edit'!$C$1:$AQ$220,'Book Details - NO EDIT'!K$1,FALSE) -> Boy | L100: =VLOOKUP($A100,'Loyd List 1-190 - Edit'!$C$1:$AQ$220,'Book Details - NO EDIT'!L$1,FALSE) -> 77 | M100: =IF(ISNA(VLOOKUP(L100,$A$3:$L$220,M$1,FALSE)),"",(VLOOKUP(L100,$A$3:$L$220,M$1,FALSE))) -> 30 | N100: =IF(ISNA(VLOOKUP(M100,$A$3:$L$220,N$1,FALSE)),"",(VLOOKUP(M100,$A$3:$L$220,N$1,FALSE))) -> 14 | O100: =IF(ISNA(VLOOKUP(N100,$A$3:$L$220,O$1,FALSE)),"",(VLOOKUP(N100,$A$3:$L$220,O$1,FALSE))) -> 4 | P100: =IF(ISNA(VLOOKUP(O100,$A$3:$L$220,P$1,FALSE)),"",(VLOOKUP(O100,$A$3:$L$220,P$1,FALSE))) -> 1 | Q100: =IF(ISNA(VLOOKUP(P100,$A$3:$L$220,Q$1,FALSE)),"",(VLOOKUP(P100,$A$3:$L$220,Q$1,FALSE))) -> 0 | R100: =IF(ISNA(VLOOKUP(Q100,$A$3:$L$220,R$1,FALSE)),"",(VLOOKUP(Q100,$A$3:$L$220,R$1,FALSE))) | S100: =IF(ISNA(VLOOKUP(R100,$A$3:$L$220,S$1,FALSE)),"",(VLOOKUP(R100,$A$3:$L$220,S$1,FALSE))) | T100: =IF(L100=1,1,IF(M100=1,2,IF(N100=1,3,IF(O100=1,4,IF(P100=1,5,IF(Q100=1,6,IF(R100=1,7,IF(S100=1,8,0)))))))) -> 5 | U100: =A100 -> 98 | V100: =_xlfn.CONCAT(F100," (",G100,"–",H100,")") -> Peter (1922–2022) | W100: =_xlfn.CONCAT(F100," (#",A100,")") -> Peter (#98) | X100: =_xlfn.CONCAT(F100," (",G100,"–",H100,": #",A100,")") -> Peter (1922–2022: #98) | Y100: =_xlfn.CONCAT(B100," ",IF(C100="",E100,_xlfn.CONCAT(C100," ",IF(D100="",E100,_xlfn.CONCAT(D100," ",E100))))) -> Peter Haig LOYD | Z100: =VLOOKUP(L100,$U$2:$X$230,Z$1,FALSE) -> Wilfrid (1893–1971: #77) | AA100: =_xlfn.CONCAT(AN100," ",AO100," ",AP100," ",AQ100," ",AR100," ",AS100," ",AT100," ",AU100) -> Wilfrid (1893–1971: #77) Archie (1847–1922: #30) Thomas (1812–1857: #14) William (1770–1828: #4) William (1729–1800: #1) | AB100: =VLOOKUP(U100,'Siblings of those BORN Loyd'!$A$2:$G$230,7,FALSE) -> 3 – Geoffrey (1926–2018: #105) Denise (1928–: #106) Andrew (1934–1975: #111) | AC100: =IF(ISNA(IF(K100="Boy",VLOOKUP(A100,'Siblings of those BORN Loyd'!$AP$3:$AQ$70,2,FALSE),VLOOKUP(A100,'Children of Female Loyds'!$AR$5:$AT$60,3,FALSE))),AM100,IF(K100="Boy",VLOOKUP(A100,'Siblings of those BORN Loyd'!$AP$3:$AQ$70,2,FALSE),VLOOKUP(A100,'Children of Female Loyds'!$AR$5:$AT$60,3,FALSE))) -> 5 - Julie (1952–: #128); Penelope (1954–1954: #132); William (1955–: #134); Tony (1963–: #145); Sophie (1969–: #154) | AD100: =IF(AE100="d.s.p",_xlfn.CONCAT(AE100,"."),IF(AG100=0,"-",_xlfn.CONCAT(AG100," - ",AE100," ",AF100))) -> 5 - Chloe PEMBERTON (1991 - : #128a) Kate PEMBERTON (1993 - : #128b) Freddie NEWING (2006 - : #154a) Gus NEWING (2008 - : #154b) Albert NEWING (2015 - 2015: #154c) | AE100: =IF(ISNA(IF(K100="Boy",VLOOKUP(A100,'Grandchildren of Male Loyds'!$AQ$3:$AS$51,3,FALSE),VLOOKUP(A100,'Grandchildren of Female Loyds'!$AX$5:$AZ$63,3,FALSE))),AM100,IF(K100="Boy",VLOOKUP(A100,'Grandchildren of Male Loyds'!$AQ$3:$AS$51,3,FALSE),VLOOKUP(A100,'Grandchildren of Female Loyds'!$AX$5:$AZ$63,3,FALSE))) | AF100: =IF(ISNA(VLOOKUP(A100,'Grandchildren Loyd Daughters'!$BD$5:$BF$50,4,FALSE)),"",VLOOKUP(A100,'Grandchildren Loyd Daughters'!$BD$5:$BF$50,3,FALSE)) -> Chloe PEMBERTON (1991 - : #128a) Kate PEMBERTON (1993 - : #128b) Freddie NEWING (2006 - : #154a) Gus NEWING (2008 - : #154b) Albert NEWING (2015 - 2015: #154c) | AG100: =IF(ISNA(VLOOKUP(A100,'Grandchildren of Male Loyds'!$AQ$3:$AR$60,2,FALSE)),0,VLOOKUP(A100,'Grandchildren of Male Loyds'!$AQ$3:$AR$60,2,FALSE))+IF(ISNA(VLOOKUP(A100,'Grandchildren of Female Loyds'!$AX$5:$AY$50,2,FALSE)),0,VLOOKUP(A100,'Grandchildren of Female Loyds'!$AX$5:$AY$50,2,FALSE))+IF(ISNA(VLOOKUP(A100,'Grandchildren Loyd Daughters'!$BD$5:$BE$50,2,FALSE)),0,VLOOKUP(A100,'Grandchildren Loyd Daughters'!$BD$5:$BE$50,2,FALSE)) -> 5 | AH100: =VLOOKUP($U100,'Loyd List 1-190 - Edit'!$P$3:$AJ$220,21,FALSE) -> Emily Charlotte Eileen OAKELEY (b. 28 Jan 1896, d. 8 May 1978) | AI100: =VLOOKUP(A100,'Updated Bios & Spouse Details'!$A$1:$J$200,7,FALSE) -> (1) Suzanne DUNCAN (b. 25 Aug 1928, ). | AJ100: =IF(VLOOKUP($A100,'Loyd List 1-190 - Edit'!$C$1:$AQ$220,'Book Details - NO EDIT'!AJ$1,FALSE)="","",(VLOOKUP($A100,'Loyd List 1-190 - Edit'!$C$1:$AQ$220,'Book Details - NO EDIT'!AJ$1,FALSE))) -> 18361 | AK100: =VLOOKUP(A100,'Updated Bios & Spouse Details'!$A$1:$J$200,8,FALSE) -> (1) Married 8 Apr 1950 at Tewkesbury Abbey, Suzanne only child of Eric McLeod DUNCAN of The Croft, The Leigh, Nr. Cheltenham, Gloucestershire. (Issue 1 son & 2 daughters - divorced 1957). (2) Married 26 Aug 1961 at Chelsea Registry Office, Rosie elder daughter of Dr John Hay MOIR of Worplesdon, Surrey. Cremated 18 Mar 1997. (Issue 1 son & 1 daughter). (3) 10 Oct 1998 at Burgh House, Hampstead, London NW3, Rosemary, elder daughter of Flight Lieutenant David Moore CROOK (b. 24 Nov 1914, d. 18 Dec 1944 flying) DFC 1 Nov 1940 of Glenwood, Edgerton, Huddersfield, Yorkshire. David served in World War II in Battle of Britain in 609 Squadron. David Crook, author of "Spitfire Pilot", Faber and Faber 1942. | AL100: =VLOOKUP(A100,'Updated Bios & Spouse Details'!$A$1:$J$200,5,FALSE) -> Peter lived in North London and was the eldest son of Wilfrid (1893–1971: #77). Born 9 Oct 1922 at Frittenden, Kent. Baptised 9 Dec 1922 at St Michael’s, Chester Square. Educated Eton 1936-40. Served in World War II in Home Fleet in HMS Belfast, and on land in India and Burma. Captain, Royal Marines. Adjutant and Troop Commander, 42 Commando Royal Marines 1943-45. OC Royal Marines HMS Nigeria 1945-47. Retired from Royal Marines 1958. Imperial Chemical Industries, Plastics Division 1958-61. BTR Industries 1961-66. Industrial Society 1966-74. Director, British Institute of Management 1974-84. FMS 1966, FBIM 1974 (now FIMgt), FIIM 1979. Yachtmaster (Offshore) 1976. Loyd Family Archivist producing a Loyd book series: THE LOYD FAMILY, "Who's Who", first edition published in 1985; and then updated in 2000 with the second edition entitled, “THE LOYD FAMILY – A "Who's Who" in date of birth order from William LLOYD (1729-1800) to the present day.” Peter died 13 May 2022 in the Royal Free Hospital and his funeral service was held at Hampstead Parish Church, Hampstead, London on 27 May 2022. Issue: (1st wife) 1 son, 2 daughters. (2nd wife) 1 son, 1 daughter. | AM100: =IF(AND(LEN(H100)>0,ISNA(IF(K100="Boy",VLOOKUP(A100,'Siblings of those BORN Loyd'!$AP$3:$AQ$70,2,FALSE),VLOOKUP(A100,'Children of Female Loyds'!$AR$5:$AS$60,2,FALSE)))),"d.s.p","") | AN100: =(IF(OR(L100=0,LEN(L100)=0),"",_xlfn.CONCAT(VLOOKUP(L100,$U$3:$X$230,4,FALSE)))) -> Wilfrid (1893–1971: #77) | AO100: =(IF(OR(M100=0,LEN(M100)=0),"",_xlfn.CONCAT(VLOOKUP(M100,$U$3:$X$230,4,FALSE)))) -> Archie (1847–1922: #30) | AP100: =(IF(OR(N100=0,LEN(N100)=0),"",_xlfn.CONCAT(VLOOKUP(N100,$U$3:$X$230,4,FALSE)))) -> Thomas (1812–1857: #14) | AQ100: =(IF(OR(O100=0,LEN(O100)=0),"",_xlfn.CONCAT(VLOOKUP(O100,$U$3:$X$230,4,FALSE)))) -> William (1770–1828: #4) | AR100: =(IF(OR(P100=0,LEN(P100)=0),"",_xlfn.CONCAT(VLOOKUP(P100,$U$3:$X$230,4,FALSE)))) -> William (1729–1800: #1) | AS100: =(IF(OR(Q100=0,LEN(Q100)=0),"",_xlfn.CONCAT(VLOOKUP(Q100,$U$3:$X$230,4,FALSE)))) | AT100: =(IF(OR(R100=0,LEN(R100)=0),"",_xlfn.CONCAT(VLOOKUP(R100,$U$3:$X$230,4,FALSE)))) | AU100: =(IF(OR(S100=0,LEN(S100)=0),"",_xlfn.CONCAT(VLOOKUP(S100,$U$3:$X$230,4,FALSE)))) | AW100: =VLOOKUP(A100,'Updated Bios & Spouse Details'!$A$1:$J$193,6,FALSE) -> England, India and Burma | AX100: =VLOOKUP($A100,'Loyd List 1-190 - Edit'!$P$2:$AQ$220,AX$1,FALSE) -> 98 | AY100: =IF(ISNA(VLOOKUP(A100,'Data check lookup table'!$G$2:$V$73,13,FALSE))," - ",VLOOKUP(A100,'Data check lookup table'!$G$2:$V$73,13,FALSE)) -> rosemaryloyd@gmail.com | AZ100: =TEXT(J100,"dd/mm/yyyy") -> 13/05/2022 | BA100: =(IF(OR(Q100=0,LEN(Q100)=0),"",_xlfn.CONCAT(", ",VLOOKUP(Q100,$U$3:$X$230,4,FALSE)))) | BB100: =(IF(OR(R100=0,LEN(R100)=0),"",_xlfn.CONCAT("; ",VLOOKUP(R100,$U$3:$X$230,4,FALSE))))
A101: ='Loyd List 1-190 - Edit'!C101 -> 99 | B101: =VLOOKUP($A101,'Loyd List 1-190 - Edit'!$C$1:$AQ$220,'Book Details - NO EDIT'!B$1,FALSE) -> Peter | C101: =IF(VLOOKUP($A101,'Loyd List 1-190 - Edit'!$C$1:$AQ$220,'Book Details - NO EDIT'!C$1,FALSE)="","",VLOOKUP($A101,'Loyd List 1-190 - Edit'!$C$1:$AQ$220,'Book Details - NO EDIT'!C$1,FALSE)) -> Wyndham | D101: =IF(VLOOKUP($A101,'Loyd List 1-190 - Edit'!$C$1:$AQ$220,'Book Details - NO EDIT'!D$1,FALSE)="","",VLOOKUP($A101,'Loyd List 1-190 - Edit'!$C$1:$AQ$220,'Book Details - NO EDIT'!D$1,FALSE)) | E101: =IF(VLOOKUP($A101,'Loyd List 1-190 - Edit'!$C$1:$AQ$220,'Book Details - NO EDIT'!E$1,FALSE)="","",VLOOKUP($A101,'Loyd List 1-190 - Edit'!$C$1:$AQ$220,'Book Details - NO EDIT'!E$1,FALSE)) -> LOYD | F101: =IF(VLOOKUP($A101,'Loyd List 1-190 - Edit'!$C$1:$AQ$220,'Book Details - NO EDIT'!F$1,FALSE)="",B101,VLOOKUP($A101,'Loyd List 1-190 - Edit'!$C$1:$AQ$220,'Book Details - NO EDIT'!F$1,FALSE)) -> Peter | G101: =IF(VLOOKUP($A101,'Loyd List 1-190 - Edit'!$C$1:$AQ$220,'Book Details - NO EDIT'!G$1,FALSE)="","",VALUE(VLOOKUP($A101,'Loyd List 1-190 - Edit'!$C$1:$AQ$220,'Book Details - NO EDIT'!G$1,FALSE))) -> 1923 | H101: =IF(VLOOKUP($A101,'Loyd List 1-190 - Edit'!$C$1:$AQ$220,'Book Details - NO EDIT'!H$1,FALSE)="","",VALUE(VLOOKUP($A101,'Loyd List 1-190 - Edit'!$C$1:$AQ$220,'Book Details - NO EDIT'!H$1,FALSE))) -> 1974 | I101: =IF(VLOOKUP($A101,'Loyd List 1-190 - Edit'!$C$1:$AQ$220,'Book Details - NO EDIT'!I$1,FALSE)="","",(VLOOKUP($A101,'Loyd List 1-190 - Edit'!$C$1:$AQ$220,'Book Details - NO EDIT'!I$1,FALSE))) -> 8509 | J101: =IF(VLOOKUP($A101,'Loyd List 1-190 - Edit'!$C$1:$AQ$220,'Book Details - NO EDIT'!J$1,FALSE)="","",(VLOOKUP($A101,'Loyd List 1-190 - Edit'!$C$1:$AQ$220,'Book Details - NO EDIT'!J$1,FALSE))) -> 12/06/1974 | K101: =VLOOKUP($A101,'Loyd List 1-190 - Edit'!$C$1:$AQ$220,'Book Details - NO EDIT'!K$1,FALSE) -> Boy | L101: =VLOOKUP($A101,'Loyd List 1-190 - Edit'!$C$1:$AQ$220,'Book Details - NO EDIT'!L$1,FALSE) -> 66 | M101: =IF(ISNA(VLOOKUP(L101,$A$3:$L$220,M$1,FALSE)),"",(VLOOKUP(L101,$A$3:$L$220,M$1,FALSE))) -> 44 | N101: =IF(ISNA(VLOOKUP(M101,$A$3:$L$220,N$1,FALSE)),"",(VLOOKUP(M101,$A$3:$L$220,N$1,FALSE))) -> 23 | O101: =IF(ISNA(VLOOKUP(N101,$A$3:$L$220,O$1,FALSE)),"",(VLOOKUP(N101,$A$3:$L$220,O$1,FALSE))) -> 8 | P101: =IF(ISNA(VLOOKUP(O101,$A$3:$L$220,P$1,FALSE)),"",(VLOOKUP(O101,$A$3:$L$220,P$1,FALSE))) -> 1 | Q101: =IF(ISNA(VLOOKUP(P101,$A$3:$L$220,Q$1,FALSE)),"",(VLOOKUP(P101,$A$3:$L$220,Q$1,FALSE))) -> 0 | R101: =IF(ISNA(VLOOKUP(Q101,$A$3:$L$220,R$1,FALSE)),"",(VLOOKUP(Q101,$A$3:$L$220,R$1,FALSE))) | S101: =IF(ISNA(VLOOKUP(R101,$A$3:$L$220,S$1,FALSE)),"",(VLOOKUP(R101,$A$3:$L$220,S$1,FALSE))) | T101: =IF(L101=1,1,IF(M101=1,2,IF(N101=1,3,IF(O101=1,4,IF(P101=1,5,IF(Q101=1,6,IF(R101=1,7,IF(S101=1,8,0)))))))) -> 5 | U101: =A101 -> 99 | V101: =_xlfn.CONCAT(F101," (",G101,"–",H101,")") -> Peter (1923–1974) | W101: =_xlfn.CONCAT(F101," (#",A101,")") -> Peter (#99) | X101: =_xlfn.CONCAT(F101," (",G101,"–",H101,": #",A101,")") -> Peter (1923–1974: #99) | Y101: =_xlfn.CONCAT(B101," ",IF(C101="",E101,_xlfn.CONCAT(C101," ",IF(D101="",E101,_xlfn.CONCAT(D101," ",E101))))) -> Peter Wyndham LOYD | Z101: =VLOOKUP(L101,$U$2:$X$230,Z$1,FALSE) -> William (1889–1947: #66) | AA101: =_xlfn.CONCAT(AN101," ",AO101," ",AP101," ",AQ101," ",AR101," ",AS101," ",AT101," ",AU101) -> William (1889–1947: #66) Harry (1861–1938: #44) William (1821–1885: #23) Edward (1780–1863: #8) William (1729–1800: #1) | AB101: =VLOOKUP(U101,'Siblings of those BORN Loyd'!$A$2:$G$230,7,FALSE) -> 2 – Delia (1915–2007: #88) Edward (1921–1977: #96) | AC101: =IF(ISNA(IF(K101="Boy",VLOOKUP(A101,'Siblings of those BORN Loyd'!$AP$3:$AQ$70,2,FALSE),VLOOKUP(A101,'Children of Female Loyds'!$AR$5:$AT$60,3,FALSE))),AM101,IF(K101="Boy",VLOOKUP(A101,'Siblings of those BORN Loyd'!$AP$3:$AQ$70,2,FALSE),VLOOKUP(A101,'Children of Female Loyds'!$AR$5:$AT$60,3,FALSE))) -> 2 - Henrietta (1959–: #137); Andrew (1962–: #144) | AD101: =IF(AE101="d.s.p",_xlfn.CONCAT(AE101,"."),IF(AG101=0,"-",_xlfn.CONCAT(AG101," - ",AE101," ",AF101))) -> 1 - Honor GELL (1998 - : #137a) | AE101: =IF(ISNA(IF(K101="Boy",VLOOKUP(A101,'Grandchildren of Male Loyds'!$AQ$3:$AS$51,3,FALSE),VLOOKUP(A101,'Grandchildren of Female Loyds'!$AX$5:$AZ$63,3,FALSE))),AM101,IF(K101="Boy",VLOOKUP(A101,'Grandchildren of Male Loyds'!$AQ$3:$AS$51,3,FALSE),VLOOKUP(A101,'Grandchildren of Female Loyds'!$AX$5:$AZ$63,3,FALSE))) | AF101: =IF(ISNA(VLOOKUP(A101,'Grandchildren Loyd Daughters'!$BD$5:$BF$50,4,FALSE)),"",VLOOKUP(A101,'Grandchildren Loyd Daughters'!$BD$5:$BF$50,3,FALSE)) -> Honor GELL (1998 - : #137a) | AG101: =IF(ISNA(VLOOKUP(A101,'Grandchildren of Male Loyds'!$AQ$3:$AR$60,2,FALSE)),0,VLOOKUP(A101,'Grandchildren of Male Loyds'!$AQ$3:$AR$60,2,FALSE))+IF(ISNA(VLOOKUP(A101,'Grandchildren of Female Loyds'!$AX$5:$AY$50,2,FALSE)),0,VLOOKUP(A101,'Grandchildren of Female Loyds'!$AX$5:$AY$50,2,FALSE))+IF(ISNA(VLOOKUP(A101,'Grandchildren Loyd Daughters'!$BD$5:$BE$50,2,FALSE)),0,VLOOKUP(A101,'Grandchildren Loyd Daughters'!$BD$5:$BE$50,2,FALSE)) -> 1 | AH101: =VLOOKUP($U101,'Loyd List 1-190 - Edit'!$P$3:$AJ$220,21,FALSE) -> The Hon Bettine Henrietta KNATCHBULL-HUGESSEN (b. 15 Sep 1888, d. 9 Aug 1967) | AI101: =VLOOKUP(A101,'Updated Bios & Spouse Details'!$A$1:$J$200,7,FALSE) -> Sally Elizabeth Jane INGLIS (b. 18 Jan 1931, d. 27 Aug 2020) | AJ101: =IF(VLOOKUP($A101,'Loyd List 1-190 - Edit'!$C$1:$AQ$220,'Book Details - NO EDIT'!AJ$1,FALSE)="","",(VLOOKUP($A101,'Loyd List 1-190 - Edit'!$C$1:$AQ$220,'Book Details - NO EDIT'!AJ$1,FALSE))) -> 21248 | AK101: =VLOOKUP(A101,'Updated Bios & Spouse Details'!$A$1:$J$200,8,FALSE) -> Married Sally, at St. Peter’s, Eaton Square, London, SW1, eldest daughter of John INGLIS of West Nisbet, Jedburgh, Roxburghshire. | AL101: =VLOOKUP(A101,'Updated Bios & Spouse Details'!$A$1:$J$200,5,FALSE) -> Peter lived at Towersey Manor, Thame, Oxfordshire and was the younger son of William (1889–1947: #66). Born 18 Apr 1923. Educated Eton 1936-40. . Served in World War II as Captain, Coldstream Guards and later as Major, Coldstream Guards. Died 12 Jun 1974. Issue: 1 son, 1 daughter. | AM101: =IF(AND(LEN(H101)>0,ISNA(IF(K101="Boy",VLOOKUP(A101,'Siblings of those BORN Loyd'!$AP$3:$AQ$70,2,FALSE),VLOOKUP(A101,'Children of Female Loyds'!$AR$5:$AS$60,2,FALSE)))),"d.s.p","") | AN101: =(IF(OR(L101=0,LEN(L101)=0),"",_xlfn.CONCAT(VLOOKUP(L101,$U$3:$X$230,4,FALSE)))) -> William (1889–1947: #66) | AO101: =(IF(OR(M101=0,LEN(M101)=0),"",_xlfn.CONCAT(VLOOKUP(M101,$U$3:$X$230,4,FALSE)))) -> Harry (1861–1938: #44) | AP101: =(IF(OR(N101=0,LEN(N101)=0),"",_xlfn.CONCAT(VLOOKUP(N101,$U$3:$X$230,4,FALSE)))) -> William (1821–1885: #23) | AQ101: =(IF(OR(O101=0,LEN(O101)=0),"",_xlfn.CONCAT(VLOOKUP(O101,$U$3:$X$230,4,FALSE)))) -> Edward (1780–1863: #8) | AR101: =(IF(OR(P101=0,LEN(P101)=0),"",_xlfn.CONCAT(VLOOKUP(P101,$U$3:$X$230,4,FALSE)))) -> William (1729–1800: #1) | AS101: =(IF(OR(Q101=0,LEN(Q101)=0),"",_xlfn.CONCAT(VLOOKUP(Q101,$U$3:$X$230,4,FALSE)))) | AT101: =(IF(OR(R101=0,LEN(R101)=0),"",_xlfn.CONCAT(VLOOKUP(R101,$U$3:$X$230,4,FALSE)))) | AU101: =(IF(OR(S101=0,LEN(S101)=0),"",_xlfn.CONCAT(VLOOKUP(S101,$U$3:$X$230,4,FALSE)))) | AW101: =VLOOKUP(A101,'Updated Bios & Spouse Details'!$A$1:$J$193,6,FALSE) -> England | AX101: =VLOOKUP($A101,'Loyd List 1-190 - Edit'!$P$2:$AQ$220,AX$1,FALSE) -> 99 | AY101: =IF(ISNA(VLOOKUP(A101,'Data check lookup table'!$G$2:$V$73,AY$1,FALSE))," - ",VLOOKUP(A101,'Data check lookup table'!$G$2:$V$73,AY$1,FALSE)) -> - | AZ101: =TEXT(J101,"dd/mm/yyyy") -> 12/06/1974 | BA101: =(IF(OR(Q101=0,LEN(Q101)=0),"",_xlfn.CONCAT(", ",VLOOKUP(Q101,$U$3:$X$230,4,FALSE)))) | BB101: =(IF(OR(R101=0,LEN(R101)=0),"",_xlfn.CONCAT("; ",VLOOKUP(R101,$U$3:$X$230,4,FALSE)))) | BI101: 12/06/1974
